Workbook

Sheet Inputs & Assumptions
B1: ABS CASH FLOW MODEL — INPUTS & ASSUMPTIONS
B2: Lender Finance Europe — Corporate Loan Securitisation. All calculations are live formulas; blue cells are inputs.
A4: 1. PORTFOLIO & LOAN TERMS
B5: Number of loans | C5: 30
B6: Original principal balance per loan (EUR) | C6: 20000000 | D6: each loan identical
B7: Original pool notional (EUR) | C7: =$C$5*$C$6 -> 600000000
B8: Interest period | C8: Quarterly
B9: Asset spread over 3M EURIBOR (bps) | C9: 500 | D9: E+500bps
B10: Asset margin (decimal) | C10: =$C$9/10000 -> 0.05
B11: Interest-only period (quarters) | C11: 4 | D11: no amort in q1-4
B12: Scheduled amortisation rate / quarter | C12: 0.03 | D12: 3% of opening bal, q5 onward
B13: Original loan tenor (quarters) | C13: 28 | D13: 7 years -> matches 7y CDR
B14: Origination window (months, 1 per month) | C14: 30 | D14: staggered maturities
B15: Day-count convention | C15: 30/360 (interest = rate/4)
A17: 2. DEFAULT, RECOVERY & PREPAYMENT (BASE CASE)
B18: Recovery rate on defaulted balance | C18: 0.6 | D18: base case
B19: Recovery lag (quarters) | C19: 8 | D19: 2 years after default
B20: Constant prepayment rate CPR (annual) | C20: 0.1 | D20: base case
A22: Cumulative default term structure (B-rated, from origination)
B23: Loan year | C23: 1 | D23: 2 | E23: 3 | F23: 4 | G23: 5 | H23: 6 | I23: 7
B24: Cumulative default rate | C24: 0.0318 | D24: 0.0746 | E24: 0.1126 | F24: 0.143 | G24: 0.1667 | H24: 0.1859 | I24: 0.201
B25: Marginal annual default (= diff) | C25: =C24 -> 0.0318 | D25: =D24-C24 -> 0.0428 | E25: =E24-D24 -> 0.038 | F25: =F24-E24 -> 0.0304 | G25: =G24-F24 -> 0.0237 | H25: =H24-G24 -> 0.0192 | I25: =I24-H24 -> 0.0151
B26: Marginal quarterly default (= annual / 4) | C26: =C25/4 -> 0.00795 | D26: =D25/4 -> 0.0107 | E26: =E25/4 -> 0.0095 | F26: =F25/4 -> 0.0076 | G26: =G25/4 -> 0.005925 | H26: =H25/4 -> 0.0048 | I26: =I25/4 -> 0.003775 | K26: Applied to outstanding balance; recoveries lagged 8q
A28: 3. LIABILITY STRUCTURE & WATERFALL
B29: Senior initial LTV | C29: 0.6 | D29: attachment
B30: Junior initial LTV | C30: 0.4
B31: Max senior LTV (= senior initial +5%) | C31: =$C$29+0.05 -> 0.65 | D31: de-levering trigger
B32: Senior spread over 3M EURIBOR (bps) | C32: 200 | D32: E+200bps
B33: Senior margin (decimal) | C33: =$C$32/10000 -> 0.02
B34: Senior legal tenor (quarters) | C34: 20 | D34: 5 years
B35: Senior costs & expenses (EUR / annum) | C35: 150000
B36: Senior costs / quarter (EUR) | C36: =$C$35/4 -> 37500
B37: Senior share of principal if >=20 loans | C37: 0.7
B38: Senior share of principal if 10-19 loans | C38: 0.8
B39: Senior share of principal if <10 loans | C39: 1
A41: 4. 3-MONTH EURIBOR — SPOT & FORWARD PATH
B42: EURIBOR spot (3M, current fixing) | C42: 0.02324 | D42: Src: euribor-rates.info ~07-Jul-2026; ECB depo 2.25% eff 17-Jun-26
B43: EURIBOR mode (1 = flat at spot, 2 = forward path) | C43: 1 | D43: switch to 2 to use the editable forward vector below
B44: Note: assets (E+500) & senior (E+200) both float, so the EURIBOR level largely nets out of credit metrics.
A46: Quarterly rate vectors (columns = projection quarters)
B47: Quarter t | E47: 1 | F47: 2 | G47: 3 | H47: 4 | I47: 5 | J47: 6 | K47: 7 | L47: 8 | M47: 9 | N47: 10 | O47: 11 | P47: 12 | Q47: 13 | R47: 14 | S47: 15 | T47: 16 | U47: 17 | V47: 18 | W47: 19 | X47: 20 | Y47: 21 | Z47: 22 | AA47: 23 | AB47: 24 | AC47: 25 | AD47: 26 | AE47: 27 | AF47: 28 | AG47: 29 | AH47: 30 | AI47: 31 | AJ47: 32 | AK47: 33 | AL47: 34 | AM47: 35 | AN47: 36
B48: Period (years) | E48: =E47/4 -> 0.25 | F48: =F47/4 -> 0.5 | G48: =G47/4 -> 0.75 | H48: =H47/4 -> 1 | I48: =I47/4 -> 1.25 | J48: =J47/4 -> 1.5 | K48: =K47/4 -> 1.75 | L48: =L47/4 -> 2 | ... AN48: =AN47/4 -> 9
B49: EURIBOR forward (editable) | E49: 0.0235 | F49: 0.0235 | G49: 0.0225 | H49: 0.0222 | I49: 0.022 | J49: 0.0217 | K49: 0.0215 | L49: 0.0197 | M49: 0.018 | N49: 0.0162 | O49: 0.0145 | P49: 0.0127 | Q49: 0.02 | R49: 0.02 | S49: 0.02 | T49: 0.02 | U49: 0.02 | V49: 0.02 | W49: 0.02 | X49: 0.02 | Y49: 0.02 | Z49: 0.02 | AA49: 0.02 | AB49: 0.02 | AC49: 0.02 | AD49: 0.02 | AE49: 0.02 | AF49: 0.02 | AG49: 0.02 | AH49: 0.02 | AI49: 0.02 | AJ49: 0.02 | AK49: 0.02 | AL49: 0.02 | AM49: 0.02 | AN49: 0.02
B50: EURIBOR effective (used by model) | E50: =IF($C$43=1,$C$42,E49) -> 0.02324 | F50: =IF($C$43=1,$C$42,F49) -> 0.02324 | G50: =IF($C$43=1,$C$42,G49) -> 0.02324 | H50: =IF($C$43=1,$C$42,H49) -> 0.02324 | I50: =IF($C$43=1,$C$42,I49) -> 0.02324 | J50: =IF($C$43=1,$C$42,J49) -> 0.02324 | K50: =IF($C$43=1,$C$42,K49) -> 0.02324 | L50: =IF($C$43=1,$C$42,L49) -> 0.02324 | ... AN50: =IF($C$43=1,$C$42,AN49) -> 0.02324
B51: Asset rate (EURIBOR + asset margin) | E51: =E50+$C$10 -> 0.07324 | F51: =F50+$C$10 -> 0.07324 | G51: =G50+$C$10 -> 0.07324 | H51: =H50+$C$10 -> 0.07324 | I51: =I50+$C$10 -> 0.07324 | J51: =J50+$C$10 -> 0.07324 | K51: =K50+$C$10 -> 0.07324 | L51: =L50+$C$10 -> 0.07324 | ... AN51: =AN50+$C$10 -> 0.07324
B52: Senior rate (EURIBOR + senior margin) | E52: =E50+$C$33 -> 0.04324 | F52: =F50+$C$33 -> 0.04324 | G52: =G50+$C$33 -> 0.04324 | H52: =H50+$C$33 -> 0.04324 | I52: =I50+$C$33 -> 0.04324 | J52: =J50+$C$33 -> 0.04324 | K52: =K50+$C$33 -> 0.04324 | L52: =L50+$C$33 -> 0.04324 | ... AN52: =AN50+$C$33 -> 0.04324
A54: 5. SCENARIO SELECTOR & STRESS MULTIPLIERS
B55: Active scenario (1-4) | C55: 1 | D55: <- dropdown drives the Asset & Liability sheets
B57: Scenario | C57: Name | D57: Default mult. | E57: Recovery rate | F57: CPR (annual) | G57: Quarterly SMM
B58: 1 | C58: Base | D58: 1 | E58: 0.6 | F58: 0.1 | G58: =1-(1-F58)^(1/4) -> 0.025996254
B59: 2 | C59: Mild stress | D59: 1.25 | E59: 0.5 | F59: 0.08 | G59: =1-(1-F59)^(1/4) -> 0.020629639
B60: 3 | C60: Moderate | D60: 1.5 | E60: 0.4 | F60: 0.12 | G60: =1-(1-F60)^(1/4) -> 0.031453072
B61: 4 | C61: Severe | D61: 2 | E61: 0.3 | F61: 0.2 | G61: =1-(1-F61)^(1/4) -> 0.054258391
B63: ACTIVE default multiplier | C63: =INDEX(D58:D61,$C$55) -> 1
B64: ACTIVE recovery rate | C64: =INDEX(E58:E61,$C$55) -> 0.6
B65: ACTIVE CPR | C65: =INDEX(F58:F61,$C$55) -> 0.1
B66: ACTIVE quarterly SMM | C66: =INDEX(G58:G61,$C$55) -> 0.025996254
A68: 6. REFERENCE SINGLE-LOAN AMORTISATION SCHEDULE (per EUR 20m loan, no defaults/prepay)
B69: Loan age (q) | C69: Opening balance | D69: Scheduled amort | E69: Closing balance
B70: 0 | C70: =$C$6 -> 20000000 | D70: 0 | E70: =C70-D70 -> 20000000
B71: 1 | C71: =E70 -> 20000000 | D71: =IF(B71<=$C$11,0,IF(B71>=$C$13,C71,$C$12*C71)) -> 0 | E71: =C71-D71 -> 20000000
B72: 2 | C72: =E71 -> 20000000 | D72: =IF(B72<=$C$11,0,IF(B72>=$C$13,C72,$C$12*C72)) -> 0 | E72: =C72-D72 -> 20000000
B73: 3 | C73: =E72 -> 20000000 | D73: =IF(B73<=$C$11,0,IF(B73>=$C$13,C73,$C$12*C73)) -> 0 | E73: =C73-D73 -> 20000000
B74: 4 | C74: =E73 -> 20000000 | D74: =IF(B74<=$C$11,0,IF(B74>=$C$13,C74,$C$12*C74)) -> 0 | E74: =C74-D74 -> 20000000
B75: 5 | C75: =E74 -> 20000000 | D75: =IF(B75<=$C$11,0,IF(B75>=$C$13,C75,$C$12*C75)) -> 600000 | E75: =C75-D75 -> 19400000
B76: 6 | C76: =E75 -> 19400000 | D76: =IF(B76<=$C$11,0,IF(B76>=$C$13,C76,$C$12*C76)) -> 582000 | E76: =C76-D76 -> 18818000
B77: 7 | C77: =E76 -> 18818000 | D77: =IF(B77<=$C$11,0,IF(B77>=$C$13,C77,$C$12*C77)) -> 564540 | E77: =C77-D77 -> 18253460
B78: 8 | C78: =E77 -> 18253460 | D78: =IF(B78<=$C$11,0,IF(B78>=$C$13,C78,$C$12*C78)) -> 547603.8 | E78: =C78-D78 -> 17705856
B79: 9 | C79: =E78 -> 17705856 | D79: =IF(B79<=$C$11,0,IF(B79>=$C$13,C79,$C$12*C79)) -> 531175.69 | E79: =C79-D79 -> 17174681
B80: 10 | C80: =E79 -> 17174681 | D80: =IF(B80<=$C$11,0,IF(B80>=$C$13,C80,$C$12*C80)) -> 515240.42 | E80: =C80-D80 -> 16659440
B81: 11 | C81: =E80 -> 16659440 | D81: =IF(B81<=$C$11,0,IF(B81>=$C$13,C81,$C$12*C81)) -> 499783.2 | E81: =C81-D81 -> 16159657
B82: 12 | C82: =E81 -> 16159657 | D82: =IF(B82<=$C$11,0,IF(B82>=$C$13,C82,$C$12*C82)) -> 484789.71 | E82: =C82-D82 -> 15674867
... B98: 28 | C98: =E97 -> 9926128.3 | D98: =IF(B98<=$C$11,0,IF(B98>=$C$13,C98,$C$12*C98)) -> 9926128.3 | E98: =C98-D98 -> 0
A100: 7. LOAN-LEVEL TABLE (30 loans, staggered by origination month)
B101: Loan # | C101: Origination (months ago) | D101: Seasoning (q) = ROUND(m/3) | E101: Maturity quarter (28 - s) | F101: Current balance (EUR)
B102: 1 | C102: 1 | D102: =ROUND(C102/3,0) -> 0 | E102: =$C$13-D102 -> 28 | F102: =INDEX($E$70:$E$98,D102+1) -> 20000000
B103: 2 | C103: 2 | D103: =ROUND(C103/3,0) -> 1 | E103: =$C$13-D103 -> 27 | F103: =INDEX($E$70:$E$98,D103+1) -> 20000000
B104: 3 | C104: 3 | D104: =ROUND(C104/3,0) -> 1 | E104: =$C$13-D104 -> 27 | F104: =INDEX($E$70:$E$98,D104+1) -> 20000000
B105: 4 | C105: 4 | D105: =ROUND(C105/3,0) -> 1 | E105: =$C$13-D105 -> 27 | F105: =INDEX($E$70:$E$98,D105+1) -> 20000000
B106: 5 | C106: 5 | D106: =ROUND(C106/3,0) -> 2 | E106: =$C$13-D106 -> 26 | F106: =INDEX($E$70:$E$98,D106+1) -> 20000000
B107: 6 | C107: 6 | D107: =ROUND(C107/3,0) -> 2 | E107: =$C$13-D107 -> 26 | F107: =INDEX($E$70:$E$98,D107+1) -> 20000000
B108: 7 | C108: 7 | D108: =ROUND(C108/3,0) -> 2 | E108: =$C$13-D108 -> 26 | F108: =INDEX($E$70:$E$98,D108+1) -> 20000000
B109: 8 | C109: 8 | D109: =ROUND(C109/3,0) -> 3 | E109: =$C$13-D109 -> 25 | F109: =INDEX($E$70:$E$98,D109+1) -> 20000000
B110: 9 | C110: 9 | D110: =ROUND(C110/3,0) -> 3 | E110: =$C$13-D110 -> 25 | F110: =INDEX($E$70:$E$98,D110+1) -> 20000000
B111: 10 | C111: 10 | D111: =ROUND(C111/3,0) -> 3 | E111: =$C$13-D111 -> 25 | F111: =INDEX($E$70:$E$98,D111+1) -> 20000000
B112: 11 | C112: 11 | D112: =ROUND(C112/3,0) -> 4 | E112: =$C$13-D112 -> 24 | F112: =INDEX($E$70:$E$98,D112+1) -> 20000000
B113: 12 | C113: 12 | D113: =ROUND(C113/3,0) -> 4 | E113: =$C$13-D113 -> 24 | F113: =INDEX($E$70:$E$98,D113+1) -> 20000000
... B131: 30 | C131: 30 | D131: =ROUND(C131/3,0) -> 10 | E131: =$C$13-D131 -> 18 | F131: =INDEX($E$70:$E$98,D131+1) -> 16659440
B133: Current pool value V0 (EUR) | C133: =SUM(F102:F131) -> 5.6737487e+08
B134: Senior notional = V0 x senior LTV (EUR) | C134: =$C$133*$C$29 -> 3.4042492e+08
B135: Junior notional = V0 x junior LTV (EUR) | C135: =$C$133*$C$30 -> 2.2694995e+08
B136: Check: Senior + Junior = V0 | C136: =$C$134+$C$135-$C$133 -> 0
A138: 8. ORIGINATION COHORTS (loans grouped by identical seasoning — equivalent to loan-level since terms are identical)
B139: Cohort | C139: Seasoning s (q) | D139: Loan count n | E139: Maturity q (28-s) | F139: Initial balance/loan | G139: Cohort initial balance (EUR)
B140: 1 | C140: 0 | D140: =COUNTIF($D$102:$D$131,C140) -> 1 | E140: =$C$13-C140 -> 28 | F140: =INDEX($E$70:$E$98,C140+1) -> 20000000 | G140: =D140*F140 -> 20000000
B141: 2 | C141: 1 | D141: =COUNTIF($D$102:$D$131,C141) -> 3 | E141: =$C$13-C141 -> 27 | F141: =INDEX($E$70:$E$98,C141+1) -> 20000000 | G141: =D141*F141 -> 60000000
B142: 3 | C142: 2 | D142: =COUNTIF($D$102:$D$131,C142) -> 3 | E142: =$C$13-C142 -> 26 | F142: =INDEX($E$70:$E$98,C142+1) -> 20000000 | G142: =D142*F142 -> 60000000
B143: 4 | C143: 3 | D143: =COUNTIF($D$102:$D$131,C143) -> 3 | E143: =$C$13-C143 -> 25 | F143: =INDEX($E$70:$E$98,C143+1) -> 20000000 | G143: =D143*F143 -> 60000000
B144: 5 | C144: 4 | D144: =COUNTIF($D$102:$D$131,C144) -> 3 | E144: =$C$13-C144 -> 24 | F144: =INDEX($E$70:$E$98,C144+1) -> 20000000 | G144: =D144*F144 -> 60000000
B145: 6 | C145: 5 | D145: =COUNTIF($D$102:$D$131,C145) -> 3 | E145: =$C$13-C145 -> 23 | F145: =INDEX($E$70:$E$98,C145+1) -> 19400000 | G145: =D145*F145 -> 58200000
...

Sheet Asset Cash Flows
A1: PART 1 — ASSET CASH FLOW MODELLING
A2: Portfolio of 30 corporate loans (EUR 20m each), 3M EURIBOR + 500bps, quarterly. Values in EUR millions unless noted.
A4: STEP 2-3 CONTRACTUAL (EXPECTED) CASH FLOWS — per loan, before defaults/prepayments
A5: Loan-level projection (EUR m). Header = projection quarter. | E5: 1 | F5: 2 | G5: 3 | H5: 4 | I5: 5 | J5: 6 | K5: 7 | L5: 8 | M5: 9 | N5: 10 | O5: 11 | P5: 12 | Q5: 13 | R5: 14 | S5: 15 | T5: 16 | U5: 17 | V5: 18 | W5: 19 | X5: 20 | Y5: 21 | Z5: 22 | AA5: 23 | AB5: 24 | AC5: 25 | AD5: 26 | AE5: 27 | AF5: 28 | AG5: 29 | AH5: 30 | AI5: 31 | AJ5: 32 | AK5: 33 | AL5: 34 | AM5: 35 | AN5: 36
A6: Contractual principal due | B6: ='Inputs & Assumptions'!$B$102 -> 1 | E6: =IF(('Inputs & Assumptions'!$D$102+1)<='Inputs & Assumptions'!$C$13,INDEX('Inputs & Assumptions'!$D$70:$D$98,'Inputs & Assumptions'!$D$102+1+1),0) -> 0 | F6: =IF(('Inputs & Assumptions'!$D$102+2)<='Inputs & Assumptions'!$C$13,INDEX('Inputs & Assumptions'!$D$70:$D$98,'Inputs & Assumptions'!$D$102+2+1),0) -> 0 | G6: =IF(('Inputs & Assumptions'!$D$102+3)<='Inputs & Assumptions'!$C$13,INDEX('Inputs & Assumptions'!$D$70:$D$98,'Inputs & Assumptions'!$D$102+3+1),0) -> 0 | H6: =IF(('Inputs & Assumptions'!$D$102+4)<='Inputs & Assumptions'!$C$13,INDEX('Inputs & Assumptions'!$D$70:$D$98,'Inputs & Assumptions'!$D$102+4+1),0) -> 0 | I6: =IF(('Inputs & Assumptions'!$D$102+5)<='Inputs & Assumptions'!$C$13,INDEX('Inputs & Assumptions'!$D$70:$D$98,'Inputs & Assumptions'!$D$102+5+1),0) -> 600000 | J6: =IF(('Inputs & Assumptions'!$D$102+6)<='Inputs & Assumptions'!$C$13,INDEX('Inputs & Assumptions'!$D$70:$D$98,'Inputs & Assumptions'!$D$102+6+1),0) -> 582000 | K6: =IF(('Inputs & Assumptions'!$D$102+7)<='Inputs & Assumptions'!$C$13,INDEX('Inputs & Assumptions'!$D$70:$D$98,'Inputs & Assumptions'!$D$102+7+1),0) -> 564540 | L6: =IF(('Inputs & Assumptions'!$D$102+8)<='Inputs & Assumptions'!$C$13,INDEX('Inputs & Assumptions'!$D$70:$D$98,'Inputs & Assumptions'!$D$102+8+1),0) -> 547603.8 | M6: =IF(('Inputs & Assumptions'!$D$102+9)<='Inputs & Assumptions'!$C$13,INDEX('Inputs & Assumptions'!$D$70:$D$98,'Inputs & Assumptions'!$D$102+9+1),0) -> 531175.69 | N6: =IF(('Inputs & Assumptions'!$D$102+10)<='Inputs & Assumptions'!$C$13,INDEX('Inputs & Assumptions'!$D$70:$D$98,'Inputs & Assumptions'!$D$102+10+1),0) -> 515240.42 | O6: =IF(('Inputs & Assumptions'!$D$102+11)<='Inputs & Assumptions'!$C$13,INDEX('Inputs & Assumptions'!$D$70:$D$98,'Inputs & Assumptions'!$D$102+11+1),0) -> 499783.2 | P6: =IF(('Inputs & Assumptions'!$D$102+12)<='Inputs & Assumptions'!$C$13,INDEX('Inputs & Assumptions'!$D$70:$D$98,'Inputs & Assumptions'!$D$102+12+1),0) -> 484789.71 | Q6: =IF(('Inputs & Assumptions'!$D$102+13)<='Inputs & Assumptions'!$C$13,INDEX('Inputs & Assumptions'!$D$70:$D$98,'Inputs & Assumptions'!$D$102+13+1),0) -> 470246.02 | R6: =IF(('Inputs & Assumptions'!$D$102+14)<='Inputs & Assumptions'!$C$13,INDEX('Inputs & Assumptions'!$D$70:$D$98,'Inputs & Assumptions'!$D$102+14+1),0) -> 456138.64 | S6: =IF(('Inputs & Assumptions'!$D$102+15)<='Inputs & Assumptions'!$C$13,INDEX('Inputs & Assumptions'!$D$70:$D$98,'Inputs & Assumptions'!$D$102+15+1),0) -> 442454.48 | T6: =IF(('Inputs & Assumptions'!$D$102+16)<='Inputs & Assumptions'!$C$13,INDEX('Inputs & Assumptions'!$D$70:$D$98,'Inputs & Assumptions'!$D$102+16+1),0) -> 429180.84 | U6: =IF(('Inputs & Assumptions'!$D$102+17)<='Inputs & Assumptions'!$C$13,INDEX('Inputs & Assumptions'!$D$70:$D$98,'Inputs & Assumptions'!$D$102+17+1),0) -> 416305.42 | V6: =IF(('Inputs & Assumptions'!$D$102+18)<='Inputs & Assumptions'!$C$13,INDEX('Inputs & Assumptions'!$D$70:$D$98,'Inputs & Assumptions'!$D$102+18+1),0) -> 403816.25 | W6: =IF(('Inputs & Assumptions'!$D$102+19)<='Inputs & Assumptions'!$C$13,INDEX('Inputs & Assumptions'!$D$70:$D$98,'Inputs & Assumptions'!$D$102+19+1),0) -> 391701.77 | X6: =IF(('Inputs & Assumptions'!$D$102+20)<='Inputs & Assumptions'!$C$13,INDEX('Inputs & Assumptions'!$D$70:$D$98,'Inputs & Assumptions'!$D$102+20+1),0) -> 379950.71 | Y6: =IF(('Inputs & Assumptions'!$D$102+21)<='Inputs & Assumptions'!$C$13,INDEX('Inputs & Assumptions'!$D$70:$D$98,'Inputs & Assumptions'!$D$102+21+1),0) -> 368552.19 | Z6: =IF(('Inputs & Assumptions'!$D$102+22)<='Inputs & Assumptions'!$C$13,INDEX('Inputs & Assumptions'!$D$70:$D$98,'Inputs & Assumptions'!$D$102+22+1),0) -> 357495.63 | AA6: =IF(('Inputs & Assumptions'!$D$102+23)<='Inputs & Assumptions'!$C$13,INDEX('Inputs & Assumptions'!$D$70:$D$98,'Inputs & Assumptions'!$D$102+23+1),0) -> 346770.76 | AB6: =IF(('Inputs & Assumptions'!$D$102+24)<='Inputs & Assumptions'!$C$13,INDEX('Inputs & Assumptions'!$D$70:$D$98,'Inputs & Assumptions'!$D$102+24+1),0) -> 336367.63 | AC6: =IF(('Inputs & Assumptions'!$D$102+25)<='Inputs & Assumptions'!$C$13,INDEX('Inputs & Assumptions'!$D$70:$D$98,'Inputs & Assumptions'!$D$102+25+1),0) -> 326276.61 | AD6: =IF(('Inputs & Assumptions'!$D$102+26)<='Inputs & Assumptions'!$C$13,INDEX('Inputs & Assumptions'!$D$70:$D$98,'Inputs & Assumptions'!$D$102+26+1),0) -> 316488.31 | AE6: =IF(('Inputs & Assumptions'!$D$102+27)<='Inputs & Assumptions'!$C$13,INDEX('Inputs & Assumptions'!$D$70:$D$98,'Inputs & Assumptions'!$D$102+27+1),0) -> 306993.66 | AF6: =IF(('Inputs & Assumptions'!$D$102+28)<='Inputs & Assumptions'!$C$13,INDEX('Inputs & Assumptions'!$D$70:$D$98,'Inputs & Assumptions'!$D$102+28+1),0) -> 9926128.3 | AG6: =IF(('Inputs & Assumptions'!$D$102+29)<='Inputs & Assumptions'!$C$13,INDEX('Inputs & Assumptions'!$D$70:$D$98,'Inputs & Assumptions'!$D$102+29+1),0) -> 0 | AH6: =IF(('Inputs & Assumptions'!$D$102+30)<='Inputs & Assumptions'!$C$13,INDEX('Inputs & Assumptions'!$D$70:$D$98,'Inputs & Assumptions'!$D$102+30+1),0) -> 0 | AI6: =IF(('Inputs & Assumptions'!$D$102+31)<='Inputs & Assumptions'!$C$13,INDEX('Inputs & Assumptions'!$D$70:$D$98,'Inputs & Assumptions'!$D$102+31+1),0) -> 0 | AJ6: =IF(('Inputs & Assumptions'!$D$102+32)<='Inputs & Assumptions'!$C$13,INDEX('Inputs & Assumptions'!$D$70:$D$98,'Inputs & Assumptions'!$D$102+32+1),0) -> 0 | AK6: =IF(('Inputs & Assumptions'!$D$102+33)<='Inputs & Assumptions'!$C$13,INDEX('Inputs & Assumptions'!$D$70:$D$98,'Inputs & Assumptions'!$D$102+33+1),0) -> 0 | AL6: =IF(('Inputs & Assumptions'!$D$102+34)<='Inputs & Assumptions'!$C$13,INDEX('Inputs & Assumptions'!$D$70:$D$98,'Inputs & Assumptions'!$D$102+34+1),0) -> 0 | AM6: =IF(('Inputs & Assumptions'!$D$102+35)<='Inputs & Assumptions'!$C$13,INDEX('Inputs & Assumptions'!$D$70:$D$98,'Inputs & Assumptions'!$D$102+35+1),0) -> 0 | AN6: =IF(('Inputs & Assumptions'!$D$102+36)<='Inputs & Assumptions'!$C$13,INDEX('Inputs & Assumptions'!$D$70:$D$98,'Inputs & Assumptions'!$D$102+36+1),0) -> 0
B7: ='Inputs & Assumptions'!$B$103 -> 2 | E7: =IF(('Inputs & Assumptions'!$D$103+1)<='Inputs & Assumptions'!$C$13,INDEX('Inputs & Assumptions'!$D$70:$D$98,'Inputs & Assumptions'!$D$103+1+1),0) -> 0 | F7: =IF(('Inputs & Assumptions'!$D$103+2)<='Inputs & Assumptions'!$C$13,INDEX('Inputs & Assumptions'!$D$70:$D$98,'Inputs & Assumptions'!$D$103+2+1),0) -> 0 | G7: =IF(('Inputs & Assumptions'!$D$103+3)<='Inputs & Assumptions'!$C$13,INDEX('Inputs & Assumptions'!$D$70:$D$98,'Inputs & Assumptions'!$D$103+3+1),0) -> 0 | H7: =IF(('Inputs & Assumptions'!$D$103+4)<='Inputs & Assumptions'!$C$13,INDEX('Inputs & Assumptions'!$D$70:$D$98,'Inputs & Assumptions'!$D$103+4+1),0) -> 600000 | I7: =IF(('Inputs & Assumptions'!$D$103+5)<='Inputs & Assumptions'!$C$13,INDEX('Inputs & Assumptions'!$D$70:$D$98,'Inputs & Assumptions'!$D$103+5+1),0) -> 582000 | J7: =IF(('Inputs & Assumptions'!$D$103+6)<='Inputs & Assumptions'!$C$13,INDEX('Inputs & Assumptions'!$D$70:$D$98,'Inputs & Assumptions'!$D$103+6+1),0) -> 564540 | K7: =IF(('Inputs & Assumptions'!$D$103+7)<='Inputs & Assumptions'!$C$13,INDEX('Inputs & Assumptions'!$D$70:$D$98,'Inputs & Assumptions'!$D$103+7+1),0) -> 547603.8 | L7: =IF(('Inputs & Assumptions'!$D$103+8)<='Inputs & Assumptions'!$C$13,INDEX('Inputs & Assumptions'!$D$70:$D$98,'Inputs & Assumptions'!$D$103+8+1),0) -> 531175.69 | M7: =IF(('Inputs & Assumptions'!$D$103+9)<='Inputs & Assumptions'!$C$13,INDEX('Inputs & Assumptions'!$D$70:$D$98,'Inputs & Assumptions'!$D$103+9+1),0) -> 515240.42 | N7: =IF(('Inputs & Assumptions'!$D$103+10)<='Inputs & Assumptions'!$C$13,INDEX('Inputs & Assumptions'!$D$70:$D$98,'Inputs & Assumptions'!$D$103+10+1),0) -> 499783.2 | O7: =IF(('Inputs & Assumptions'!$D$103+11)<='Inputs & Assumptions'!$C$13,INDEX('Inputs & Assumptions'!$D$70:$D$98,'Inputs & Assumptions'!$D$103+11+1),0) -> 484789.71 | P7: =IF(('Inputs & Assumptions'!$D$103+12)<='Inputs & Assumptions'!$C$13,INDEX('Inputs & Assumptions'!$D$70:$D$98,'Inputs & Assumptions'!$D$103+12+1),0) -> 470246.02 | Q7: =IF(('Inputs & Assumptions'!$D$103+13)<='Inputs & Assumptions'!$C$13,INDEX('Inputs & Assumptions'!$D$70:$D$98,'Inputs & Assumptions'!$D$103+13+1),0) -> 456138.64 | R7: =IF(('Inputs & Assumptions'!$D$103+14)<='Inputs & Assumptions'!$C$13,INDEX('Inputs & Assumptions'!$D$70:$D$98,'Inputs & Assumptions'!$D$103+14+1),0) -> 442454.48 | S7: =IF(('Inputs & Assumptions'!$D$103+15)<='Inputs & Assumptions'!$C$13,INDEX('Inputs & Assumptions'!$D$70:$D$98,'Inputs & Assumptions'!$D$103+15+1),0) -> 429180.84 | T7: =IF(('Inputs & Assumptions'!$D$103+16)<='Inputs & Assumptions'!$C$13,INDEX('Inputs & Assumptions'!$D$70:$D$98,'Inputs & Assumptions'!$D$103+16+1),0) -> 416305.42 | U7: =IF(('Inputs & Assumptions'!$D$103+17)<='Inputs & Assumptions'!$C$13,INDEX('Inputs & Assumptions'!$D$70:$D$98,'Inputs & Assumptions'!$D$103+17+1),0) -> 403816.25 | V7: =IF(('Inputs & Assumptions'!$D$103+18)<='Inputs & Assumptions'!$C$13,INDEX('Inputs & Assumptions'!$D$70:$D$98,'Inputs & Assumptions'!$D$103+18+1),0) -> 391701.77 | W7: =IF(('Inputs & Assumptions'!$D$103+19)<='Inputs & Assumptions'!$C$13,INDEX('Inputs & Assumptions'!$D$70:$D$98,'Inputs & Assumptions'!$D$103+19+1),0) -> 379950.71 | X7: =IF(('Inputs & Assumptions'!$D$103+20)<='Inputs & Assumptions'!$C$13,INDEX('Inputs & Assumptions'!$D$70:$D$98,'Inputs & Assumptions'!$D$103+20+1),0) -> 368552.19 | Y7: =IF(('Inputs & Assumptions'!$D$103+21)<='Inputs & Assumptions'!$C$13,INDEX('Inputs & Assumptions'!$D$70:$D$98,'Inputs & Assumptions'!$D$103+21+1),0) -> 357495.63 | Z7: =IF(('Inputs & Assumptions'!$D$103+22)<='Inputs & Assumptions'!$C$13,INDEX('Inputs & Assumptions'!$D$70:$D$98,'Inputs & Assumptions'!$D$103+22+1),0) -> 346770.76 | AA7: =IF(('Inputs & Assumptions'!$D$103+23)<='Inputs & Assumptions'!$C$13,INDEX('Inputs & Assumptions'!$D$70:$D$98,'Inputs & Assumptions'!$D$103+23+1),0) -> 336367.63 | AB7: =IF(('Inputs & Assumptions'!$D$103+24)<='Inputs & Assumptions'!$C$13,INDEX('Inputs & Assumptions'!$D$70:$D$98,'Inputs & Assumptions'!$D$103+24+1),0) -> 326276.61 | AC7: =IF(('Inputs & Assumptions'!$D$103+25)<='Inputs & Assumptions'!$C$13,INDEX('Inputs & Assumptions'!$D$70:$D$98,'Inputs & Assumptions'!$D$103+25+1),0) -> 316488.31 | AD7: =IF(('Inputs & Assumptions'!$D$103+26)<='Inputs & Assumptions'!$C$13,INDEX('Inputs & Assumptions'!$D$70:$D$98,'Inputs & Assumptions'!$D$103+26+1),0) -> 306993.66 | AE7: =IF(('Inputs & Assumptions'!$D$103+27)<='Inputs & Assumptions'!$C$13,INDEX('Inputs & Assumptions'!$D$70:$D$98,'Inputs & Assumptions'!$D$103+27+1),0) -> 9926128.3 | AF7: =IF(('Inputs & Assumptions'!$D$103+28)<='Inputs & Assumptions'!$C$13,INDEX('Inputs & Assumptions'!$D$70:$D$98,'Inputs & Assumptions'!$D$103+28+1),0) -> 0 | AG7: =IF(('Inputs & Assumptions'!$D$103+29)<='Inputs & Assumptions'!$C$13,INDEX('Inputs & Assumptions'!$D$70:$D$98,'Inputs & Assumptions'!$D$103+29+1),0) -> 0 | AH7: =IF(('Inputs & Assumptions'!$D$103+30)<='Inputs & Assumptions'!$C$13,INDEX('Inputs & Assumptions'!$D$70:$D$98,'Inputs & Assumptions'!$D$103+30+1),0) -> 0 | AI7: =IF(('Inputs & Assumptions'!$D$103+31)<='Inputs & Assumptions'!$C$13,INDEX('Inputs & Assumptions'!$D$70:$D$98,'Inputs & Assumptions'!$D$103+31+1),0) -> 0 | AJ7: =IF(('Inputs & Assumptions'!$D$103+32)<='Inputs & Assumptions'!$C$13,INDEX('Inputs & Assumptions'!$D$70:$D$98,'Inputs & Assumptions'!$D$103+32+1),0) -> 0 | AK7: =IF(('Inputs & Assumptions'!$D$103+33)<='Inputs & Assumptions'!$C$13,INDEX('Inputs & Assumptions'!$D$70:$D$98,'Inputs & Assumptions'!$D$103+33+1),0) -> 0 | AL7: =IF(('Inputs & Assumptions'!$D$103+34)<='Inputs & Assumptions'!$C$13,INDEX('Inputs & Assumptions'!$D$70:$D$98,'Inputs & Assumptions'!$D$103+34+1),0) -> 0 | AM7: =IF(('Inputs & Assumptions'!$D$103+35)<='Inputs & Assumptions'!$C$13,INDEX('Inputs & Assumptions'!$D$70:$D$98,'Inputs & Assumptions'!$D$103+35+1),0) -> 0 | AN7: =IF(('Inputs & Assumptions'!$D$103+36)<='Inputs & Assumptions'!$C$13,INDEX('Inputs & Assumptions'!$D$70:$D$98,'Inputs & Assumptions'!$D$103+36+1),0) -> 0
B8: ='Inputs & Assumptions'!$B$104 -> 3 | E8: =IF(('Inputs & Assumptions'!$D$104+1)<='Inputs & Assumptions'!$C$13,INDEX('Inputs & Assumptions'!$D$70:$D$98,'Inputs & Assumptions'!$D$104+1+1),0) -> 0 | F8: =IF(('Inputs & Assumptions'!$D$104+2)<='Inputs & Assumptions'!$C$13,INDEX('Inputs & Assumptions'!$D$70:$D$98,'Inputs & Assumptions'!$D$104+2+1),0) -> 0 | G8: =IF(('Inputs & Assumptions'!$D$104+3)<='Inputs & Assumptions'!$C$13,INDEX('Inputs & Assumptions'!$D$70:$D$98,'Inputs & Assumptions'!$D$104+3+1),0) -> 0 | H8: =IF(('Inputs & Assumptions'!$D$104+4)<='Inputs & Assumptions'!$C$13,INDEX('Inputs & Assumptions'!$D$70:$D$98,'Inputs & Assumptions'!$D$104+4+1),0) -> 600000 | I8: =IF(('Inputs & Assumptions'!$D$104+5)<='Inputs & Assumptions'!$C$13,INDEX('Inputs & Assumptions'!$D$70:$D$98,'Inputs & Assumptions'!$D$104+5+1),0) -> 582000 | J8: =IF(('Inputs & Assumptions'!$D$104+6)<='Inputs & Assumptions'!$C$13,INDEX('Inputs & Assumptions'!$D$70:$D$98,'Inputs & Assumptions'!$D$104+6+1),0) -> 564540 | K8: =IF(('Inputs & Assumptions'!$D$104+7)<='Inputs & Assumptions'!$C$13,INDEX('Inputs & Assumptions'!$D$70:$D$98,'Inputs & Assumptions'!$D$104+7+1),0) -> 547603.8 | L8: =IF(('Inputs & Assumptions'!$D$104+8)<='Inputs & Assumptions'!$C$13,INDEX('Inputs & Assumptions'!$D$70:$D$98,'Inputs & Assumptions'!$D$104+8+1),0) -> 531175.69 | M8: =IF(('Inputs & Assumptions'!$D$104+9)<='Inputs & Assumptions'!$C$13,INDEX('Inputs & Assumptions'!$D$70:$D$98,'Inputs & Assumptions'!$D$104+9+1),0) -> 515240.42 | N8: =IF(('Inputs & Assumptions'!$D$104+10)<='Inputs & Assumptions'!$C$13,INDEX('Inputs & Assumptions'!$D$70:$D$98,'Inputs & Assumptions'!$D$104+10+1),0) -> 499783.2 | O8: =IF(('Inputs & Assumptions'!$D$104+11)<='Inputs & Assumptions'!$C$13,INDEX('Inputs & Assumptions'!$D$70:$D$98,'Inputs & Assumptions'!$D$104+11+1),0) -> 484789.71 | P8: =IF(('Inputs & Assumptions'!$D$104+12)<='Inputs & Assumptions'!$C$13,INDEX('Inputs & Assumptions'!$D$70:$D$98,'Inputs & Assumptions'!$D$104+12+1),0) -> 470246.02 | Q8: =IF(('Inputs & Assumptions'!$D$104+13)<='Inputs & Assumptions'!$C$13,INDEX('Inputs & Assumptions'!$D$70:$D$98,'Inputs & Assumptions'!$D$104+13+1),0) -> 456138.64 | R8: =IF(('Inputs & Assumptions'!$D$104+14)<='Inputs & Assumptions'!$C$13,INDEX('Inputs & Assumptions'!$D$70:$D$98,'Inputs & Assumptions'!$D$104+14+1),0) -> 442454.48 | S8: =IF(('Inputs & Assumptions'!$D$104+15)<='Inputs & Assumptions'!$C$13,INDEX('Inputs & Assumptions'!$D$70:$D$98,'Inputs & Assumptions'!$D$104+15+1),0) -> 429180.84 | T8: =IF(('Inputs & Assumptions'!$D$104+16)<='Inputs & Assumptions'!$C$13,INDEX('Inputs & Assumptions'!$D$70:$D$98,'Inputs & Assumptions'!$D$104+16+1),0) -> 416305.42 | U8: =IF(('Inputs & Assumptions'!$D$104+17)<='Inputs & Assumptions'!$C$13,INDEX('Inputs & Assumptions'!$D$70:$D$98,'Inputs & Assumptions'!$D$104+17+1),0) -> 403816.25 | V8: =IF(('Inputs & Assumptions'!$D$104+18)<='Inputs & Assumptions'!$C$13,INDEX('Inputs & Assumptions'!$D$70:$D$98,'Inputs & Assumptions'!$D$104+18+1),0) -> 391701.77 | W8: =IF(('Inputs & Assumptions'!$D$104+19)<='Inputs & Assumptions'!$C$13,INDEX('Inputs & Assumptions'!$D$70:$D$98,'Inputs & Assumptions'!$D$104+19+1),0) -> 379950.71 | X8: =IF(('Inputs & Assumptions'!$D$104+20)<='Inputs & Assumptions'!$C$13,INDEX('Inputs & Assumptions'!$D$70:$D$98,'Inputs & Assumptions'!$D$104+20+1),0) -> 368552.19 | Y8: =IF(('Inputs & Assumptions'!$D$104+21)<='Inputs & Assumptions'!$C$13,INDEX('Inputs & Assumptions'!$D$70:$D$98,'Inputs & Assumptions'!$D$104+21+1),0) -> 357495.63 | Z8: =IF(('Inputs & Assumptions'!$D$104+22)<='Inputs & Assumptions'!$C$13,INDEX('Inputs & Assumptions'!$D$70:$D$98,'Inputs & Assumptions'!$D$104+22+1),0) -> 346770.76 | AA8: =IF(('Inputs & Assumptions'!$D$104+23)<='Inputs & Assumptions'!$C$13,INDEX('Inputs & Assumptions'!$D$70:$D$98,'Inputs & Assumptions'!$D$104+23+1),0) -> 336367.63 | AB8: =IF(('Inputs & Assumptions'!$D$104+24)<='Inputs & Assumptions'!$C$13,INDEX('Inputs & Assumptions'!$D$70:$D$98,'Inputs & Assumptions'!$D$104+24+1),0) -> 326276.61 | AC8: =IF(('Inputs & Assumptions'!$D$104+25)<='Inputs & Assumptions'!$C$13,INDEX('Inputs & Assumptions'!$D$70:$D$98,'Inputs & Assumptions'!$D$104+25+1),0) -> 316488.31 | AD8: =IF(('Inputs & Assumptions'!$D$104+26)<='Inputs & Assumptions'!$C$13,INDEX('Inputs & Assumptions'!$D$70:$D$98,'Inputs & Assumptions'!$D$104+26+1),0) -> 306993.66 | AE8: =IF(('Inputs & Assumptions'!$D$104+27)<='Inputs & Assumptions'!$C$13,INDEX('Inputs & Assumptions'!$D$70:$D$98,'Inputs & Assumptions'!$D$104+27+1),0) -> 9926128.3 | AF8: =IF(('Inputs & Assumptions'!$D$104+28)<='Inputs & Assumptions'!$C$13,INDEX('Inputs & Assumptions'!$D$70:$D$98,'Inputs & Assumptions'!$D$104+28+1),0) -> 0 | AG8: =IF(('Inputs & Assumptions'!$D$104+29)<='Inputs & Assumptions'!$C$13,INDEX('Inputs & Assumptions'!$D$70:$D$98,'Inputs & Assumptions'!$D$104+29+1),0) -> 0 | AH8: =IF(('Inputs & Assumptions'!$D$104+30)<='Inputs & Assumptions'!$C$13,INDEX('Inputs & Assumptions'!$D$70:$D$98,'Inputs & Assumptions'!$D$104+30+1),0) -> 0 | AI8: =IF(('Inputs & Assumptions'!$D$104+31)<='Inputs & Assumptions'!$C$13,INDEX('Inputs & Assumptions'!$D$70:$D$98,'Inputs & Assumptions'!$D$104+31+1),0) -> 0 | AJ8: =IF(('Inputs & Assumptions'!$D$104+32)<='Inputs & Assumptions'!$C$13,INDEX('Inputs & Assumptions'!$D$70:$D$98,'Inputs & Assumptions'!$D$104+32+1),0) -> 0 | AK8: =IF(('Inputs & Assumptions'!$D$104+33)<='Inputs & Assumptions'!$C$13,INDEX('Inputs & Assumptions'!$D$70:$D$98,'Inputs & Assumptions'!$D$104+33+1),0) -> 0 | AL8: =IF(('Inputs & Assumptions'!$D$104+34)<='Inputs & Assumptions'!$C$13,INDEX('Inputs & Assumptions'!$D$70:$D$98,'Inputs & Assumptions'!$D$104+34+1),0) -> 0 | AM8: =IF(('Inputs & Assumptions'!$D$104+35)<='Inputs & Assumptions'!$C$13,INDEX('Inputs & Assumptions'!$D$70:$D$98,'Inputs & Assumptions'!$D$104+35+1),0) -> 0 | AN8: =IF(('Inputs & Assumptions'!$D$104+36)<='Inputs & Assumptions'!$C$13,INDEX('Inputs & Assumptions'!$D$70:$D$98,'Inputs & Assumptions'!$D$104+36+1),0) -> 0
B9: ='Inputs & Assumptions'!$B$105 -> 4 | E9: =IF(('Inputs & Assumptions'!$D$105+1)<='Inputs & Assumptions'!$C$13,INDEX('Inputs & Assumptions'!$D$70:$D$98,'Inputs & Assumptions'!$D$105+1+1),0) -> 0 | F9: =IF(('Inputs & Assumptions'!$D$105+2)<='Inputs & Assumptions'!$C$13,INDEX('Inputs & Assumptions'!$D$70:$D$98,'Inputs & Assumptions'!$D$105+2+1),0) -> 0 | G9: =IF(('Inputs & Assumptions'!$D$105+3)<='Inputs & Assumptions'!$C$13,INDEX('Inputs & Assumptions'!$D$70:$D$98,'Inputs & Assumptions'!$D$105+3+1),0) -> 0 | H9: =IF(('Inputs & Assumptions'!$D$105+4)<='Inputs & Assumptions'!$C$13,INDEX('Inputs & Assumptions'!$D$70:$D$98,'Inputs & Assumptions'!$D$105+4+1),0) -> 600000 | I9: =IF(('Inputs & Assumptions'!$D$105+5)<='Inputs & Assumptions'!$C$13,INDEX('Inputs & Assumptions'!$D$70:$D$98,'Inputs & Assumptions'!$D$105+5+1),0) -> 582000 | J9: =IF(('Inputs & Assumptions'!$D$105+6)<='Inputs & Assumptions'!$C$13,INDEX('Inputs & Assumptions'!$D$70:$D$98,'Inputs & Assumptions'!$D$105+6+1),0) -> 564540 | K9: =IF(('Inputs & Assumptions'!$D$105+7)<='Inputs & Assumptions'!$C$13,INDEX('Inputs & Assumptions'!$D$70:$D$98,'Inputs & Assumptions'!$D$105+7+1),0) -> 547603.8 | L9: =IF(('Inputs & Assumptions'!$D$105+8)<='Inputs & Assumptions'!$C$13,INDEX('Inputs & Assumptions'!$D$70:$D$98,'Inputs & Assumptions'!$D$105+8+1),0) -> 531175.69 | M9: =IF(('Inputs & Assumptions'!$D$105+9)<='Inputs & Assumptions'!$C$13,INDEX('Inputs & Assumptions'!$D$70:$D$98,'Inputs & Assumptions'!$D$105+9+1),0) -> 515240.42 | N9: =IF(('Inputs & Assumptions'!$D$105+10)<='Inputs & Assumptions'!$C$13,INDEX('Inputs & Assumptions'!$D$70:$D$98,'Inputs & Assumptions'!$D$105+10+1),0) -> 499783.2 | O9: =IF(('Inputs & Assumptions'!$D$105+11)<='Inputs & Assumptions'!$C$13,INDEX('Inputs & Assumptions'!$D$70:$D$98,'Inputs & Assumptions'!$D$105+11+1),0) -> 484789.71 | P9: =IF(('Inputs & Assumptions'!$D$105+12)<='Inputs & Assumptions'!$C$13,INDEX('Inputs & Assumptions'!$D$70:$D$98,'Inputs & Assumptions'!$D$105+12+1),0) -> 470246.02 | Q9: =IF(('Inputs & Assumptions'!$D$105+13)<='Inputs & Assumptions'!$C$13,INDEX('Inputs & Assumptions'!$D$70:$D$98,'Inputs & Assumptions'!$D$105+13+1),0) -> 456138.64 | R9: =IF(('Inputs & Assumptions'!$D$105+14)<='Inputs & Assumptions'!$C$13,INDEX('Inputs & Assumptions'!$D$70:$D$98,'Inputs & Assumptions'!$D$105+14+1),0) -> 442454.48 | S9: =IF(('Inputs & Assumptions'!$D$105+15)<='Inputs & Assumptions'!$C$13,INDEX('Inputs & Assumptions'!$D$70:$D$98,'Inputs & Assumptions'!$D$105+15+1),0) -> 429180.84 | T9: =IF(('Inputs & Assumptions'!$D$105+16)<='Inputs & Assumptions'!$C$13,INDEX('Inputs & Assumptions'!$D$70:$D$98,'Inputs & Assumptions'!$D$105+16+1),0) -> 416305.42 | U9: =IF(('Inputs & Assumptions'!$D$105+17)<='Inputs & Assumptions'!$C$13,INDEX('Inputs & Assumptions'!$D$70:$D$98,'Inputs & Assumptions'!$D$105+17+1),0) -> 403816.25 | V9: =IF(('Inputs & Assumptions'!$D$105+18)<='Inputs & Assumptions'!$C$13,INDEX('Inputs & Assumptions'!$D$70:$D$98,'Inputs & Assumptions'!$D$105+18+1),0) -> 391701.77 | W9: =IF(('Inputs & Assumptions'!$D$105+19)<='Inputs & Assumptions'!$C$13,INDEX('Inputs & Assumptions'!$D$70:$D$98,'Inputs & Assumptions'!$D$105+19+1),0) -> 379950.71 | X9: =IF(('Inputs & Assumptions'!$D$105+20)<='Inputs & Assumptions'!$C$13,INDEX('Inputs & Assumptions'!$D$70:$D$98,'Inputs & Assumptions'!$D$105+20+1),0) -> 368552.19 | Y9: =IF(('Inputs & Assumptions'!$D$105+21)<='Inputs & Assumptions'!$C$13,INDEX('Inputs & Assumptions'!$D$70:$D$98,'Inputs & Assumptions'!$D$105+21+1),0) -> 357495.63 | Z9: =IF(('Inputs & Assumptions'!$D$105+22)<='Inputs & Assumptions'!$C$13,INDEX('Inputs & Assumptions'!$D$70:$D$98,'Inputs & Assumptions'!$D$105+22+1),0) -> 346770.76 | AA9: =IF(('Inputs & Assumptions'!$D$105+23)<='Inputs & Assumptions'!$C$13,INDEX('Inputs & Assumptions'!$D$70:$D$98,'Inputs & Assumptions'!$D$105+23+1),0) -> 336367.63 | AB9: =IF(('Inputs & Assumptions'!$D$105+24)<='Inputs & Assumptions'!$C$13,INDEX('Inputs & Assumptions'!$D$70:$D$98,'Inputs & Assumptions'!$D$105+24+1),0) -> 326276.61 | AC9: =IF(('Inputs & Assumptions'!$D$105+25)<='Inputs & Assumptions'!$C$13,INDEX('Inputs & Assumptions'!$D$70:$D$98,'Inputs & Assumptions'!$D$105+25+1),0) -> 316488.31 | AD9: =IF(('Inputs & Assumptions'!$D$105+26)<='Inputs & Assumptions'!$C$13,INDEX('Inputs & Assumptions'!$D$70:$D$98,'Inputs & Assumptions'!$D$105+26+1),0) -> 306993.66 | AE9: =IF(('Inputs & Assumptions'!$D$105+27)<='Inputs & Assumptions'!$C$13,INDEX('Inputs & Assumptions'!$D$70:$D$98,'Inputs & Assumptions'!$D$105+27+1),0) -> 9926128.3 | AF9: =IF(('Inputs & Assumptions'!$D$105+28)<='Inputs & Assumptions'!$C$13,INDEX('Inputs & Assumptions'!$D$70:$D$98,'Inputs & Assumptions'!$D$105+28+1),0) -> 0 | AG9: =IF(('Inputs & Assumptions'!$D$105+29)<='Inputs & Assumptions'!$C$13,INDEX('Inputs & Assumptions'!$D$70:$D$98,'Inputs & Assumptions'!$D$105+29+1),0) -> 0 | AH9: =IF(('Inputs & Assumptions'!$D$105+30)<='Inputs & Assumptions'!$C$13,INDEX('Inputs & Assumptions'!$D$70:$D$98,'Inputs & Assumptions'!$D$105+30+1),0) -> 0 | AI9: =IF(('Inputs & Assumptions'!$D$105+31)<='Inputs & Assumptions'!$C$13,INDEX('Inputs & Assumptions'!$D$70:$D$98,'Inputs & Assumptions'!$D$105+31+1),0) -> 0 | AJ9: =IF(('Inputs & Assumptions'!$D$105+32)<='Inputs & Assumptions'!$C$13,INDEX('Inputs & Assumptions'!$D$70:$D$98,'Inputs & Assumptions'!$D$105+32+1),0) -> 0 | AK9: =IF(('Inputs & Assumptions'!$D$105+33)<='Inputs & Assumptions'!$C$13,INDEX('Inputs & Assumptions'!$D$70:$D$98,'Inputs & Assumptions'!$D$105+33+1),0) -> 0 | AL9: =IF(('Inputs & Assumptions'!$D$105+34)<='Inputs & Assumptions'!$C$13,INDEX('Inputs & Assumptions'!$D$70:$D$98,'Inputs & Assumptions'!$D$105+34+1),0) -> 0 | AM9: =IF(('Inputs & Assumptions'!$D$105+35)<='Inputs & Assumptions'!$C$13,INDEX('Inputs & Assumptions'!$D$70:$D$98,'Inputs & Assumptions'!$D$105+35+1),0) -> 0 | AN9: =IF(('Inputs & Assumptions'!$D$105+36)<='Inputs & Assumptions'!$C$13,INDEX('Inputs & Assumptions'!$D$70:$D$98,'Inputs & Assumptions'!$D$105+36+1),0) -> 0
B10: ='Inputs & Assumptions'!$B$106 -> 5 | E10: =IF(('Inputs & Assumptions'!$D$106+1)<='Inputs & Assumptions'!$C$13,INDEX('Inputs & Assumptions'!$D$70:$D$98,'Inputs & Assumptions'!$D$106+1+1),0) -> 0 | F10: =IF(('Inputs & Assumptions'!$D$106+2)<='Inputs & Assumptions'!$C$13,INDEX('Inputs & Assumptions'!$D$70:$D$98,'Inputs & Assumptions'!$D$106+2+1),0) -> 0 | G10: =IF(('Inputs & Assumptions'!$D$106+3)<='Inputs & Assumptions'!$C$13,INDEX('Inputs & Assumptions'!$D$70:$D$98,'Inputs & Assumptions'!$D$106+3+1),0) -> 600000 | H10: =IF(('Inputs & Assumptions'!$D$106+4)<='Inputs & Assumptions'!$C$13,INDEX('Inputs & Assumptions'!$D$70:$D$98,'Inputs & Assumptions'!$D$106+4+1),0) -> 582000 | I10: =IF(('Inputs & Assumptions'!$D$106+5)<='Inputs & Assumptions'!$C$13,INDEX('Inputs & Assumptions'!$D$70:$D$98,'Inputs & Assumptions'!$D$106+5+1),0) -> 564540 | J10: =IF(('Inputs & Assumptions'!$D$106+6)<='Inputs & Assumptions'!$C$13,INDEX('Inputs & Assumptions'!$D$70:$D$98,'Inputs & Assumptions'!$D$106+6+1),0) -> 547603.8 | K10: =IF(('Inputs & Assumptions'!$D$106+7)<='Inputs & Assumptions'!$C$13,INDEX('Inputs & Assumptions'!$D$70:$D$98,'Inputs & Assumptions'!$D$106+7+1),0) -> 531175.69 | L10: =IF(('Inputs & Assumptions'!$D$106+8)<='Inputs & Assumptions'!$C$13,INDEX('Inputs & Assumptions'!$D$70:$D$98,'Inputs & Assumptions'!$D$106+8+1),0) -> 515240.42 | M10: =IF(('Inputs & Assumptions'!$D$106+9)<='Inputs & Assumptions'!$C$13,INDEX('Inputs & Assumptions'!$D$70:$D$98,'Inputs & Assumptions'!$D$106+9+1),0) -> 499783.2 | N10: =IF(('Inputs & Assumptions'!$D$106+10)<='Inputs & Assumptions'!$C$13,INDEX('Inputs & Assumptions'!$D$70:$D$98,'Inputs & Assumptions'!$D$106+10+1),0) -> 484789.71 | O10: =IF(('Inputs & Assumptions'!$D$106+11)<='Inputs & Assumptions'!$C$13,INDEX('Inputs & Assumptions'!$D$70:$D$98,'Inputs & Assumptions'!$D$106+11+1),0) -> 470246.02 | P10: =IF(('Inputs & Assumptions'!$D$106+12)<='Inputs & Assumptions'!$C$13,INDEX('Inputs & Assumptions'!$D$70:$D$98,'Inputs & Assumptions'!$D$106+12+1),0) -> 456138.64 | Q10: =IF(('Inputs & Assumptions'!$D$106+13)<='Inputs & Assumptions'!$C$13,INDEX('Inputs & Assumptions'!$D$70:$D$98,'Inputs & Assumptions'!$D$106+13+1),0) -> 442454.48 | R10: =IF(('Inputs & Assumptions'!$D$106+14)<='Inputs & Assumptions'!$C$13,INDEX('Inputs & Assumptions'!$D$70:$D$98,'Inputs & Assumptions'!$D$106+14+1),0) -> 429180.84 | S10: =IF(('Inputs & Assumptions'!$D$106+15)<='Inputs & Assumptions'!$C$13,INDEX('Inputs & Assumptions'!$D$70:$D$98,'Inputs & Assumptions'!$D$106+15+1),0) -> 416305.42 | T10: =IF(('Inputs & Assumptions'!$D$106+16)<='Inputs & Assumptions'!$C$13,INDEX('Inputs & Assumptions'!$D$70:$D$98,'Inputs & Assumptions'!$D$106+16+1),0) -> 403816.25 | U10: =IF(('Inputs & Assumptions'!$D$106+17)<='Inputs & Assumptions'!$C$13,INDEX('Inputs & Assumptions'!$D$70:$D$98,'Inputs & Assumptions'!$D$106+17+1),0) -> 391701.77 | V10: =IF(('Inputs & Assumptions'!$D$106+18)<='Inputs & Assumptions'!$C$13,INDEX('Inputs & Assumptions'!$D$70:$D$98,'Inputs & Assumptions'!$D$106+18+1),0) -> 379950.71 | W10: =IF(('Inputs & Assumptions'!$D$106+19)<='Inputs & Assumptions'!$C$13,INDEX('Inputs & Assumptions'!$D$70:$D$98,'Inputs & Assumptions'!$D$106+19+1),0) -> 368552.19 | X10: =IF(('Inputs & Assumptions'!$D$106+20)<='Inputs & Assumptions'!$C$13,INDEX('Inputs & Assumptions'!$D$70:$D$98,'Inputs & Assumptions'!$D$106+20+1),0) -> 357495.63 | Y10: =IF(('Inputs & Assumptions'!$D$106+21)<='Inputs & Assumptions'!$C$13,INDEX('Inputs & Assumptions'!$D$70:$D$98,'Inputs & Assumptions'!$D$106+21+1),0) -> 346770.76 | Z10: =IF(('Inputs & Assumptions'!$D$106+22)<='Inputs & Assumptions'!$C$13,INDEX('Inputs & Assumptions'!$D$70:$D$98,'Inputs & Assumptions'!$D$106+22+1),0) -> 336367.63 | AA10: =IF(('Inputs & Assumptions'!$D$106+23)<='Inputs & Assumptions'!$C$13,INDEX('Inputs & Assumptions'!$D$70:$D$98,'Inputs & Assumptions'!$D$106+23+1),0) -> 326276.61 | AB10: =IF(('Inputs & Assumptions'!$D$106+24)<='Inputs & Assumptions'!$C$13,INDEX('Inputs & Assumptions'!$D$70:$D$98,'Inputs & Assumptions'!$D$106+24+1),0) -> 316488.31 | AC10: =IF(('Inputs & Assumptions'!$D$106+25)<='Inputs & Assumptions'!$C$13,INDEX('Inputs & Assumptions'!$D$70:$D$98,'Inputs & Assumptions'!$D$106+25+1),0) -> 306993.66 | AD10: =IF(('Inputs & Assumptions'!$D$106+26)<='Inputs & Assumptions'!$C$13,INDEX('Inputs & Assumptions'!$D$70:$D$98,'Inputs & Assumptions'!$D$106+26+1),0) -> 9926128.3 | AE10: =IF(('Inputs & Assumptions'!$D$106+27)<='Inputs & Assumptions'!$C$13,INDEX('Inputs & Assumptions'!$D$70:$D$98,'Inputs & Assumptions'!$D$106+27+1),0) -> 0 | AF10: =IF(('Inputs & Assumptions'!$D$106+28)<='Inputs & Assumptions'!$C$13,INDEX('Inputs & Assumptions'!$D$70:$D$98,'Inputs & Assumptions'!$D$106+28+1),0) -> 0 | AG10: =IF(('Inputs & Assumptions'!$D$106+29)<='Inputs & Assumptions'!$C$13,INDEX('Inputs & Assumptions'!$D$70:$D$98,'Inputs & Assumptions'!$D$106+29+1),0) -> 0 | AH10: =IF(('Inputs & Assumptions'!$D$106+30)<='Inputs & Assumptions'!$C$13,INDEX('Inputs & Assumptions'!$D$70:$D$98,'Inputs & Assumptions'!$D$106+30+1),0) -> 0 | AI10: =IF(('Inputs & Assumptions'!$D$106+31)<='Inputs & Assumptions'!$C$13,INDEX('Inputs & Assumptions'!$D$70:$D$98,'Inputs & Assumptions'!$D$106+31+1),0) -> 0 | AJ10: =IF(('Inputs & Assumptions'!$D$106+32)<='Inputs & Assumptions'!$C$13,INDEX('Inputs & Assumptions'!$D$70:$D$98,'Inputs & Assumptions'!$D$106+32+1),0) -> 0 | AK10: =IF(('Inputs & Assumptions'!$D$106+33)<='Inputs & Assumptions'!$C$13,INDEX('Inputs & Assumptions'!$D$70:$D$98,'Inputs & Assumptions'!$D$106+33+1),0) -> 0 | AL10: =IF(('Inputs & Assumptions'!$D$106+34)<='Inputs & Assumptions'!$C$13,INDEX('Inputs & Assumptions'!$D$70:$D$98,'Inputs & Assumptions'!$D$106+34+1),0) -> 0 | AM10: =IF(('Inputs & Assumptions'!$D$106+35)<='Inputs & Assumptions'!$C$13,INDEX('Inputs & Assumptions'!$D$70:$D$98,'Inputs & Assumptions'!$D$106+35+1),0) -> 0 | AN10: =IF(('Inputs & Assumptions'!$D$106+36)<='Inputs & Assumptions'!$C$13,INDEX('Inputs & Assumptions'!$D$70:$D$98,'Inputs & Assumptions'!$D$106+36+1),0) -> 0
B11: ='Inputs & Assumptions'!$B$107 -> 6 | E11: =IF(('Inputs & Assumptions'!$D$107+1)<='Inputs & Assumptions'!$C$13,INDEX('Inputs & Assumptions'!$D$70:$D$98,'Inputs & Assumptions'!$D$107+1+1),0) -> 0 | F11: =IF(('Inputs & Assumptions'!$D$107+2)<='Inputs & Assumptions'!$C$13,INDEX('Inputs & Assumptions'!$D$70:$D$98,'Inputs & Assumptions'!$D$107+2+1),0) -> 0 | G11: =IF(('Inputs & Assumptions'!$D$107+3)<='Inputs & Assumptions'!$C$13,INDEX('Inputs & Assumptions'!$D$70:$D$98,'Inputs & Assumptions'!$D$107+3+1),0) -> 600000 | H11: =IF(('Inputs & Assumptions'!$D$107+4)<='Inputs & Assumptions'!$C$13,INDEX('Inputs & Assumptions'!$D$70:$D$98,'Inputs & Assumptions'!$D$107+4+1),0) -> 582000 | I11: =IF(('Inputs & Assumptions'!$D$107+5)<='Inputs & Assumptions'!$C$13,INDEX('Inputs & Assumptions'!$D$70:$D$98,'Inputs & Assumptions'!$D$107+5+1),0) -> 564540 | J11: =IF(('Inputs & Assumptions'!$D$107+6)<='Inputs & Assumptions'!$C$13,INDEX('Inputs & Assumptions'!$D$70:$D$98,'Inputs & Assumptions'!$D$107+6+1),0) -> 547603.8 | K11: =IF(('Inputs & Assumptions'!$D$107+7)<='Inputs & Assumptions'!$C$13,INDEX('Inputs & Assumptions'!$D$70:$D$98,'Inputs & Assumptions'!$D$107+7+1),0) -> 531175.69 | L11: =IF(('Inputs & Assumptions'!$D$107+8)<='Inputs & Assumptions'!$C$13,INDEX('Inputs & Assumptions'!$D$70:$D$98,'Inputs & Assumptions'!$D$107+8+1),0) -> 515240.42 | M11: =IF(('Inputs & Assumptions'!$D$107+9)<='Inputs & Assumptions'!$C$13,INDEX('Inputs & Assumptions'!$D$70:$D$98,'Inputs & Assumptions'!$D$107+9+1),0) -> 499783.2 | N11: =IF(('Inputs & Assumptions'!$D$107+10)<='Inputs & Assumptions'!$C$13,INDEX('Inputs & Assumptions'!$D$70:$D$98,'Inputs & Assumptions'!$D$107+10+1),0) -> 484789.71 | O11: =IF(('Inputs & Assumptions'!$D$107+11)<='Inputs & Assumptions'!$C$13,INDEX('Inputs & Assumptions'!$D$70:$D$98,'Inputs & Assumptions'!$D$107+11+1),0) -> 470246.02 | P11: =IF(('Inputs & Assumptions'!$D$107+12)<='Inputs & Assumptions'!$C$13,INDEX('Inputs & Assumptions'!$D$70:$D$98,'Inputs & Assumptions'!$D$107+12+1),0) -> 456138.64 | Q11: =IF(('Inputs & Assumptions'!$D$107+13)<='Inputs & Assumptions'!$C$13,INDEX('Inputs & Assumptions'!$D$70:$D$98,'Inputs & Assumptions'!$D$107+13+1),0) -> 442454.48 | R11: =IF(('Inputs & Assumptions'!$D$107+14)<='Inputs & Assumptions'!$C$13,INDEX('Inputs & Assumptions'!$D$70:$D$98,'Inputs & Assumptions'!$D$107+14+1),0) -> 429180.84 | S11: =IF(('Inputs & Assumptions'!$D$107+15)<='Inputs & Assumptions'!$C$13,INDEX('Inputs & Assumptions'!$D$70:$D$98,'Inputs & Assumptions'!$D$107+15+1),0) -> 416305.42 | T11: =IF(('Inputs & Assumptions'!$D$107+16)<='Inputs & Assumptions'!$C$13,INDEX('Inputs & Assumptions'!$D$70:$D$98,'Inputs & Assumptions'!$D$107+16+1),0) -> 403816.25 | U11: =IF(('Inputs & Assumptions'!$D$107+17)<='Inputs & Assumptions'!$C$13,INDEX('Inputs & Assumptions'!$D$70:$D$98,'Inputs & Assumptions'!$D$107+17+1),0) -> 391701.77 | V11: =IF(('Inputs & Assumptions'!$D$107+18)<='Inputs & Assumptions'!$C$13,INDEX('Inputs & Assumptions'!$D$70:$D$98,'Inputs & Assumptions'!$D$107+18+1),0) -> 379950.71 | W11: =IF(('Inputs & Assumptions'!$D$107+19)<='Inputs & Assumptions'!$C$13,INDEX('Inputs & Assumptions'!$D$70:$D$98,'Inputs & Assumptions'!$D$107+19+1),0) -> 368552.19 | X11: =IF(('Inputs & Assumptions'!$D$107+20)<='Inputs & Assumptions'!$C$13,INDEX('Inputs & Assumptions'!$D$70:$D$98,'Inputs & Assumptions'!$D$107+20+1),0) -> 357495.63 | Y11: =IF(('Inputs & Assumptions'!$D$107+21)<='Inputs & Assumptions'!$C$13,INDEX('Inputs & Assumptions'!$D$70:$D$98,'Inputs & Assumptions'!$D$107+21+1),0) -> 346770.76 | Z11: =IF(('Inputs & Assumptions'!$D$107+22)<='Inputs & Assumptions'!$C$13,INDEX('Inputs & Assumptions'!$D$70:$D$98,'Inputs & Assumptions'!$D$107+22+1),0) -> 336367.63 | AA11: =IF(('Inputs & Assumptions'!$D$107+23)<='Inputs & Assumptions'!$C$13,INDEX('Inputs & Assumptions'!$D$70:$D$98,'Inputs & Assumptions'!$D$107+23+1),0) -> 326276.61 | AB11: =IF(('Inputs & Assumptions'!$D$107+24)<='Inputs & Assumptions'!$C$13,INDEX('Inputs & Assumptions'!$D$70:$D$98,'Inputs & Assumptions'!$D$107+24+1),0) -> 316488.31 | AC11: =IF(('Inputs & Assumptions'!$D$107+25)<='Inputs & Assumptions'!$C$13,INDEX('Inputs & Assumptions'!$D$70:$D$98,'Inputs & Assumptions'!$D$107+25+1),0) -> 306993.66 | AD11: =IF(('Inputs & Assumptions'!$D$107+26)<='Inputs & Assumptions'!$C$13,INDEX('Inputs & Assumptions'!$D$70:$D$98,'Inputs & Assumptions'!$D$107+26+1),0) -> 9926128.3 | AE11: =IF(('Inputs & Assumptions'!$D$107+27)<='Inputs & Assumptions'!$C$13,INDEX('Inputs & Assumptions'!$D$70:$D$98,'Inputs & Assumptions'!$D$107+27+1),0) -> 0 | AF11: =IF(('Inputs & Assumptions'!$D$107+28)<='Inputs & Assumptions'!$C$13,INDEX('Inputs & Assumptions'!$D$70:$D$98,'Inputs & Assumptions'!$D$107+28+1),0) -> 0 | AG11: =IF(('Inputs & Assumptions'!$D$107+29)<='Inputs & Assumptions'!$C$13,INDEX('Inputs & Assumptions'!$D$70:$D$98,'Inputs & Assumptions'!$D$107+29+1),0) -> 0 | AH11: =IF(('Inputs & Assumptions'!$D$107+30)<='Inputs & Assumptions'!$C$13,INDEX('Inputs & Assumptions'!$D$70:$D$98,'Inputs & Assumptions'!$D$107+30+1),0) -> 0 | AI11: =IF(('Inputs & Assumptions'!$D$107+31)<='Inputs & Assumptions'!$C$13,INDEX('Inputs & Assumptions'!$D$70:$D$98,'Inputs & Assumptions'!$D$107+31+1),0) -> 0 | AJ11: =IF(('Inputs & Assumptions'!$D$107+32)<='Inputs & Assumptions'!$C$13,INDEX('Inputs & Assumptions'!$D$70:$D$98,'Inputs & Assumptions'!$D$107+32+1),0) -> 0 | AK11: =IF(('Inputs & Assumptions'!$D$107+33)<='Inputs & Assumptions'!$C$13,INDEX('Inputs & Assumptions'!$D$70:$D$98,'Inputs & Assumptions'!$D$107+33+1),0) -> 0 | AL11: =IF(('Inputs & Assumptions'!$D$107+34)<='Inputs & Assumptions'!$C$13,INDEX('Inputs & Assumptions'!$D$70:$D$98,'Inputs & Assumptions'!$D$107+34+1),0) -> 0 | AM11: =IF(('Inputs & Assumptions'!$D$107+35)<='Inputs & Assumptions'!$C$13,INDEX('Inputs & Assumptions'!$D$70:$D$98,'Inputs & Assumptions'!$D$107+35+1),0) -> 0 | AN11: =IF(('Inputs & Assumptions'!$D$107+36)<='Inputs & Assumptions'!$C$13,INDEX('Inputs & Assumptions'!$D$70:$D$98,'Inputs & Assumptions'!$D$107+36+1),0) -> 0
B12: ='Inputs & Assumptions'!$B$108 -> 7 | E12: =IF(('Inputs & Assumptions'!$D$108+1)<='Inputs & Assumptions'!$C$13,INDEX('Inputs & Assumptions'!$D$70:$D$98,'Inputs & Assumptions'!$D$108+1+1),0) -> 0 | F12: =IF(('Inputs & Assumptions'!$D$108+2)<='Inputs & Assumptions'!$C$13,INDEX('Inputs & Assumptions'!$D$70:$D$98,'Inputs & Assumptions'!$D$108+2+1),0) -> 0 | G12: =IF(('Inputs & Assumptions'!$D$108+3)<='Inputs & Assumptions'!$C$13,INDEX('Inputs & Assumptions'!$D$70:$D$98,'Inputs & Assumptions'!$D$108+3+1),0) -> 600000 | H12: =IF(('Inputs & Assumptions'!$D$108+4)<='Inputs & Assumptions'!$C$13,INDEX('Inputs & Assumptions'!$D$70:$D$98,'Inputs & Assumptions'!$D$108+4+1),0) -> 582000 | I12: =IF(('Inputs & Assumptions'!$D$108+5)<='Inputs & Assumptions'!$C$13,INDEX('Inputs & Assumptions'!$D$70:$D$98,'Inputs & Assumptions'!$D$108+5+1),0) -> 564540 | J12: =IF(('Inputs & Assumptions'!$D$108+6)<='Inputs & Assumptions'!$C$13,INDEX('Inputs & Assumptions'!$D$70:$D$98,'Inputs & Assumptions'!$D$108+6+1),0) -> 547603.8 | K12: =IF(('Inputs & Assumptions'!$D$108+7)<='Inputs & Assumptions'!$C$13,INDEX('Inputs & Assumptions'!$D$70:$D$98,'Inputs & Assumptions'!$D$108+7+1),0) -> 531175.69 | L12: =IF(('Inputs & Assumptions'!$D$108+8)<='Inputs & Assumptions'!$C$13,INDEX('Inputs & Assumptions'!$D$70:$D$98,'Inputs & Assumptions'!$D$108+8+1),0) -> 515240.42 | M12: =IF(('Inputs & Assumptions'!$D$108+9)<='Inputs & Assumptions'!$C$13,INDEX('Inputs & Assumptions'!$D$70:$D$98,'Inputs & Assumptions'!$D$108+9+1),0) -> 499783.2 | N12: =IF(('Inputs & Assumptions'!$D$108+10)<='Inputs & Assumptions'!$C$13,INDEX('Inputs & Assumptions'!$D$70:$D$98,'Inputs & Assumptions'!$D$108+10+1),0) -> 484789.71 | O12: =IF(('Inputs & Assumptions'!$D$108+11)<='Inputs & Assumptions'!$C$13,INDEX('Inputs & Assumptions'!$D$70:$D$98,'Inputs & Assumptions'!$D$108+11+1),0) -> 470246.02 | P12: =IF(('Inputs & Assumptions'!$D$108+12)<='Inputs & Assumptions'!$C$13,INDEX('Inputs & Assumptions'!$D$70:$D$98,'Inputs & Assumptions'!$D$108+12+1),0) -> 456138.64 | Q12: =IF(('Inputs & Assumptions'!$D$108+13)<='Inputs & Assumptions'!$C$13,INDEX('Inputs & Assumptions'!$D$70:$D$98,'Inputs & Assumptions'!$D$108+13+1),0) -> 442454.48 | R12: =IF(('Inputs & Assumptions'!$D$108+14)<='Inputs & Assumptions'!$C$13,INDEX('Inputs & Assumptions'!$D$70:$D$98,'Inputs & Assumptions'!$D$108+14+1),0) -> 429180.84 | S12: =IF(('Inputs & Assumptions'!$D$108+15)<='Inputs & Assumptions'!$C$13,INDEX('Inputs & Assumptions'!$D$70:$D$98,'Inputs & Assumptions'!$D$108+15+1),0) -> 416305.42 | T12: =IF(('Inputs & Assumptions'!$D$108+16)<='Inputs & Assumptions'!$C$13,INDEX('Inputs & Assumptions'!$D$70:$D$98,'Inputs & Assumptions'!$D$108+16+1),0) -> 403816.25 | U12: =IF(('Inputs & Assumptions'!$D$108+17)<='Inputs & Assumptions'!$C$13,INDEX('Inputs & Assumptions'!$D$70:$D$98,'Inputs & Assumptions'!$D$108+17+1),0) -> 391701.77 | V12: =IF(('Inputs & Assumptions'!$D$108+18)<='Inputs & Assumptions'!$C$13,INDEX('Inputs & Assumptions'!$D$70:$D$98,'Inputs & Assumptions'!$D$108+18+1),0) -> 379950.71 | W12: =IF(('Inputs & Assumptions'!$D$108+19)<='Inputs & Assumptions'!$C$13,INDEX('Inputs & Assumptions'!$D$70:$D$98,'Inputs & Assumptions'!$D$108+19+1),0) -> 368552.19 | X12: =IF(('Inputs & Assumptions'!$D$108+20)<='Inputs & Assumptions'!$C$13,INDEX('Inputs & Assumptions'!$D$70:$D$98,'Inputs & Assumptions'!$D$108+20+1),0) -> 357495.63 | Y12: =IF(('Inputs & Assumptions'!$D$108+21)<='Inputs & Assumptions'!$C$13,INDEX('Inputs & Assumptions'!$D$70:$D$98,'Inputs & Assumptions'!$D$108+21+1),0) -> 346770.76 | Z12: =IF(('Inputs & Assumptions'!$D$108+22)<='Inputs & Assumptions'!$C$13,INDEX('Inputs & Assumptions'!$D$70:$D$98,'Inputs & Assumptions'!$D$108+22+1),0) -> 336367.63 | AA12: =IF(('Inputs & Assumptions'!$D$108+23)<='Inputs & Assumptions'!$C$13,INDEX('Inputs & Assumptions'!$D$70:$D$98,'Inputs & Assumptions'!$D$108+23+1),0) -> 326276.61 | AB12: =IF(('Inputs & Assumptions'!$D$108+24)<='Inputs & Assumptions'!$C$13,INDEX('Inputs & Assumptions'!$D$70:$D$98,'Inputs & Assumptions'!$D$108+24+1),0) -> 316488.31 | AC12: =IF(('Inputs & Assumptions'!$D$108+25)<='Inputs & Assumptions'!$C$13,INDEX('Inputs & Assumptions'!$D$70:$D$98,'Inputs & Assumptions'!$D$108+25+1),0) -> 306993.66 | AD12: =IF(('Inputs & Assumptions'!$D$108+26)<='Inputs & Assumptions'!$C$13,INDEX('Inputs & Assumptions'!$D$70:$D$98,'Inputs & Assumptions'!$D$108+26+1),0) -> 9926128.3 | AE12: =IF(('Inputs & Assumptions'!$D$108+27)<='Inputs & Assumptions'!$C$13,INDEX('Inputs & Assumptions'!$D$70:$D$98,'Inputs & Assumptions'!$D$108+27+1),0) -> 0 | AF12: =IF(('Inputs & Assumptions'!$D$108+28)<='Inputs & Assumptions'!$C$13,INDEX('Inputs & Assumptions'!$D$70:$D$98,'Inputs & Assumptions'!$D$108+28+1),0) -> 0 | AG12: =IF(('Inputs & Assumptions'!$D$108+29)<='Inputs & Assumptions'!$C$13,INDEX('Inputs & Assumptions'!$D$70:$D$98,'Inputs & Assumptions'!$D$108+29+1),0) -> 0 | AH12: =IF(('Inputs & Assumptions'!$D$108+30)<='Inputs & Assumptions'!$C$13,INDEX('Inputs & Assumptions'!$D$70:$D$98,'Inputs & Assumptions'!$D$108+30+1),0) -> 0 | AI12: =IF(('Inputs & Assumptions'!$D$108+31)<='Inputs & Assumptions'!$C$13,INDEX('Inputs & Assumptions'!$D$70:$D$98,'Inputs & Assumptions'!$D$108+31+1),0) -> 0 | AJ12: =IF(('Inputs & Assumptions'!$D$108+32)<='Inputs & Assumptions'!$C$13,INDEX('Inputs & Assumptions'!$D$70:$D$98,'Inputs & Assumptions'!$D$108+32+1),0) -> 0 | AK12: =IF(('Inputs & Assumptions'!$D$108+33)<='Inputs & Assumptions'!$C$13,INDEX('Inputs & Assumptions'!$D$70:$D$98,'Inputs & Assumptions'!$D$108+33+1),0) -> 0 | AL12: =IF(('Inputs & Assumptions'!$D$108+34)<='Inputs & Assumptions'!$C$13,INDEX('Inputs & Assumptions'!$D$70:$D$98,'Inputs & Assumptions'!$D$108+34+1),0) -> 0 | AM12: =IF(('Inputs & Assumptions'!$D$108+35)<='Inputs & Assumptions'!$C$13,INDEX('Inputs & Assumptions'!$D$70:$D$98,'Inputs & Assumptions'!$D$108+35+1),0) -> 0 | AN12: =IF(('Inputs & Assumptions'!$D$108+36)<='Inputs & Assumptions'!$C$13,INDEX('Inputs & Assumptions'!$D$70:$D$98,'Inputs & Assumptions'!$D$108+36+1),0) -> 0
B13: ='Inputs & Assumptions'!$B$109 -> 8 | E13: =IF(('Inputs & Assumptions'!$D$109+1)<='Inputs & Assumptions'!$C$13,INDEX('Inputs & Assumptions'!$D$70:$D$98,'Inputs & Assumptions'!$D$109+1+1),0) -> 0 | F13: =IF(('Inputs & Assumptions'!$D$109+2)<='Inputs & Assumptions'!$C$13,INDEX('Inputs & Assumptions'!$D$70:$D$98,'Inputs & Assumptions'!$D$109+2+1),0) -> 600000 | G13: =IF(('Inputs & Assumptions'!$D$109+3)<='Inputs & Assumptions'!$C$13,INDEX('Inputs & Assumptions'!$D$70:$D$98,'Inputs & Assumptions'!$D$109+3+1),0) -> 582000 | H13: =IF(('Inputs & Assumptions'!$D$109+4)<='Inputs & Assumptions'!$C$13,INDEX('Inputs & Assumptions'!$D$70:$D$98,'Inputs & Assumptions'!$D$109+4+1),0) -> 564540 | I13: =IF(('Inputs & Assumptions'!$D$109+5)<='Inputs & Assumptions'!$C$13,INDEX('Inputs & Assumptions'!$D$70:$D$98,'Inputs & Assumptions'!$D$109+5+1),0) -> 547603.8 | J13: =IF(('Inputs & Assumptions'!$D$109+6)<='Inputs & Assumptions'!$C$13,INDEX('Inputs & Assumptions'!$D$70:$D$98,'Inputs & Assumptions'!$D$109+6+1),0) -> 531175.69 | K13: =IF(('Inputs & Assumptions'!$D$109+7)<='Inputs & Assumptions'!$C$13,INDEX('Inputs & Assumptions'!$D$70:$D$98,'Inputs & Assumptions'!$D$109+7+1),0) -> 515240.42 | L13: =IF(('Inputs & Assumptions'!$D$109+8)<='Inputs & Assumptions'!$C$13,INDEX('Inputs & Assumptions'!$D$70:$D$98,'Inputs & Assumptions'!$D$109+8+1),0) -> 499783.2 | M13: =IF(('Inputs & Assumptions'!$D$109+9)<='Inputs & Assumptions'!$C$13,INDEX('Inputs & Assumptions'!$D$70:$D$98,'Inputs & Assumptions'!$D$109+9+1),0) -> 484789.71 | N13: =IF(('Inputs & Assumptions'!$D$109+10)<='Inputs & Assumptions'!$C$13,INDEX('Inputs & Assumptions'!$D$70:$D$98,'Inputs & Assumptions'!$D$109+10+1),0) -> 470246.02 | O13: =IF(('Inputs & Assumptions'!$D$109+11)<='Inputs & Assumptions'!$C$13,INDEX('Inputs & Assumptions'!$D$70:$D$98,'Inputs & Assumptions'!$D$109+11+1),0) -> 456138.64 | P13: =IF(('Inputs & Assumptions'!$D$109+12)<='Inputs & Assumptions'!$C$13,INDEX('Inputs & Assumptions'!$D$70:$D$98,'Inputs & Assumptions'!$D$109+12+1),0) -> 442454.48 | Q13: =IF(('Inputs & Assumptions'!$D$109+13)<='Inputs & Assumptions'!$C$13,INDEX('Inputs & Assumptions'!$D$70:$D$98,'Inputs & Assumptions'!$D$109+13+1),0) -> 429180.84 | R13: =IF(('Inputs & Assumptions'!$D$109+14)<='Inputs & Assumptions'!$C$13,INDEX('Inputs & Assumptions'!$D$70:$D$98,'Inputs & Assumptions'!$D$109+14+1),0) -> 416305.42 | S13: =IF(('Inputs & Assumptions'!$D$109+15)<='Inputs & Assumptions'!$C$13,INDEX('Inputs & Assumptions'!$D$70:$D$98,'Inputs & Assumptions'!$D$109+15+1),0) -> 403816.25 | T13: =IF(('Inputs & Assumptions'!$D$109+16)<='Inputs & Assumptions'!$C$13,INDEX('Inputs & Assumptions'!$D$70:$D$98,'Inputs & Assumptions'!$D$109+16+1),0) -> 391701.77 | U13: =IF(('Inputs & Assumptions'!$D$109+17)<='Inputs & Assumptions'!$C$13,INDEX('Inputs & Assumptions'!$D$70:$D$98,'Inputs & Assumptions'!$D$109+17+1),0) -> 379950.71 | V13: =IF(('Inputs & Assumptions'!$D$109+18)<='Inputs & Assumptions'!$C$13,INDEX('Inputs & Assumptions'!$D$70:$D$98,'Inputs & Assumptions'!$D$109+18+1),0) -> 368552.19 | W13: =IF(('Inputs & Assumptions'!$D$109+19)<='Inputs & Assumptions'!$C$13,INDEX('Inputs & Assumptions'!$D$70:$D$98,'Inputs & Assumptions'!$D$109+19+1),0) -> 357495.63 | X13: =IF(('Inputs & Assumptions'!$D$109+20)<='Inputs & Assumptions'!$C$13,INDEX('Inputs & Assumptions'!$D$70:$D$98,'Inputs & Assumptions'!$D$109+20+1),0) -> 346770.76 | Y13: =IF(('Inputs & Assumptions'!$D$109+21)<='Inputs & Assumptions'!$C$13,INDEX('Inputs & Assumptions'!$D$70:$D$98,'Inputs & Assumptions'!$D$109+21+1),0) -> 336367.63 | Z13: =IF(('Inputs & Assumptions'!$D$109+22)<='Inputs & Assumptions'!$C$13,INDEX('Inputs & Assumptions'!$D$70:$D$98,'Inputs & Assumptions'!$D$109+22+1),0) -> 326276.61 | AA13: =IF(('Inputs & Assumptions'!$D$109+23)<='Inputs & Assumptions'!$C$13,INDEX('Inputs & Assumptions'!$D$70:$D$98,'Inputs & Assumptions'!$D$109+23+1),0) -> 316488.31 | AB13: =IF(('Inputs & Assumptions'!$D$109+24)<='Inputs & Assumptions'!$C$13,INDEX('Inputs & Assumptions'!$D$70:$D$98,'Inputs & Assumptions'!$D$109+24+1),0) -> 306993.66 | AC13: =IF(('Inputs & Assumptions'!$D$109+25)<='Inputs & Assumptions'!$C$13,INDEX('Inputs & Assumptions'!$D$70:$D$98,'Inputs & Assumptions'!$D$109+25+1),0) -> 9926128.3 | AD13: =IF(('Inputs & Assumptions'!$D$109+26)<='Inputs & Assumptions'!$C$13,INDEX('Inputs & Assumptions'!$D$70:$D$98,'Inputs & Assumptions'!$D$109+26+1),0) -> 0 | AE13: =IF(('Inputs & Assumptions'!$D$109+27)<='Inputs & Assumptions'!$C$13,INDEX('Inputs & Assumptions'!$D$70:$D$98,'Inputs & Assumptions'!$D$109+27+1),0) -> 0 | AF13: =IF(('Inputs & Assumptions'!$D$109+28)<='Inputs & Assumptions'!$C$13,INDEX('Inputs & Assumptions'!$D$70:$D$98,'Inputs & Assumptions'!$D$109+28+1),0) -> 0 | AG13: =IF(('Inputs & Assumptions'!$D$109+29)<='Inputs & Assumptions'!$C$13,INDEX('Inputs & Assumptions'!$D$70:$D$98,'Inputs & Assumptions'!$D$109+29+1),0) -> 0 | AH13: =IF(('Inputs & Assumptions'!$D$109+30)<='Inputs & Assumptions'!$C$13,INDEX('Inputs & Assumptions'!$D$70:$D$98,'Inputs & Assumptions'!$D$109+30+1),0) -> 0 | AI13: =IF(('Inputs & Assumptions'!$D$109+31)<='Inputs & Assumptions'!$C$13,INDEX('Inputs & Assumptions'!$D$70:$D$98,'Inputs & Assumptions'!$D$109+31+1),0) -> 0 | AJ13: =IF(('Inputs & Assumptions'!$D$109+32)<='Inputs & Assumptions'!$C$13,INDEX('Inputs & Assumptions'!$D$70:$D$98,'Inputs & Assumptions'!$D$109+32+1),0) -> 0 | AK13: =IF(('Inputs & Assumptions'!$D$109+33)<='Inputs & Assumptions'!$C$13,INDEX('Inputs & Assumptions'!$D$70:$D$98,'Inputs & Assumptions'!$D$109+33+1),0) -> 0 | AL13: =IF(('Inputs & Assumptions'!$D$109+34)<='Inputs & Assumptions'!$C$13,INDEX('Inputs & Assumptions'!$D$70:$D$98,'Inputs & Assumptions'!$D$109+34+1),0) -> 0 | AM13: =IF(('Inputs & Assumptions'!$D$109+35)<='Inputs & Assumptions'!$C$13,INDEX('Inputs & Assumptions'!$D$70:$D$98,'Inputs & Assumptions'!$D$109+35+1),0) -> 0 | AN13: =IF(('Inputs & Assumptions'!$D$109+36)<='Inputs & Assumptions'!$C$13,INDEX('Inputs & Assumptions'!$D$70:$D$98,'Inputs & Assumptions'!$D$109+36+1),0) -> 0
B14: ='Inputs & Assumptions'!$B$110 -> 9 | E14: =IF(('Inputs & Assumptions'!$D$110+1)<='Inputs & Assumptions'!$C$13,INDEX('Inputs & Assumptions'!$D$70:$D$98,'Inputs & Assumptions'!$D$110+1+1),0) -> 0 | F14: =IF(('Inputs & Assumptions'!$D$110+2)<='Inputs & Assumptions'!$C$13,INDEX('Inputs & Assumptions'!$D$70:$D$98,'Inputs & Assumptions'!$D$110+2+1),0) -> 600000 | G14: =IF(('Inputs & Assumptions'!$D$110+3)<='Inputs & Assumptions'!$C$13,INDEX('Inputs & Assumptions'!$D$70:$D$98,'Inputs & Assumptions'!$D$110+3+1),0) -> 582000 | H14: =IF(('Inputs & Assumptions'!$D$110+4)<='Inputs & Assumptions'!$C$13,INDEX('Inputs & Assumptions'!$D$70:$D$98,'Inputs & Assumptions'!$D$110+4+1),0) -> 564540 | I14: =IF(('Inputs & Assumptions'!$D$110+5)<='Inputs & Assumptions'!$C$13,INDEX('Inputs & Assumptions'!$D$70:$D$98,'Inputs & Assumptions'!$D$110+5+1),0) -> 547603.8 | J14: =IF(('Inputs & Assumptions'!$D$110+6)<='Inputs & Assumptions'!$C$13,INDEX('Inputs & Assumptions'!$D$70:$D$98,'Inputs & Assumptions'!$D$110+6+1),0) -> 531175.69 | K14: =IF(('Inputs & Assumptions'!$D$110+7)<='Inputs & Assumptions'!$C$13,INDEX('Inputs & Assumptions'!$D$70:$D$98,'Inputs & Assumptions'!$D$110+7+1),0) -> 515240.42 | L14: =IF(('Inputs & Assumptions'!$D$110+8)<='Inputs & Assumptions'!$C$13,INDEX('Inputs & Assumptions'!$D$70:$D$98,'Inputs & Assumptions'!$D$110+8+1),0) -> 499783.2 | M14: =IF(('Inputs & Assumptions'!$D$110+9)<='Inputs & Assumptions'!$C$13,INDEX('Inputs & Assumptions'!$D$70:$D$98,'Inputs & Assumptions'!$D$110+9+1),0) -> 484789.71 | N14: =IF(('Inputs & Assumptions'!$D$110+10)<='Inputs & Assumptions'!$C$13,INDEX('Inputs & Assumptions'!$D$70:$D$98,'Inputs & Assumptions'!$D$110+10+1),0) -> 470246.02 | O14: =IF(('Inputs & Assumptions'!$D$110+11)<='Inputs & Assumptions'!$C$13,INDEX('Inputs & Assumptions'!$D$70:$D$98,'Inputs & Assumptions'!$D$110+11+1),0) -> 456138.64 | P14: =IF(('Inputs & Assumptions'!$D$110+12)<='Inputs & Assumptions'!$C$13,INDEX('Inputs & Assumptions'!$D$70:$D$98,'Inputs & Assumptions'!$D$110+12+1),0) -> 442454.48 | Q14: =IF(('Inputs & Assumptions'!$D$110+13)<='Inputs & Assumptions'!$C$13,INDEX('Inputs & Assumptions'!$D$70:$D$98,'Inputs & Assumptions'!$D$110+13+1),0) -> 429180.84 | R14: =IF(('Inputs & Assumptions'!$D$110+14)<='Inputs & Assumptions'!$C$13,INDEX('Inputs & Assumptions'!$D$70:$D$98,'Inputs & Assumptions'!$D$110+14+1),0) -> 416305.42 | S14: =IF(('Inputs & Assumptions'!$D$110+15)<='Inputs & Assumptions'!$C$13,INDEX('Inputs & Assumptions'!$D$70:$D$98,'Inputs & Assumptions'!$D$110+15+1),0) -> 403816.25 | T14: =IF(('Inputs & Assumptions'!$D$110+16)<='Inputs & Assumptions'!$C$13,INDEX('Inputs & Assumptions'!$D$70:$D$98,'Inputs & Assumptions'!$D$110+16+1),0) -> 391701.77 | U14: =IF(('Inputs & Assumptions'!$D$110+17)<='Inputs & Assumptions'!$C$13,INDEX('Inputs & Assumptions'!$D$70:$D$98,'Inputs & Assumptions'!$D$110+17+1),0) -> 379950.71 | V14: =IF(('Inputs & Assumptions'!$D$110+18)<='Inputs & Assumptions'!$C$13,INDEX('Inputs & Assumptions'!$D$70:$D$98,'Inputs & Assumptions'!$D$110+18+1),0) -> 368552.19 | W14: =IF(('Inputs & Assumptions'!$D$110+19)<='Inputs & Assumptions'!$C$13,INDEX('Inputs & Assumptions'!$D$70:$D$98,'Inputs & Assumptions'!$D$110+19+1),0) -> 357495.63 | X14: =IF(('Inputs & Assumptions'!$D$110+20)<='Inputs & Assumptions'!$C$13,INDEX('Inputs & Assumptions'!$D$70:$D$98,'Inputs & Assumptions'!$D$110+20+1),0) -> 346770.76 | Y14: =IF(('Inputs & Assumptions'!$D$110+21)<='Inputs & Assumptions'!$C$13,INDEX('Inputs & Assumptions'!$D$70:$D$98,'Inputs & Assumptions'!$D$110+21+1),0) -> 336367.63 | Z14: =IF(('Inputs & Assumptions'!$D$110+22)<='Inputs & Assumptions'!$C$13,INDEX('Inputs & Assumptions'!$D$70:$D$98,'Inputs & Assumptions'!$D$110+22+1),0) -> 326276.61 | AA14: =IF(('Inputs & Assumptions'!$D$110+23)<='Inputs & Assumptions'!$C$13,INDEX('Inputs & Assumptions'!$D$70:$D$98,'Inputs & Assumptions'!$D$110+23+1),0) -> 316488.31 | AB14: =IF(('Inputs & Assumptions'!$D$110+24)<='Inputs & Assumptions'!$C$13,INDEX('Inputs & Assumptions'!$D$70:$D$98,'Inputs & Assumptions'!$D$110+24+1),0) -> 306993.66 | AC14: =IF(('Inputs & Assumptions'!$D$110+25)<='Inputs & Assumptions'!$C$13,INDEX('Inputs & Assumptions'!$D$70:$D$98,'Inputs & Assumptions'!$D$110+25+1),0) -> 9926128.3 | AD14: =IF(('Inputs & Assumptions'!$D$110+26)<='Inputs & Assumptions'!$C$13,INDEX('Inputs & Assumptions'!$D$70:$D$98,'Inputs & Assumptions'!$D$110+26+1),0) -> 0 | AE14: =IF(('Inputs & Assumptions'!$D$110+27)<='Inputs & Assumptions'!$C$13,INDEX('Inputs & Assumptions'!$D$70:$D$98,'Inputs & Assumptions'!$D$110+27+1),0) -> 0 | AF14: =IF(('Inputs & Assumptions'!$D$110+28)<='Inputs & Assumptions'!$C$13,INDEX('Inputs & Assumptions'!$D$70:$D$98,'Inputs & Assumptions'!$D$110+28+1),0) -> 0 | AG14: =IF(('Inputs & Assumptions'!$D$110+29)<='Inputs & Assumptions'!$C$13,INDEX('Inputs & Assumptions'!$D$70:$D$98,'Inputs & Assumptions'!$D$110+29+1),0) -> 0 | AH14: =IF(('Inputs & Assumptions'!$D$110+30)<='Inputs & Assumptions'!$C$13,INDEX('Inputs & Assumptions'!$D$70:$D$98,'Inputs & Assumptions'!$D$110+30+1),0) -> 0 | AI14: =IF(('Inputs & Assumptions'!$D$110+31)<='Inputs & Assumptions'!$C$13,INDEX('Inputs & Assumptions'!$D$70:$D$98,'Inputs & Assumptions'!$D$110+31+1),0) -> 0 | AJ14: =IF(('Inputs & Assumptions'!$D$110+32)<='Inputs & Assumptions'!$C$13,INDEX('Inputs & Assumptions'!$D$70:$D$98,'Inputs & Assumptions'!$D$110+32+1),0) -> 0 | AK14: =IF(('Inputs & Assumptions'!$D$110+33)<='Inputs & Assumptions'!$C$13,INDEX('Inputs & Assumptions'!$D$70:$D$98,'Inputs & Assumptions'!$D$110+33+1),0) -> 0 | AL14: =IF(('Inputs & Assumptions'!$D$110+34)<='Inputs & Assumptions'!$C$13,INDEX('Inputs & Assumptions'!$D$70:$D$98,'Inputs & Assumptions'!$D$110+34+1),0) -> 0 | AM14: =IF(('Inputs & Assumptions'!$D$110+35)<='Inputs & Assumptions'!$C$13,INDEX('Inputs & Assumptions'!$D$70:$D$98,'Inputs & Assumptions'!$D$110+35+1),0) -> 0 | AN14: =IF(('Inputs & Assumptions'!$D$110+36)<='Inputs & Assumptions'!$C$13,INDEX('Inputs & Assumptions'!$D$70:$D$98,'Inputs & Assumptions'!$D$110+36+1),0) -> 0
B15: ='Inputs & Assumptions'!$B$111 -> 10 | E15: =IF(('Inputs & Assumptions'!$D$111+1)<='Inputs & Assumptions'!$C$13,INDEX('Inputs & Assumptions'!$D$70:$D$98,'Inputs & Assumptions'!$D$111+1+1),0) -> 0 | F15: =IF(('Inputs & Assumptions'!$D$111+2)<='Inputs & Assumptions'!$C$13,INDEX('Inputs & Assumptions'!$D$70:$D$98,'Inputs & Assumptions'!$D$111+2+1),0) -> 600000 | G15: =IF(('Inputs & Assumptions'!$D$111+3)<='Inputs & Assumptions'!$C$13,INDEX('Inputs & Assumptions'!$D$70:$D$98,'Inputs & Assumptions'!$D$111+3+1),0) -> 582000 | H15: =IF(('Inputs & Assumptions'!$D$111+4)<='Inputs & Assumptions'!$C$13,INDEX('Inputs & Assumptions'!$D$70:$D$98,'Inputs & Assumptions'!$D$111+4+1),0) -> 564540 | I15: =IF(('Inputs & Assumptions'!$D$111+5)<='Inputs & Assumptions'!$C$13,INDEX('Inputs & Assumptions'!$D$70:$D$98,'Inputs & Assumptions'!$D$111+5+1),0) -> 547603.8 | J15: =IF(('Inputs & Assumptions'!$D$111+6)<='Inputs & Assumptions'!$C$13,INDEX('Inputs & Assumptions'!$D$70:$D$98,'Inputs & Assumptions'!$D$111+6+1),0) -> 531175.69 | K15: =IF(('Inputs & Assumptions'!$D$111+7)<='Inputs & Assumptions'!$C$13,INDEX('Inputs & Assumptions'!$D$70:$D$98,'Inputs & Assumptions'!$D$111+7+1),0) -> 515240.42 | L15: =IF(('Inputs & Assumptions'!$D$111+8)<='Inputs & Assumptions'!$C$13,INDEX('Inputs & Assumptions'!$D$70:$D$98,'Inputs & Assumptions'!$D$111+8+1),0) -> 499783.2 | M15: =IF(('Inputs & Assumptions'!$D$111+9)<='Inputs & Assumptions'!$C$13,INDEX('Inputs & Assumptions'!$D$70:$D$98,'Inputs & Assumptions'!$D$111+9+1),0) -> 484789.71 | N15: =IF(('Inputs & Assumptions'!$D$111+10)<='Inputs & Assumptions'!$C$13,INDEX('Inputs & Assumptions'!$D$70:$D$98,'Inputs & Assumptions'!$D$111+10+1),0) -> 470246.02 | O15: =IF(('Inputs & Assumptions'!$D$111+11)<='Inputs & Assumptions'!$C$13,INDEX('Inputs & Assumptions'!$D$70:$D$98,'Inputs & Assumptions'!$D$111+11+1),0) -> 456138.64 | P15: =IF(('Inputs & Assumptions'!$D$111+12)<='Inputs & Assumptions'!$C$13,INDEX('Inputs & Assumptions'!$D$70:$D$98,'Inputs & Assumptions'!$D$111+12+1),0) -> 442454.48 | Q15: =IF(('Inputs & Assumptions'!$D$111+13)<='Inputs & Assumptions'!$C$13,INDEX('Inputs & Assumptions'!$D$70:$D$98,'Inputs & Assumptions'!$D$111+13+1),0) -> 429180.84 | R15: =IF(('Inputs & Assumptions'!$D$111+14)<='Inputs & Assumptions'!$C$13,INDEX('Inputs & Assumptions'!$D$70:$D$98,'Inputs & Assumptions'!$D$111+14+1),0) -> 416305.42 | S15: =IF(('Inputs & Assumptions'!$D$111+15)<='Inputs & Assumptions'!$C$13,INDEX('Inputs & Assumptions'!$D$70:$D$98,'Inputs & Assumptions'!$D$111+15+1),0) -> 403816.25 | T15: =IF(('Inputs & Assumptions'!$D$111+16)<='Inputs & Assumptions'!$C$13,INDEX('Inputs & Assumptions'!$D$70:$D$98,'Inputs & Assumptions'!$D$111+16+1),0) -> 391701.77 | U15: =IF(('Inputs & Assumptions'!$D$111+17)<='Inputs & Assumptions'!$C$13,INDEX('Inputs & Assumptions'!$D$70:$D$98,'Inputs & Assumptions'!$D$111+17+1),0) -> 379950.71 | V15: =IF(('Inputs & Assumptions'!$D$111+18)<='Inputs & Assumptions'!$C$13,INDEX('Inputs & Assumptions'!$D$70:$D$98,'Inputs & Assumptions'!$D$111+18+1),0) -> 368552.19 | W15: =IF(('Inputs & Assumptions'!$D$111+19)<='Inputs & Assumptions'!$C$13,INDEX('Inputs & Assumptions'!$D$70:$D$98,'Inputs & Assumptions'!$D$111+19+1),0) -> 357495.63 | X15: =IF(('Inputs & Assumptions'!$D$111+20)<='Inputs & Assumptions'!$C$13,INDEX('Inputs & Assumptions'!$D$70:$D$98,'Inputs & Assumptions'!$D$111+20+1),0) -> 346770.76 | Y15: =IF(('Inputs & Assumptions'!$D$111+21)<='Inputs & Assumptions'!$C$13,INDEX('Inputs & Assumptions'!$D$70:$D$98,'Inputs & Assumptions'!$D$111+21+1),0) -> 336367.63 | Z15: =IF(('Inputs & Assumptions'!$D$111+22)<='Inputs & Assumptions'!$C$13,INDEX('Inputs & Assumptions'!$D$70:$D$98,'Inputs & Assumptions'!$D$111+22+1),0) -> 326276.61 | AA15: =IF(('Inputs & Assumptions'!$D$111+23)<='Inputs & Assumptions'!$C$13,INDEX('Inputs & Assumptions'!$D$70:$D$98,'Inputs & Assumptions'!$D$111+23+1),0) -> 316488.31 | AB15: =IF(('Inputs & Assumptions'!$D$111+24)<='Inputs & Assumptions'!$C$13,INDEX('Inputs & Assumptions'!$D$70:$D$98,'Inputs & Assumptions'!$D$111+24+1),0) -> 306993.66 | AC15: =IF(('Inputs & Assumptions'!$D$111+25)<='Inputs & Assumptions'!$C$13,INDEX('Inputs & Assumptions'!$D$70:$D$98,'Inputs & Assumptions'!$D$111+25+1),0) -> 9926128.3 | AD15: =IF(('Inputs & Assumptions'!$D$111+26)<='Inputs & Assumptions'!$C$13,INDEX('Inputs & Assumptions'!$D$70:$D$98,'Inputs & Assumptions'!$D$111+26+1),0) -> 0 | AE15: =IF(('Inputs & Assumptions'!$D$111+27)<='Inputs & Assumptions'!$C$13,INDEX('Inputs & Assumptions'!$D$70:$D$98,'Inputs & Assumptions'!$D$111+27+1),0) -> 0 | AF15: =IF(('Inputs & Assumptions'!$D$111+28)<='Inputs & Assumptions'!$C$13,INDEX('Inputs & Assumptions'!$D$70:$D$98,'Inputs & Assumptions'!$D$111+28+1),0) -> 0 | AG15: =IF(('Inputs & Assumptions'!$D$111+29)<='Inputs & Assumptions'!$C$13,INDEX('Inputs & Assumptions'!$D$70:$D$98,'Inputs & Assumptions'!$D$111+29+1),0) -> 0 | AH15: =IF(('Inputs & Assumptions'!$D$111+30)<='Inputs & Assumptions'!$C$13,INDEX('Inputs & Assumptions'!$D$70:$D$98,'Inputs & Assumptions'!$D$111+30+1),0) -> 0 | AI15: =IF(('Inputs & Assumptions'!$D$111+31)<='Inputs & Assumptions'!$C$13,INDEX('Inputs & Assumptions'!$D$70:$D$98,'Inputs & Assumptions'!$D$111+31+1),0) -> 0 | AJ15: =IF(('Inputs & Assumptions'!$D$111+32)<='Inputs & Assumptions'!$C$13,INDEX('Inputs & Assumptions'!$D$70:$D$98,'Inputs & Assumptions'!$D$111+32+1),0) -> 0 | AK15: =IF(('Inputs & Assumptions'!$D$111+33)<='Inputs & Assumptions'!$C$13,INDEX('Inputs & Assumptions'!$D$70:$D$98,'Inputs & Assumptions'!$D$111+33+1),0) -> 0 | AL15: =IF(('Inputs & Assumptions'!$D$111+34)<='Inputs & Assumptions'!$C$13,INDEX('Inputs & Assumptions'!$D$70:$D$98,'Inputs & Assumptions'!$D$111+34+1),0) -> 0 | AM15: =IF(('Inputs & Assumptions'!$D$111+35)<='Inputs & Assumptions'!$C$13,INDEX('Inputs & Assumptions'!$D$70:$D$98,'Inputs & Assumptions'!$D$111+35+1),0) -> 0 | AN15: =IF(('Inputs & Assumptions'!$D$111+36)<='Inputs & Assumptions'!$C$13,INDEX('Inputs & Assumptions'!$D$70:$D$98,'Inputs & Assumptions'!$D$111+36+1),0) -> 0
B16: ='Inputs & Assumptions'!$B$112 -> 11 | E16: =IF(('Inputs & Assumptions'!$D$112+1)<='Inputs & Assumptions'!$C$13,INDEX('Inputs & Assumptions'!$D$70:$D$98,'Inputs & Assumptions'!$D$112+1+1),0) -> 600000 | F16: =IF(('Inputs & Assumptions'!$D$112+2)<='Inputs & Assumptions'!$C$13,INDEX('Inputs & Assumptions'!$D$70:$D$98,'Inputs & Assumptions'!$D$112+2+1),0) -> 582000 | G16: =IF(('Inputs & Assumptions'!$D$112+3)<='Inputs & Assumptions'!$C$13,INDEX('Inputs & Assumptions'!$D$70:$D$98,'Inputs & Assumptions'!$D$112+3+1),0) -> 564540 | H16: =IF(('Inputs & Assumptions'!$D$112+4)<='Inputs & Assumptions'!$C$13,INDEX('Inputs & Assumptions'!$D$70:$D$98,'Inputs & Assumptions'!$D$112+4+1),0) -> 547603.8 | I16: =IF(('Inputs & Assumptions'!$D$112+5)<='Inputs & Assumptions'!$C$13,INDEX('Inputs & Assumptions'!$D$70:$D$98,'Inputs & Assumptions'!$D$112+5+1),0) -> 531175.69 | J16: =IF(('Inputs & Assumptions'!$D$112+6)<='Inputs & Assumptions'!$C$13,INDEX('Inputs & Assumptions'!$D$70:$D$98,'Inputs & Assumptions'!$D$112+6+1),0) -> 515240.42 | K16: =IF(('Inputs & Assumptions'!$D$112+7)<='Inputs & Assumptions'!$C$13,INDEX('Inputs & Assumptions'!$D$70:$D$98,'Inputs & Assumptions'!$D$112+7+1),0) -> 499783.2 | L16: =IF(('Inputs & Assumptions'!$D$112+8)<='Inputs & Assumptions'!$C$13,INDEX('Inputs & Assumptions'!$D$70:$D$98,'Inputs & Assumptions'!$D$112+8+1),0) -> 484789.71 | M16: =IF(('Inputs & Assumptions'!$D$112+9)<='Inputs & Assumptions'!$C$13,INDEX('Inputs & Assumptions'!$D$70:$D$98,'Inputs & Assumptions'!$D$112+9+1),0) -> 470246.02 | N16: =IF(('Inputs & Assumptions'!$D$112+10)<='Inputs & Assumptions'!$C$13,INDEX('Inputs & Assumptions'!$D$70:$D$98,'Inputs & Assumptions'!$D$112+10+1),0) -> 456138.64 | O16: =IF(('Inputs & Assumptions'!$D$112+11)<='Inputs & Assumptions'!$C$13,INDEX('Inputs & Assumptions'!$D$70:$D$98,'Inputs & Assumptions'!$D$112+11+1),0) -> 442454.48 | P16: =IF(('Inputs & Assumptions'!$D$112+12)<='Inputs & Assumptions'!$C$13,INDEX('Inputs & Assumptions'!$D$70:$D$98,'Inputs & Assumptions'!$D$112+12+1),0) -> 429180.84 | Q16: =IF(('Inputs & Assumptions'!$D$112+13)<='Inputs & Assumptions'!$C$13,INDEX('Inputs & Assumptions'!$D$70:$D$98,'Inputs & Assumptions'!$D$112+13+1),0) -> 416305.42 | R16: =IF(('Inputs & Assumptions'!$D$112+14)<='Inputs & Assumptions'!$C$13,INDEX('Inputs & Assumptions'!$D$70:$D$98,'Inputs & Assumptions'!$D$112+14+1),0) -> 403816.25 | S16: =IF(('Inputs & Assumptions'!$D$112+15)<='Inputs & Assumptions'!$C$13,INDEX('Inputs & Assumptions'!$D$70:$D$98,'Inputs & Assumptions'!$D$112+15+1),0) -> 391701.77 | T16: =IF(('Inputs & Assumptions'!$D$112+16)<='Inputs & Assumptions'!$C$13,INDEX('Inputs & Assumptions'!$D$70:$D$98,'Inputs & Assumptions'!$D$112+16+1),0) -> 379950.71 | U16: =IF(('Inputs & Assumptions'!$D$112+17)<='Inputs & Assumptions'!$C$13,INDEX('Inputs & Assumptions'!$D$70:$D$98,'Inputs & Assumptions'!$D$112+17+1),0) -> 368552.19 | V16: =IF(('Inputs & Assumptions'!$D$112+18)<='Inputs & Assumptions'!$C$13,INDEX('Inputs & Assumptions'!$D$70:$D$98,'Inputs & Assumptions'!$D$112+18+1),0) -> 357495.63 | W16: =IF(('Inputs & Assumptions'!$D$112+19)<='Inputs & Assumptions'!$C$13,INDEX('Inputs & Assumptions'!$D$70:$D$98,'Inputs & Assumptions'!$D$112+19+1),0) -> 346770.76 | X16: =IF(('Inputs & Assumptions'!$D$112+20)<='Inputs & Assumptions'!$C$13,INDEX('Inputs & Assumptions'!$D$70:$D$98,'Inputs & Assumptions'!$D$112+20+1),0) -> 336367.63 | Y16: =IF(('Inputs & Assumptions'!$D$112+21)<='Inputs & Assumptions'!$C$13,INDEX('Inputs & Assumptions'!$D$70:$D$98,'Inputs & Assumptions'!$D$112+21+1),0) -> 326276.61 | Z16: =IF(('Inputs & Assumptions'!$D$112+22)<='Inputs & Assumptions'!$C$13,INDEX('Inputs & Assumptions'!$D$70:$D$98,'Inputs & Assumptions'!$D$112+22+1),0) -> 316488.31 | AA16: =IF(('Inputs & Assumptions'!$D$112+23)<='Inputs & Assumptions'!$C$13,INDEX('Inputs & Assumptions'!$D$70:$D$98,'Inputs & Assumptions'!$D$112+23+1),0) -> 306993.66 | AB16: =IF(('Inputs & Assumptions'!$D$112+24)<='Inputs & Assumptions'!$C$13,INDEX('Inputs & Assumptions'!$D$70:$D$98,'Inputs & Assumptions'!$D$112+24+1),0) -> 9926128.3 | AC16: =IF(('Inputs & Assumptions'!$D$112+25)<='Inputs & Assumptions'!$C$13,INDEX('Inputs & Assumptions'!$D$70:$D$98,'Inputs & Assumptions'!$D$112+25+1),0) -> 0 | AD16: =IF(('Inputs & Assumptions'!$D$112+26)<='Inputs & Assumptions'!$C$13,INDEX('Inputs & Assumptions'!$D$70:$D$98,'Inputs & Assumptions'!$D$112+26+1),0) -> 0 | AE16: =IF(('Inputs & Assumptions'!$D$112+27)<='Inputs & Assumptions'!$C$13,INDEX('Inputs & Assumptions'!$D$70:$D$98,'Inputs & Assumptions'!$D$112+27+1),0) -> 0 | AF16: =IF(('Inputs & Assumptions'!$D$112+28)<='Inputs & Assumptions'!$C$13,INDEX('Inputs & Assumptions'!$D$70:$D$98,'Inputs & Assumptions'!$D$112+28+1),0) -> 0 | AG16: =IF(('Inputs & Assumptions'!$D$112+29)<='Inputs & Assumptions'!$C$13,INDEX('Inputs & Assumptions'!$D$70:$D$98,'Inputs & Assumptions'!$D$112+29+1),0) -> 0 | AH16: =IF(('Inputs & Assumptions'!$D$112+30)<='Inputs & Assumptions'!$C$13,INDEX('Inputs & Assumptions'!$D$70:$D$98,'Inputs & Assumptions'!$D$112+30+1),0) -> 0 | AI16: =IF(('Inputs & Assumptions'!$D$112+31)<='Inputs & Assumptions'!$C$13,INDEX('Inputs & Assumptions'!$D$70:$D$98,'Inputs & Assumptions'!$D$112+31+1),0) -> 0 | AJ16: =IF(('Inputs & Assumptions'!$D$112+32)<='Inputs & Assumptions'!$C$13,INDEX('Inputs & Assumptions'!$D$70:$D$98,'Inputs & Assumptions'!$D$112+32+1),0) -> 0 | AK16: =IF(('Inputs & Assumptions'!$D$112+33)<='Inputs & Assumptions'!$C$13,INDEX('Inputs & Assumptions'!$D$70:$D$98,'Inputs & Assumptions'!$D$112+33+1),0) -> 0 | AL16: =IF(('Inputs & Assumptions'!$D$112+34)<='Inputs & Assumptions'!$C$13,INDEX('Inputs & Assumptions'!$D$70:$D$98,'Inputs & Assumptions'!$D$112+34+1),0) -> 0 | AM16: =IF(('Inputs & Assumptions'!$D$112+35)<='Inputs & Assumptions'!$C$13,INDEX('Inputs & Assumptions'!$D$70:$D$98,'Inputs & Assumptions'!$D$112+35+1),0) -> 0 | AN16: =IF(('Inputs & Assumptions'!$D$112+36)<='Inputs & Assumptions'!$C$13,INDEX('Inputs & Assumptions'!$D$70:$D$98,'Inputs & Assumptions'!$D$112+36+1),0) -> 0
B17: ='Inputs & Assumptions'!$B$113 -> 12 | E17: =IF(('Inputs & Assumptions'!$D$113+1)<='Inputs & Assumptions'!$C$13,INDEX('Inputs & Assumptions'!$D$70:$D$98,'Inputs & Assumptions'!$D$113+1+1),0) -> 600000 | F17: =IF(('Inputs & Assumptions'!$D$113+2)<='Inputs & Assumptions'!$C$13,INDEX('Inputs & Assumptions'!$D$70:$D$98,'Inputs & Assumptions'!$D$113+2+1),0) -> 582000 | G17: =IF(('Inputs & Assumptions'!$D$113+3)<='Inputs & Assumptions'!$C$13,INDEX('Inputs & Assumptions'!$D$70:$D$98,'Inputs & Assumptions'!$D$113+3+1),0) -> 564540 | H17: =IF(('Inputs & Assumptions'!$D$113+4)<='Inputs & Assumptions'!$C$13,INDEX('Inputs & Assumptions'!$D$70:$D$98,'Inputs & Assumptions'!$D$113+4+1),0) -> 547603.8 | I17: =IF(('Inputs & Assumptions'!$D$113+5)<='Inputs & Assumptions'!$C$13,INDEX('Inputs & Assumptions'!$D$70:$D$98,'Inputs & Assumptions'!$D$113+5+1),0) -> 531175.69 | J17: =IF(('Inputs & Assumptions'!$D$113+6)<='Inputs & Assumptions'!$C$13,INDEX('Inputs & Assumptions'!$D$70:$D$98,'Inputs & Assumptions'!$D$113+6+1),0) -> 515240.42 | K17: =IF(('Inputs & Assumptions'!$D$113+7)<='Inputs & Assumptions'!$C$13,INDEX('Inputs & Assumptions'!$D$70:$D$98,'Inputs & Assumptions'!$D$113+7+1),0) -> 499783.2 | L17: =IF(('Inputs & Assumptions'!$D$113+8)<='Inputs & Assumptions'!$C$13,INDEX('Inputs & Assumptions'!$D$70:$D$98,'Inputs & Assumptions'!$D$113+8+1),0) -> 484789.71 | M17: =IF(('Inputs & Assumptions'!$D$113+9)<='Inputs & Assumptions'!$C$13,INDEX('Inputs & Assumptions'!$D$70:$D$98,'Inputs & Assumptions'!$D$113+9+1),0) -> 470246.02 | N17: =IF(('Inputs & Assumptions'!$D$113+10)<='Inputs & Assumptions'!$C$13,INDEX('Inputs & Assumptions'!$D$70:$D$98,'Inputs & Assumptions'!$D$113+10+1),0) -> 456138.64 | O17: =IF(('Inputs & Assumptions'!$D$113+11)<='Inputs & Assumptions'!$C$13,INDEX('Inputs & Assumptions'!$D$70:$D$98,'Inputs & Assumptions'!$D$113+11+1),0) -> 442454.48 | P17: =IF(('Inputs & Assumptions'!$D$113+12)<='Inputs & Assumptions'!$C$13,INDEX('Inputs & Assumptions'!$D$70:$D$98,'Inputs & Assumptions'!$D$113+12+1),0) -> 429180.84 | Q17: =IF(('Inputs & Assumptions'!$D$113+13)<='Inputs & Assumptions'!$C$13,INDEX('Inputs & Assumptions'!$D$70:$D$98,'Inputs & Assumptions'!$D$113+13+1),0) -> 416305.42 | R17: =IF(('Inputs & Assumptions'!$D$113+14)<='Inputs & Assumptions'!$C$13,INDEX('Inputs & Assumptions'!$D$70:$D$98,'Inputs & Assumptions'!$D$113+14+1),0) -> 403816.25 | S17: =IF(('Inputs & Assumptions'!$D$113+15)<='Inputs & Assumptions'!$C$13,INDEX('Inputs & Assumptions'!$D$70:$D$98,'Inputs & Assumptions'!$D$113+15+1),0) -> 391701.77 | T17: =IF(('Inputs & Assumptions'!$D$113+16)<='Inputs & Assumptions'!$C$13,INDEX('Inputs & Assumptions'!$D$70:$D$98,'Inputs & Assumptions'!$D$113+16+1),0) -> 379950.71 | U17: =IF(('Inputs & Assumptions'!$D$113+17)<='Inputs & Assumptions'!$C$13,INDEX('Inputs & Assumptions'!$D$70:$D$98,'Inputs & Assumptions'!$D$113+17+1),0) -> 368552.19 | V17: =IF(('Inputs & Assumptions'!$D$113+18)<='Inputs & Assumptions'!$C$13,INDEX('Inputs & Assumptions'!$D$70:$D$98,'Inputs & Assumptions'!$D$113+18+1),0) -> 357495.63 | W17: =IF(('Inputs & Assumptions'!$D$113+19)<='Inputs & Assumptions'!$C$13,INDEX('Inputs & Assumptions'!$D$70:$D$98,'Inputs & Assumptions'!$D$113+19+1),0) -> 346770.76 | X17: =IF(('Inputs & Assumptions'!$D$113+20)<='Inputs & Assumptions'!$C$13,INDEX('Inputs & Assumptions'!$D$70:$D$98,'Inputs & Assumptions'!$D$113+20+1),0) -> 336367.63 | Y17: =IF(('Inputs & Assumptions'!$D$113+21)<='Inputs & Assumptions'!$C$13,INDEX('Inputs & Assumptions'!$D$70:$D$98,'Inputs & Assumptions'!$D$113+21+1),0) -> 326276.61 | Z17: =IF(('Inputs & Assumptions'!$D$113+22)<='Inputs & Assumptions'!$C$13,INDEX('Inputs & Assumptions'!$D$70:$D$98,'Inputs & Assumptions'!$D$113+22+1),0) -> 316488.31 | AA17: =IF(('Inputs & Assumptions'!$D$113+23)<='Inputs & Assumptions'!$C$13,INDEX('Inputs & Assumptions'!$D$70:$D$98,'Inputs & Assumptions'!$D$113+23+1),0) -> 306993.66 | AB17: =IF(('Inputs & Assumptions'!$D$113+24)<='Inputs & Assumptions'!$C$13,INDEX('Inputs & Assumptions'!$D$70:$D$98,'Inputs & Assumptions'!$D$113+24+1),0) -> 9926128.3 | AC17: =IF(('Inputs & Assumptions'!$D$113+25)<='Inputs & Assumptions'!$C$13,INDEX('Inputs & Assumptions'!$D$70:$D$98,'Inputs & Assumptions'!$D$113+25+1),0) -> 0 | AD17: =IF(('Inputs & Assumptions'!$D$113+26)<='Inputs & Assumptions'!$C$13,INDEX('Inputs & Assumptions'!$D$70:$D$98,'Inputs & Assumptions'!$D$113+26+1),0) -> 0 | AE17: =IF(('Inputs & Assumptions'!$D$113+27)<='Inputs & Assumptions'!$C$13,INDEX('Inputs & Assumptions'!$D$70:$D$98,'Inputs & Assumptions'!$D$113+27+1),0) -> 0 | AF17: =IF(('Inputs & Assumptions'!$D$113+28)<='Inputs & Assumptions'!$C$13,INDEX('Inputs & Assumptions'!$D$70:$D$98,'Inputs & Assumptions'!$D$113+28+1),0) -> 0 | AG17: =IF(('Inputs & Assumptions'!$D$113+29)<='Inputs & Assumptions'!$C$13,INDEX('Inputs & Assumptions'!$D$70:$D$98,'Inputs & Assumptions'!$D$113+29+1),0) -> 0 | AH17: =IF(('Inputs & Assumptions'!$D$113+30)<='Inputs & Assumptions'!$C$13,INDEX('Inputs & Assumptions'!$D$70:$D$98,'Inputs & Assumptions'!$D$113+30+1),0) -> 0 | AI17: =IF(('Inputs & Assumptions'!$D$113+31)<='Inputs & Assumptions'!$C$13,INDEX('Inputs & Assumptions'!$D$70:$D$98,'Inputs & Assumptions'!$D$113+31+1),0) -> 0 | AJ17: =IF(('Inputs & Assumptions'!$D$113+32)<='Inputs & Assumptions'!$C$13,INDEX('Inputs & Assumptions'!$D$70:$D$98,'Inputs & Assumptions'!$D$113+32+1),0) -> 0 | AK17: =IF(('Inputs & Assumptions'!$D$113+33)<='Inputs & Assumptions'!$C$13,INDEX('Inputs & Assumptions'!$D$70:$D$98,'Inputs & Assumptions'!$D$113+33+1),0) -> 0 | AL17: =IF(('Inputs & Assumptions'!$D$113+34)<='Inputs & Assumptions'!$C$13,INDEX('Inputs & Assumptions'!$D$70:$D$98,'Inputs & Assumptions'!$D$113+34+1),0) -> 0 | AM17: =IF(('Inputs & Assumptions'!$D$113+35)<='Inputs & Assumptions'!$C$13,INDEX('Inputs & Assumptions'!$D$70:$D$98,'Inputs & Assumptions'!$D$113+35+1),0) -> 0 | AN17: =IF(('Inputs & Assumptions'!$D$113+36)<='Inputs & Assumptions'!$C$13,INDEX('Inputs & Assumptions'!$D$70:$D$98,'Inputs & Assumptions'!$D$113+36+1),0) -> 0
B18: ='Inputs & Assumptions'!$B$114 -> 13 | E18: =IF(('Inputs & Assumptions'!$D$114+1)<='Inputs & Assumptions'!$C$13,INDEX('Inputs & Assumptions'!$D$70:$D$98,'Inputs & Assumptions'!$D$114+1+1),0) -> 600000 | F18: =IF(('Inputs & Assumptions'!$D$114+2)<='Inputs & Assumptions'!$C$13,INDEX('Inputs & Assumptions'!$D$70:$D$98,'Inputs & Assumptions'!$D$114+2+1),0) -> 582000 | G18: =IF(('Inputs & Assumptions'!$D$114+3)<='Inputs & Assumptions'!$C$13,INDEX('Inputs & Assumptions'!$D$70:$D$98,'Inputs & Assumptions'!$D$114+3+1),0) -> 564540 | H18: =IF(('Inputs & Assumptions'!$D$114+4)<='Inputs & Assumptions'!$C$13,INDEX('Inputs & Assumptions'!$D$70:$D$98,'Inputs & Assumptions'!$D$114+4+1),0) -> 547603.8 | I18: =IF(('Inputs & Assumptions'!$D$114+5)<='Inputs & Assumptions'!$C$13,INDEX('Inputs & Assumptions'!$D$70:$D$98,'Inputs & Assumptions'!$D$114+5+1),0) -> 531175.69 | J18: =IF(('Inputs & Assumptions'!$D$114+6)<='Inputs & Assumptions'!$C$13,INDEX('Inputs & Assumptions'!$D$70:$D$98,'Inputs & Assumptions'!$D$114+6+1),0) -> 515240.42 | K18: =IF(('Inputs & Assumptions'!$D$114+7)<='Inputs & Assumptions'!$C$13,INDEX('Inputs & Assumptions'!$D$70:$D$98,'Inputs & Assumptions'!$D$114+7+1),0) -> 499783.2 | L18: =IF(('Inputs & Assumptions'!$D$114+8)<='Inputs & Assumptions'!$C$13,INDEX('Inputs & Assumptions'!$D$70:$D$98,'Inputs & Assumptions'!$D$114+8+1),0) -> 484789.71 | M18: =IF(('Inputs & Assumptions'!$D$114+9)<='Inputs & Assumptions'!$C$13,INDEX('Inputs & Assumptions'!$D$70:$D$98,'Inputs & Assumptions'!$D$114+9+1),0) -> 470246.02 | N18: =IF(('Inputs & Assumptions'!$D$114+10)<='Inputs & Assumptions'!$C$13,INDEX('Inputs & Assumptions'!$D$70:$D$98,'Inputs & Assumptions'!$D$114+10+1),0) -> 456138.64 | O18: =IF(('Inputs & Assumptions'!$D$114+11)<='Inputs & Assumptions'!$C$13,INDEX('Inputs & Assumptions'!$D$70:$D$98,'Inputs & Assumptions'!$D$114+11+1),0) -> 442454.48 | P18: =IF(('Inputs & Assumptions'!$D$114+12)<='Inputs & Assumptions'!$C$13,INDEX('Inputs & Assumptions'!$D$70:$D$98,'Inputs & Assumptions'!$D$114+12+1),0) -> 429180.84 | Q18: =IF(('Inputs & Assumptions'!$D$114+13)<='Inputs & Assumptions'!$C$13,INDEX('Inputs & Assumptions'!$D$70:$D$98,'Inputs & Assumptions'!$D$114+13+1),0) -> 416305.42 | R18: =IF(('Inputs & Assumptions'!$D$114+14)<='Inputs & Assumptions'!$C$13,INDEX('Inputs & Assumptions'!$D$70:$D$98,'Inputs & Assumptions'!$D$114+14+1),0) -> 403816.25 | S18: =IF(('Inputs & Assumptions'!$D$114+15)<='Inputs & Assumptions'!$C$13,INDEX('Inputs & Assumptions'!$D$70:$D$98,'Inputs & Assumptions'!$D$114+15+1),0) -> 391701.77 | T18: =IF(('Inputs & Assumptions'!$D$114+16)<='Inputs & Assumptions'!$C$13,INDEX('Inputs & Assumptions'!$D$70:$D$98,'Inputs & Assumptions'!$D$114+16+1),0) -> 379950.71 | U18: =IF(('Inputs & Assumptions'!$D$114+17)<='Inputs & Assumptions'!$C$13,INDEX('Inputs & Assumptions'!$D$70:$D$98,'Inputs & Assumptions'!$D$114+17+1),0) -> 368552.19 | V18: =IF(('Inputs & Assumptions'!$D$114+18)<='Inputs & Assumptions'!$C$13,INDEX('Inputs & Assumptions'!$D$70:$D$98,'Inputs & Assumptions'!$D$114+18+1),0) -> 357495.63 | W18: =IF(('Inputs & Assumptions'!$D$114+19)<='Inputs & Assumptions'!$C$13,INDEX('Inputs & Assumptions'!$D$70:$D$98,'Inputs & Assumptions'!$D$114+19+1),0) -> 346770.76 | X18: =IF(('Inputs & Assumptions'!$D$114+20)<='Inputs & Assumptions'!$C$13,INDEX('Inputs & Assumptions'!$D$70:$D$98,'Inputs & Assumptions'!$D$114+20+1),0) -> 336367.63 | Y18: =IF(('Inputs & Assumptions'!$D$114+21)<='Inputs & Assumptions'!$C$13,INDEX('Inputs & Assumptions'!$D$70:$D$98,'Inputs & Assumptions'!$D$114+21+1),0) -> 326276.61 | Z18: =IF(('Inputs & Assumptions'!$D$114+22)<='Inputs & Assumptions'!$C$13,INDEX('Inputs & Assumptions'!$D$70:$D$98,'Inputs & Assumptions'!$D$114+22+1),0) -> 316488.31 | AA18: =IF(('Inputs & Assumptions'!$D$114+23)<='Inputs & Assumptions'!$C$13,INDEX('Inputs & Assumptions'!$D$70:$D$98,'Inputs & Assumptions'!$D$114+23+1),0) -> 306993.66 | AB18: =IF(('Inputs & Assumptions'!$D$114+24)<='Inputs & Assumptions'!$C$13,INDEX('Inputs & Assumptions'!$D$70:$D$98,'Inputs & Assumptions'!$D$114+24+1),0) -> 9926128.3 | AC18: =IF(('Inputs & Assumptions'!$D$114+25)<='Inputs & Assumptions'!$C$13,INDEX('Inputs & Assumptions'!$D$70:$D$98,'Inputs & Assumptions'!$D$114+25+1),0) -> 0 | AD18: =IF(('Inputs & Assumptions'!$D$114+26)<='Inputs & Assumptions'!$C$13,INDEX('Inputs & Assumptions'!$D$70:$D$98,'Inputs & Assumptions'!$D$114+26+1),0) -> 0 | AE18: =IF(('Inputs & Assumptions'!$D$114+27)<='Inputs & Assumptions'!$C$13,INDEX('Inputs & Assumptions'!$D$70:$D$98,'Inputs & Assumptions'!$D$114+27+1),0) -> 0 | AF18: =IF(('Inputs & Assumptions'!$D$114+28)<='Inputs & Assumptions'!$C$13,INDEX('Inputs & Assumptions'!$D$70:$D$98,'Inputs & Assumptions'!$D$114+28+1),0) -> 0 | AG18: =IF(('Inputs & Assumptions'!$D$114+29)<='Inputs & Assumptions'!$C$13,INDEX('Inputs & Assumptions'!$D$70:$D$98,'Inputs & Assumptions'!$D$114+29+1),0) -> 0 | AH18: =IF(('Inputs & Assumptions'!$D$114+30)<='Inputs & Assumptions'!$C$13,INDEX('Inputs & Assumptions'!$D$70:$D$98,'Inputs & Assumptions'!$D$114+30+1),0) -> 0 | AI18: =IF(('Inputs & Assumptions'!$D$114+31)<='Inputs & Assumptions'!$C$13,INDEX('Inputs & Assumptions'!$D$70:$D$98,'Inputs & Assumptions'!$D$114+31+1),0) -> 0 | AJ18: =IF(('Inputs & Assumptions'!$D$114+32)<='Inputs & Assumptions'!$C$13,INDEX('Inputs & Assumptions'!$D$70:$D$98,'Inputs & Assumptions'!$D$114+32+1),0) -> 0 | AK18: =IF(('Inputs & Assumptions'!$D$114+33)<='Inputs & Assumptions'!$C$13,INDEX('Inputs & Assumptions'!$D$70:$D$98,'Inputs & Assumptions'!$D$114+33+1),0) -> 0 | AL18: =IF(('Inputs & Assumptions'!$D$114+34)<='Inputs & Assumptions'!$C$13,INDEX('Inputs & Assumptions'!$D$70:$D$98,'Inputs & Assumptions'!$D$114+34+1),0) -> 0 | AM18: =IF(('Inputs & Assumptions'!$D$114+35)<='Inputs & Assumptions'!$C$13,INDEX('Inputs & Assumptions'!$D$70:$D$98,'Inputs & Assumptions'!$D$114+35+1),0) -> 0 | AN18: =IF(('Inputs & Assumptions'!$D$114+36)<='Inputs & Assumptions'!$C$13,INDEX('Inputs & Assumptions'!$D$70:$D$98,'Inputs & Assumptions'!$D$114+36+1),0) -> 0
B19: ='Inputs & Assumptions'!$B$115 -> 14 | E19: =IF(('Inputs & Assumptions'!$D$115+1)<='Inputs & Assumptions'!$C$13,INDEX('Inputs & Assumptions'!$D$70:$D$98,'Inputs & Assumptions'!$D$115+1+1),0) -> 582000 | F19: =IF(('Inputs & Assumptions'!$D$115+2)<='Inputs & Assumptions'!$C$13,INDEX('Inputs & Assumptions'!$D$70:$D$98,'Inputs & Assumptions'!$D$115+2+1),0) -> 564540 | G19: =IF(('Inputs & Assumptions'!$D$115+3)<='Inputs & Assumptions'!$C$13,INDEX('Inputs & Assumptions'!$D$70:$D$98,'Inputs & Assumptions'!$D$115+3+1),0) -> 547603.8 | H19: =IF(('Inputs & Assumptions'!$D$115+4)<='Inputs & Assumptions'!$C$13,INDEX('Inputs & Assumptions'!$D$70:$D$98,'Inputs & Assumptions'!$D$115+4+1),0) -> 531175.69 | I19: =IF(('Inputs & Assumptions'!$D$115+5)<='Inputs & Assumptions'!$C$13,INDEX('Inputs & Assumptions'!$D$70:$D$98,'Inputs & Assumptions'!$D$115+5+1),0) -> 515240.42 | J19: =IF(('Inputs & Assumptions'!$D$115+6)<='Inputs & Assumptions'!$C$13,INDEX('Inputs & Assumptions'!$D$70:$D$98,'Inputs & Assumptions'!$D$115+6+1),0) -> 499783.2 | K19: =IF(('Inputs & Assumptions'!$D$115+7)<='Inputs & Assumptions'!$C$13,INDEX('Inputs & Assumptions'!$D$70:$D$98,'Inputs & Assumptions'!$D$115+7+1),0) -> 484789.71 | L19: =IF(('Inputs & Assumptions'!$D$115+8)<='Inputs & Assumptions'!$C$13,INDEX('Inputs & Assumptions'!$D$70:$D$98,'Inputs & Assumptions'!$D$115+8+1),0) -> 470246.02 | M19: =IF(('Inputs & Assumptions'!$D$115+9)<='Inputs & Assumptions'!$C$13,INDEX('Inputs & Assumptions'!$D$70:$D$98,'Inputs & Assumptions'!$D$115+9+1),0) -> 456138.64 | N19: =IF(('Inputs & Assumptions'!$D$115+10)<='Inputs & Assumptions'!$C$13,INDEX('Inputs & Assumptions'!$D$70:$D$98,'Inputs & Assumptions'!$D$115+10+1),0) -> 442454.48 | O19: =IF(('Inputs & Assumptions'!$D$115+11)<='Inputs & Assumptions'!$C$13,INDEX('Inputs & Assumptions'!$D$70:$D$98,'Inputs & Assumptions'!$D$115+11+1),0) -> 429180.84 | P19: =IF(('Inputs & Assumptions'!$D$115+12)<='Inputs & Assumptions'!$C$13,INDEX('Inputs & Assumptions'!$D$70:$D$98,'Inputs & Assumptions'!$D$115+12+1),0) -> 416305.42 | Q19: =IF(('Inputs & Assumptions'!$D$115+13)<='Inputs & Assumptions'!$C$13,INDEX('Inputs & Assumptions'!$D$70:$D$98,'Inputs & Assumptions'!$D$115+13+1),0) -> 403816.25 | R19: =IF(('Inputs & Assumptions'!$D$115+14)<='Inputs & Assumptions'!$C$13,INDEX('Inputs & Assumptions'!$D$70:$D$98,'Inputs & Assumptions'!$D$115+14+1),0) -> 391701.77 | S19: =IF(('Inputs & Assumptions'!$D$115+15)<='Inputs & Assumptions'!$C$13,INDEX('Inputs & Assumptions'!$D$70:$D$98,'Inputs & Assumptions'!$D$115+15+1),0) -> 379950.71 | T19: =IF(('Inputs & Assumptions'!$D$115+16)<='Inputs & Assumptions'!$C$13,INDEX('Inputs & Assumptions'!$D$70:$D$98,'Inputs & Assumptions'!$D$115+16+1),0) -> 368552.19 | U19: =IF(('Inputs & Assumptions'!$D$115+17)<='Inputs & Assumptions'!$C$13,INDEX('Inputs & Assumptions'!$D$70:$D$98,'Inputs & Assumptions'!$D$115+17+1),0) -> 357495.63 | V19: =IF(('Inputs & Assumptions'!$D$115+18)<='Inputs & Assumptions'!$C$13,INDEX('Inputs & Assumptions'!$D$70:$D$98,'Inputs & Assumptions'!$D$115+18+1),0) -> 346770.76 | W19: =IF(('Inputs & Assumptions'!$D$115+19)<='Inputs & Assumptions'!$C$13,INDEX('Inputs & Assumptions'!$D$70:$D$98,'Inputs & Assumptions'!$D$115+19+1),0) -> 336367.63 | X19: =IF(('Inputs & Assumptions'!$D$115+20)<='Inputs & Assumptions'!$C$13,INDEX('Inputs & Assumptions'!$D$70:$D$98,'Inputs & Assumptions'!$D$115+20+1),0) -> 326276.61 | Y19: =IF(('Inputs & Assumptions'!$D$115+21)<='Inputs & Assumptions'!$C$13,INDEX('Inputs & Assumptions'!$D$70:$D$98,'Inputs & Assumptions'!$D$115+21+1),0) -> 316488.31 | Z19: =IF(('Inputs & Assumptions'!$D$115+22)<='Inputs & Assumptions'!$C$13,INDEX('Inputs & Assumptions'!$D$70:$D$98,'Inputs & Assumptions'!$D$115+22+1),0) -> 306993.66 | AA19: =IF(('Inputs & Assumptions'!$D$115+23)<='Inputs & Assumptions'!$C$13,INDEX('Inputs & Assumptions'!$D$70:$D$98,'Inputs & Assumptions'!$D$115+23+1),0) -> 9926128.3 | AB19: =IF(('Inputs & Assumptions'!$D$115+24)<='Inputs & Assumptions'!$C$13,INDEX('Inputs & Assumptions'!$D$70:$D$98,'Inputs & Assumptions'!$D$115+24+1),0) -> 0 | AC19: =IF(('Inputs & Assumptions'!$D$115+25)<='Inputs & Assumptions'!$C$13,INDEX('Inputs & Assumptions'!$D$70:$D$98,'Inputs & Assumptions'!$D$115+25+1),0) -> 0 | AD19: =IF(('Inputs & Assumptions'!$D$115+26)<='Inputs & Assumptions'!$C$13,INDEX('Inputs & Assumptions'!$D$70:$D$98,'Inputs & Assumptions'!$D$115+26+1),0) -> 0 | AE19: =IF(('Inputs & Assumptions'!$D$115+27)<='Inputs & Assumptions'!$C$13,INDEX('Inputs & Assumptions'!$D$70:$D$98,'Inputs & Assumptions'!$D$115+27+1),0) -> 0 | AF19: =IF(('Inputs & Assumptions'!$D$115+28)<='Inputs & Assumptions'!$C$13,INDEX('Inputs & Assumptions'!$D$70:$D$98,'Inputs & Assumptions'!$D$115+28+1),0) -> 0 | AG19: =IF(('Inputs & Assumptions'!$D$115+29)<='Inputs & Assumptions'!$C$13,INDEX('Inputs & Assumptions'!$D$70:$D$98,'Inputs & Assumptions'!$D$115+29+1),0) -> 0 | AH19: =IF(('Inputs & Assumptions'!$D$115+30)<='Inputs & Assumptions'!$C$13,INDEX('Inputs & Assumptions'!$D$70:$D$98,'Inputs & Assumptions'!$D$115+30+1),0) -> 0 | AI19: =IF(('Inputs & Assumptions'!$D$115+31)<='Inputs & Assumptions'!$C$13,INDEX('Inputs & Assumptions'!$D$70:$D$98,'Inputs & Assumptions'!$D$115+31+1),0) -> 0 | AJ19: =IF(('Inputs & Assumptions'!$D$115+32)<='Inputs & Assumptions'!$C$13,INDEX('Inputs & Assumptions'!$D$70:$D$98,'Inputs & Assumptions'!$D$115+32+1),0) -> 0 | AK19: =IF(('Inputs & Assumptions'!$D$115+33)<='Inputs & Assumptions'!$C$13,INDEX('Inputs & Assumptions'!$D$70:$D$98,'Inputs & Assumptions'!$D$115+33+1),0) -> 0 | AL19: =IF(('Inputs & Assumptions'!$D$115+34)<='Inputs & Assumptions'!$C$13,INDEX('Inputs & Assumptions'!$D$70:$D$98,'Inputs & Assumptions'!$D$115+34+1),0) -> 0 | AM19: =IF(('Inputs & Assumptions'!$D$115+35)<='Inputs & Assumptions'!$C$13,INDEX('Inputs & Assumptions'!$D$70:$D$98,'Inputs & Assumptions'!$D$115+35+1),0) -> 0 | AN19: =IF(('Inputs & Assumptions'!$D$115+36)<='Inputs & Assumptions'!$C$13,INDEX('Inputs & Assumptions'!$D$70:$D$98,'Inputs & Assumptions'!$D$115+36+1),0) -> 0
B20: ='Inputs & Assumptions'!$B$116 -> 15 | E20: =IF(('Inputs & Assumptions'!$D$116+1)<='Inputs & Assumptions'!$C$13,INDEX('Inputs & Assumptions'!$D$70:$D$98,'Inputs & Assumptions'!$D$116+1+1),0) -> 582000 | F20: =IF(('Inputs & Assumptions'!$D$116+2)<='Inputs & Assumptions'!$C$13,INDEX('Inputs & Assumptions'!$D$70:$D$98,'Inputs & Assumptions'!$D$116+2+1),0) -> 564540 | G20: =IF(('Inputs & Assumptions'!$D$116+3)<='Inputs & Assumptions'!$C$13,INDEX('Inputs & Assumptions'!$D$70:$D$98,'Inputs & Assumptions'!$D$116+3+1),0) -> 547603.8 | H20: =IF(('Inputs & Assumptions'!$D$116+4)<='Inputs & Assumptions'!$C$13,INDEX('Inputs & Assumptions'!$D$70:$D$98,'Inputs & Assumptions'!$D$116+4+1),0) -> 531175.69 | I20: =IF(('Inputs & Assumptions'!$D$116+5)<='Inputs & Assumptions'!$C$13,INDEX('Inputs & Assumptions'!$D$70:$D$98,'Inputs & Assumptions'!$D$116+5+1),0) -> 515240.42 | J20: =IF(('Inputs & Assumptions'!$D$116+6)<='Inputs & Assumptions'!$C$13,INDEX('Inputs & Assumptions'!$D$70:$D$98,'Inputs & Assumptions'!$D$116+6+1),0) -> 499783.2 | K20: =IF(('Inputs & Assumptions'!$D$116+7)<='Inputs & Assumptions'!$C$13,INDEX('Inputs & Assumptions'!$D$70:$D$98,'Inputs & Assumptions'!$D$116+7+1),0) -> 484789.71 | L20: =IF(('Inputs & Assumptions'!$D$116+8)<='Inputs & Assumptions'!$C$13,INDEX('Inputs & Assumptions'!$D$70:$D$98,'Inputs & Assumptions'!$D$116+8+1),0) -> 470246.02 | M20: =IF(('Inputs & Assumptions'!$D$116+9)<='Inputs & Assumptions'!$C$13,INDEX('Inputs & Assumptions'!$D$70:$D$98,'Inputs & Assumptions'!$D$116+9+1),0) -> 456138.64 | N20: =IF(('Inputs & Assumptions'!$D$116+10)<='Inputs & Assumptions'!$C$13,INDEX('Inputs & Assumptions'!$D$70:$D$98,'Inputs & Assumptions'!$D$116+10+1),0) -> 442454.48 | O20: =IF(('Inputs & Assumptions'!$D$116+11)<='Inputs & Assumptions'!$C$13,INDEX('Inputs & Assumptions'!$D$70:$D$98,'Inputs & Assumptions'!$D$116+11+1),0) -> 429180.84 | P20: =IF(('Inputs & Assumptions'!$D$116+12)<='Inputs & Assumptions'!$C$13,INDEX('Inputs & Assumptions'!$D$70:$D$98,'Inputs & Assumptions'!$D$116+12+1),0) -> 416305.42 | Q20: =IF(('Inputs & Assumptions'!$D$116+13)<='Inputs & Assumptions'!$C$13,INDEX('Inputs & Assumptions'!$D$70:$D$98,'Inputs & Assumptions'!$D$116+13+1),0) -> 403816.25 | R20: =IF(('Inputs & Assumptions'!$D$116+14)<='Inputs & Assumptions'!$C$13,INDEX('Inputs & Assumptions'!$D$70:$D$98,'Inputs & Assumptions'!$D$116+14+1),0) -> 391701.77 | S20: =IF(('Inputs & Assumptions'!$D$116+15)<='Inputs & Assumptions'!$C$13,INDEX('Inputs & Assumptions'!$D$70:$D$98,'Inputs & Assumptions'!$D$116+15+1),0) -> 379950.71 | T20: =IF(('Inputs & Assumptions'!$D$116+16)<='Inputs & Assumptions'!$C$13,INDEX('Inputs & Assumptions'!$D$70:$D$98,'Inputs & Assumptions'!$D$116+16+1),0) -> 368552.19 | U20: =IF(('Inputs & Assumptions'!$D$116+17)<='Inputs & Assumptions'!$C$13,INDEX('Inputs & Assumptions'!$D$70:$D$98,'Inputs & Assumptions'!$D$116+17+1),0) -> 357495.63 | V20: =IF(('Inputs & Assumptions'!$D$116+18)<='Inputs & Assumptions'!$C$13,INDEX('Inputs & Assumptions'!$D$70:$D$98,'Inputs & Assumptions'!$D$116+18+1),0) -> 346770.76 | W20: =IF(('Inputs & Assumptions'!$D$116+19)<='Inputs & Assumptions'!$C$13,INDEX('Inputs & Assumptions'!$D$70:$D$98,'Inputs & Assumptions'!$D$116+19+1),0) -> 336367.63 | X20: =IF(('Inputs & Assumptions'!$D$116+20)<='Inputs & Assumptions'!$C$13,INDEX('Inputs & Assumptions'!$D$70:$D$98,'Inputs & Assumptions'!$D$116+20+1),0) -> 326276.61 | Y20: =IF(('Inputs & Assumptions'!$D$116+21)<='Inputs & Assumptions'!$C$13,INDEX('Inputs & Assumptions'!$D$70:$D$98,'Inputs & Assumptions'!$D$116+21+1),0) -> 316488.31 | Z20: =IF(('Inputs & Assumptions'!$D$116+22)<='Inputs & Assumptions'!$C$13,INDEX('Inputs & Assumptions'!$D$70:$D$98,'Inputs & Assumptions'!$D$116+22+1),0) -> 306993.66 | AA20: =IF(('Inputs & Assumptions'!$D$116+23)<='Inputs & Assumptions'!$C$13,INDEX('Inputs & Assumptions'!$D$70:$D$98,'Inputs & Assumptions'!$D$116+23+1),0) -> 9926128.3 | AB20: =IF(('Inputs & Assumptions'!$D$116+24)<='Inputs & Assumptions'!$C$13,INDEX('Inputs & Assumptions'!$D$70:$D$98,'Inputs & Assumptions'!$D$116+24+1),0) -> 0 | AC20: =IF(('Inputs & Assumptions'!$D$116+25)<='Inputs & Assumptions'!$C$13,INDEX('Inputs & Assumptions'!$D$70:$D$98,'Inputs & Assumptions'!$D$116+25+1),0) -> 0 | AD20: =IF(('Inputs & Assumptions'!$D$116+26)<='Inputs & Assumptions'!$C$13,INDEX('Inputs & Assumptions'!$D$70:$D$98,'Inputs & Assumptions'!$D$116+26+1),0) -> 0 | AE20: =IF(('Inputs & Assumptions'!$D$116+27)<='Inputs & Assumptions'!$C$13,INDEX('Inputs & Assumptions'!$D$70:$D$98,'Inputs & Assumptions'!$D$116+27+1),0) -> 0 | AF20: =IF(('Inputs & Assumptions'!$D$116+28)<='Inputs & Assumptions'!$C$13,INDEX('Inputs & Assumptions'!$D$70:$D$98,'Inputs & Assumptions'!$D$116+28+1),0) -> 0 | AG20: =IF(('Inputs & Assumptions'!$D$116+29)<='Inputs & Assumptions'!$C$13,INDEX('Inputs & Assumptions'!$D$70:$D$98,'Inputs & Assumptions'!$D$116+29+1),0) -> 0 | AH20: =IF(('Inputs & Assumptions'!$D$116+30)<='Inputs & Assumptions'!$C$13,INDEX('Inputs & Assumptions'!$D$70:$D$98,'Inputs & Assumptions'!$D$116+30+1),0) -> 0 | AI20: =IF(('Inputs & Assumptions'!$D$116+31)<='Inputs & Assumptions'!$C$13,INDEX('Inputs & Assumptions'!$D$70:$D$98,'Inputs & Assumptions'!$D$116+31+1),0) -> 0 | AJ20: =IF(('Inputs & Assumptions'!$D$116+32)<='Inputs & Assumptions'!$C$13,INDEX('Inputs & Assumptions'!$D$70:$D$98,'Inputs & Assumptions'!$D$116+32+1),0) -> 0 | AK20: =IF(('Inputs & Assumptions'!$D$116+33)<='Inputs & Assumptions'!$C$13,INDEX('Inputs & Assumptions'!$D$70:$D$98,'Inputs & Assumptions'!$D$116+33+1),0) -> 0 | AL20: =IF(('Inputs & Assumptions'!$D$116+34)<='Inputs & Assumptions'!$C$13,INDEX('Inputs & Assumptions'!$D$70:$D$98,'Inputs & Assumptions'!$D$116+34+1),0) -> 0 | AM20: =IF(('Inputs & Assumptions'!$D$116+35)<='Inputs & Assumptions'!$C$13,INDEX('Inputs & Assumptions'!$D$70:$D$98,'Inputs & Assumptions'!$D$116+35+1),0) -> 0 | AN20: =IF(('Inputs & Assumptions'!$D$116+36)<='Inputs & Assumptions'!$C$13,INDEX('Inputs & Assumptions'!$D$70:$D$98,'Inputs & Assumptions'!$D$116+36+1),0) -> 0
B21: ='Inputs & Assumptions'!$B$117 -> 16 | E21: =IF(('Inputs & Assumptions'!$D$117+1)<='Inputs & Assumptions'!$C$13,INDEX('Inputs & Assumptions'!$D$70:$D$98,'Inputs & Assumptions'!$D$117+1+1),0) -> 582000 | F21: =IF(('Inputs & Assumptions'!$D$117+2)<='Inputs & Assumptions'!$C$13,INDEX('Inputs & Assumptions'!$D$70:$D$98,'Inputs & Assumptions'!$D$117+2+1),0) -> 564540 | G21: =IF(('Inputs & Assumptions'!$D$117+3)<='Inputs & Assumptions'!$C$13,INDEX('Inputs & Assumptions'!$D$70:$D$98,'Inputs & Assumptions'!$D$117+3+1),0) -> 547603.8 | H21: =IF(('Inputs & Assumptions'!$D$117+4)<='Inputs & Assumptions'!$C$13,INDEX('Inputs & Assumptions'!$D$70:$D$98,'Inputs & Assumptions'!$D$117+4+1),0) -> 531175.69 | I21: =IF(('Inputs & Assumptions'!$D$117+5)<='Inputs & Assumptions'!$C$13,INDEX('Inputs & Assumptions'!$D$70:$D$98,'Inputs & Assumptions'!$D$117+5+1),0) -> 515240.42 | J21: =IF(('Inputs & Assumptions'!$D$117+6)<='Inputs & Assumptions'!$C$13,INDEX('Inputs & Assumptions'!$D$70:$D$98,'Inputs & Assumptions'!$D$117+6+1),0) -> 499783.2 | K21: =IF(('Inputs & Assumptions'!$D$117+7)<='Inputs & Assumptions'!$C$13,INDEX('Inputs & Assumptions'!$D$70:$D$98,'Inputs & Assumptions'!$D$117+7+1),0) -> 484789.71 | L21: =IF(('Inputs & Assumptions'!$D$117+8)<='Inputs & Assumptions'!$C$13,INDEX('Inputs & Assumptions'!$D$70:$D$98,'Inputs & Assumptions'!$D$117+8+1),0) -> 470246.02 | M21: =IF(('Inputs & Assumptions'!$D$117+9)<='Inputs & Assumptions'!$C$13,INDEX('Inputs & Assumptions'!$D$70:$D$98,'Inputs & Assumptions'!$D$117+9+1),0) -> 456138.64 | N21: =IF(('Inputs & Assumptions'!$D$117+10)<='Inputs & Assumptions'!$C$13,INDEX('Inputs & Assumptions'!$D$70:$D$98,'Inputs & Assumptions'!$D$117+10+1),0) -> 442454.48 | O21: =IF(('Inputs & Assumptions'!$D$117+11)<='Inputs & Assumptions'!$C$13,INDEX('Inputs & Assumptions'!$D$70:$D$98,'Inputs & Assumptions'!$D$117+11+1),0) -> 429180.84 | P21: =IF(('Inputs & Assumptions'!$D$117+12)<='Inputs & Assumptions'!$C$13,INDEX('Inputs & Assumptions'!$D$70:$D$98,'Inputs & Assumptions'!$D$117+12+1),0) -> 416305.42 | Q21: =IF(('Inputs & Assumptions'!$D$117+13)<='Inputs & Assumptions'!$C$13,INDEX('Inputs & Assumptions'!$D$70:$D$98,'Inputs & Assumptions'!$D$117+13+1),0) -> 403816.25 | R21: =IF(('Inputs & Assumptions'!$D$117+14)<='Inputs & Assumptions'!$C$13,INDEX('Inputs & Assumptions'!$D$70:$D$98,'Inputs & Assumptions'!$D$117+14+1),0) -> 391701.77 | S21: =IF(('Inputs & Assumptions'!$D$117+15)<='Inputs & Assumptions'!$C$13,INDEX('Inputs & Assumptions'!$D$70:$D$98,'Inputs & Assumptions'!$D$117+15+1),0) -> 379950.71 | T21: =IF(('Inputs & Assumptions'!$D$117+16)<='Inputs & Assumptions'!$C$13,INDEX('Inputs & Assumptions'!$D$70:$D$98,'Inputs & Assumptions'!$D$117+16+1),0) -> 368552.19 | U21: =IF(('Inputs & Assumptions'!$D$117+17)<='Inputs & Assumptions'!$C$13,INDEX('Inputs & Assumptions'!$D$70:$D$98,'Inputs & Assumptions'!$D$117+17+1),0) -> 357495.63 | V21: =IF(('Inputs & Assumptions'!$D$117+18)<='Inputs & Assumptions'!$C$13,INDEX('Inputs & Assumptions'!$D$70:$D$98,'Inputs & Assumptions'!$D$117+18+1),0) -> 346770.76 | W21: =IF(('Inputs & Assumptions'!$D$117+19)<='Inputs & Assumptions'!$C$13,INDEX('Inputs & Assumptions'!$D$70:$D$98,'Inputs & Assumptions'!$D$117+19+1),0) -> 336367.63 | X21: =IF(('Inputs & Assumptions'!$D$117+20)<='Inputs & Assumptions'!$C$13,INDEX('Inputs & Assumptions'!$D$70:$D$98,'Inputs & Assumptions'!$D$117+20+1),0) -> 326276.61 | Y21: =IF(('Inputs & Assumptions'!$D$117+21)<='Inputs & Assumptions'!$C$13,INDEX('Inputs & Assumptions'!$D$70:$D$98,'Inputs & Assumptions'!$D$117+21+1),0) -> 316488.31 | Z21: =IF(('Inputs & Assumptions'!$D$117+22)<='Inputs & Assumptions'!$C$13,INDEX('Inputs & Assumptions'!$D$70:$D$98,'Inputs & Assumptions'!$D$117+22+1),0) -> 306993.66 | AA21: =IF(('Inputs & Assumptions'!$D$117+23)<='Inputs & Assumptions'!$C$13,INDEX('Inputs & Assumptions'!$D$70:$D$98,'Inputs & Assumptions'!$D$117+23+1),0) -> 9926128.3 | AB21: =IF(('Inputs & Assumptions'!$D$117+24)<='Inputs & Assumptions'!$C$13,INDEX('Inputs & Assumptions'!$D$70:$D$98,'Inputs & Assumptions'!$D$117+24+1),0) -> 0 | AC21: =IF(('Inputs & Assumptions'!$D$117+25)<='Inputs & Assumptions'!$C$13,INDEX('Inputs & Assumptions'!$D$70:$D$98,'Inputs & Assumptions'!$D$117+25+1),0) -> 0 | AD21: =IF(('Inputs & Assumptions'!$D$117+26)<='Inputs & Assumptions'!$C$13,INDEX('Inputs & Assumptions'!$D$70:$D$98,'Inputs & Assumptions'!$D$117+26+1),0) -> 0 | AE21: =IF(('Inputs & Assumptions'!$D$117+27)<='Inputs & Assumptions'!$C$13,INDEX('Inputs & Assumptions'!$D$70:$D$98,'Inputs & Assumptions'!$D$117+27+1),0) -> 0 | AF21: =IF(('Inputs & Assumptions'!$D$117+28)<='Inputs & Assumptions'!$C$13,INDEX('Inputs & Assumptions'!$D$70:$D$98,'Inputs & Assumptions'!$D$117+28+1),0) -> 0 | AG21: =IF(('Inputs & Assumptions'!$D$117+29)<='Inputs & Assumptions'!$C$13,INDEX('Inputs & Assumptions'!$D$70:$D$98,'Inputs & Assumptions'!$D$117+29+1),0) -> 0 | AH21: =IF(('Inputs & Assumptions'!$D$117+30)<='Inputs & Assumptions'!$C$13,INDEX('Inputs & Assumptions'!$D$70:$D$98,'Inputs & Assumptions'!$D$117+30+1),0) -> 0 | AI21: =IF(('Inputs & Assumptions'!$D$117+31)<='Inputs & Assumptions'!$C$13,INDEX('Inputs & Assumptions'!$D$70:$D$98,'Inputs & Assumptions'!$D$117+31+1),0) -> 0 | AJ21: =IF(('Inputs & Assumptions'!$D$117+32)<='Inputs & Assumptions'!$C$13,INDEX('Inputs & Assumptions'!$D$70:$D$98,'Inputs & Assumptions'!$D$117+32+1),0) -> 0 | AK21: =IF(('Inputs & Assumptions'!$D$117+33)<='Inputs & Assumptions'!$C$13,INDEX('Inputs & Assumptions'!$D$70:$D$98,'Inputs & Assumptions'!$D$117+33+1),0) -> 0 | AL21: =IF(('Inputs & Assumptions'!$D$117+34)<='Inputs & Assumptions'!$C$13,INDEX('Inputs & Assumptions'!$D$70:$D$98,'Inputs & Assumptions'!$D$117+34+1),0) -> 0 | AM21: =IF(('Inputs & Assumptions'!$D$117+35)<='Inputs & Assumptions'!$C$13,INDEX('Inputs & Assumptions'!$D$70:$D$98,'Inputs & Assumptions'!$D$117+35+1),0) -> 0 | AN21: =IF(('Inputs & Assumptions'!$D$117+36)<='Inputs & Assumptions'!$C$13,INDEX('Inputs & Assumptions'!$D$70:$D$98,'Inputs & Assumptions'!$D$117+36+1),0) -> 0
B22: ='Inputs & Assumptions'!$B$118 -> 17 | E22: =IF(('Inputs & Assumptions'!$D$118+1)<='Inputs & Assumptions'!$C$13,INDEX('Inputs & Assumptions'!$D$70:$D$98,'Inputs & Assumptions'!$D$118+1+1),0) -> 564540 | F22: =IF(('Inputs & Assumptions'!$D$118+2)<='Inputs & Assumptions'!$C$13,INDEX('Inputs & Assumptions'!$D$70:$D$98,'Inputs & Assumptions'!$D$118+2+1),0) -> 547603.8 | G22: =IF(('Inputs & Assumptions'!$D$118+3)<='Inputs & Assumptions'!$C$13,INDEX('Inputs & Assumptions'!$D$70:$D$98,'Inputs & Assumptions'!$D$118+3+1),0) -> 531175.69 | H22: =IF(('Inputs & Assumptions'!$D$118+4)<='Inputs & Assumptions'!$C$13,INDEX('Inputs & Assumptions'!$D$70:$D$98,'Inputs & Assumptions'!$D$118+4+1),0) -> 515240.42 | I22: =IF(('Inputs & Assumptions'!$D$118+5)<='Inputs & Assumptions'!$C$13,INDEX('Inputs & Assumptions'!$D$70:$D$98,'Inputs & Assumptions'!$D$118+5+1),0) -> 499783.2 | J22: =IF(('Inputs & Assumptions'!$D$118+6)<='Inputs & Assumptions'!$C$13,INDEX('Inputs & Assumptions'!$D$70:$D$98,'Inputs & Assumptions'!$D$118+6+1),0) -> 484789.71 | K22: =IF(('Inputs & Assumptions'!$D$118+7)<='Inputs & Assumptions'!$C$13,INDEX('Inputs & Assumptions'!$D$70:$D$98,'Inputs & Assumptions'!$D$118+7+1),0) -> 470246.02 | L22: =IF(('Inputs & Assumptions'!$D$118+8)<='Inputs & Assumptions'!$C$13,INDEX('Inputs & Assumptions'!$D$70:$D$98,'Inputs & Assumptions'!$D$118+8+1),0) -> 456138.64 | M22: =IF(('Inputs & Assumptions'!$D$118+9)<='Inputs & Assumptions'!$C$13,INDEX('Inputs & Assumptions'!$D$70:$D$98,'Inputs & Assumptions'!$D$118+9+1),0) -> 442454.48 | N22: =IF(('Inputs & Assumptions'!$D$118+10)<='Inputs & Assumptions'!$C$13,INDEX('Inputs & Assumptions'!$D$70:$D$98,'Inputs & Assumptions'!$D$118+10+1),0) -> 429180.84 | O22: =IF(('Inputs & Assumptions'!$D$118+11)<='Inputs & Assumptions'!$C$13,INDEX('Inputs & Assumptions'!$D$70:$D$98,'Inputs & Assumptions'!$D$118+11+1),0) -> 416305.42 | P22: =IF(('Inputs & Assumptions'!$D$118+12)<='Inputs & Assumptions'!$C$13,INDEX('Inputs & Assumptions'!$D$70:$D$98,'Inputs & Assumptions'!$D$118+12+1),0) -> 403816.25 | Q22: =IF(('Inputs & Assumptions'!$D$118+13)<='Inputs & Assumptions'!$C$13,INDEX('Inputs & Assumptions'!$D$70:$D$98,'Inputs & Assumptions'!$D$118+13+1),0) -> 391701.77 | R22: =IF(('Inputs & Assumptions'!$D$118+14)<='Inputs & Assumptions'!$C$13,INDEX('Inputs & Assumptions'!$D$70:$D$98,'Inputs & Assumptions'!$D$118+14+1),0) -> 379950.71 | S22: =IF(('Inputs & Assumptions'!$D$118+15)<='Inputs & Assumptions'!$C$13,INDEX('Inputs & Assumptions'!$D$70:$D$98,'Inputs & Assumptions'!$D$118+15+1),0) -> 368552.19 | T22: =IF(('Inputs & Assumptions'!$D$118+16)<='Inputs & Assumptions'!$C$13,INDEX('Inputs & Assumptions'!$D$70:$D$98,'Inputs & Assumptions'!$D$118+16+1),0) -> 357495.63 | U22: =IF(('Inputs & Assumptions'!$D$118+17)<='Inputs & Assumptions'!$C$13,INDEX('Inputs & Assumptions'!$D$70:$D$98,'Inputs & Assumptions'!$D$118+17+1),0) -> 346770.76 | V22: =IF(('Inputs & Assumptions'!$D$118+18)<='Inputs & Assumptions'!$C$13,INDEX('Inputs & Assumptions'!$D$70:$D$98,'Inputs & Assumptions'!$D$118+18+1),0) -> 336367.63 | W22: =IF(('Inputs & Assumptions'!$D$118+19)<='Inputs & Assumptions'!$C$13,INDEX('Inputs & Assumptions'!$D$70:$D$98,'Inputs & Assumptions'!$D$118+19+1),0) -> 326276.61 | X22: =IF(('Inputs & Assumptions'!$D$118+20)<='Inputs & Assumptions'!$C$13,INDEX('Inputs & Assumptions'!$D$70:$D$98,'Inputs & Assumptions'!$D$118+20+1),0) -> 316488.31 | Y22: =IF(('Inputs & Assumptions'!$D$118+21)<='Inputs & Assumptions'!$C$13,INDEX('Inputs & Assumptions'!$D$70:$D$98,'Inputs & Assumptions'!$D$118+21+1),0) -> 306993.66 | Z22: =IF(('Inputs & Assumptions'!$D$118+22)<='Inputs & Assumptions'!$C$13,INDEX('Inputs & Assumptions'!$D$70:$D$98,'Inputs & Assumptions'!$D$118+22+1),0) -> 9926128.3 | AA22: =IF(('Inputs & Assumptions'!$D$118+23)<='Inputs & Assumptions'!$C$13,INDEX('Inputs & Assumptions'!$D$70:$D$98,'Inputs & Assumptions'!$D$118+23+1),0) -> 0 | AB22: =IF(('Inputs & Assumptions'!$D$118+24)<='Inputs & Assumptions'!$C$13,INDEX('Inputs & Assumptions'!$D$70:$D$98,'Inputs & Assumptions'!$D$118+24+1),0) -> 0 | AC22: =IF(('Inputs & Assumptions'!$D$118+25)<='Inputs & Assumptions'!$C$13,INDEX('Inputs & Assumptions'!$D$70:$D$98,'Inputs & Assumptions'!$D$118+25+1),0) -> 0 | AD22: =IF(('Inputs & Assumptions'!$D$118+26)<='Inputs & Assumptions'!$C$13,INDEX('Inputs & Assumptions'!$D$70:$D$98,'Inputs & Assumptions'!$D$118+26+1),0) -> 0 | AE22: =IF(('Inputs & Assumptions'!$D$118+27)<='Inputs & Assumptions'!$C$13,INDEX('Inputs & Assumptions'!$D$70:$D$98,'Inputs & Assumptions'!$D$118+27+1),0) -> 0 | AF22: =IF(('Inputs & Assumptions'!$D$118+28)<='Inputs & Assumptions'!$C$13,INDEX('Inputs & Assumptions'!$D$70:$D$98,'Inputs & Assumptions'!$D$118+28+1),0) -> 0 | AG22: =IF(('Inputs & Assumptions'!$D$118+29)<='Inputs & Assumptions'!$C$13,INDEX('Inputs & Assumptions'!$D$70:$D$98,'Inputs & Assumptions'!$D$118+29+1),0) -> 0 | AH22: =IF(('Inputs & Assumptions'!$D$118+30)<='Inputs & Assumptions'!$C$13,INDEX('Inputs & Assumptions'!$D$70:$D$98,'Inputs & Assumptions'!$D$118+30+1),0) -> 0 | AI22: =IF(('Inputs & Assumptions'!$D$118+31)<='Inputs & Assumptions'!$C$13,INDEX('Inputs & Assumptions'!$D$70:$D$98,'Inputs & Assumptions'!$D$118+31+1),0) -> 0 | AJ22: =IF(('Inputs & Assumptions'!$D$118+32)<='Inputs & Assumptions'!$C$13,INDEX('Inputs & Assumptions'!$D$70:$D$98,'Inputs & Assumptions'!$D$118+32+1),0) -> 0 | AK22: =IF(('Inputs & Assumptions'!$D$118+33)<='Inputs & Assumptions'!$C$13,INDEX('Inputs & Assumptions'!$D$70:$D$98,'Inputs & Assumptions'!$D$118+33+1),0) -> 0 | AL22: =IF(('Inputs & Assumptions'!$D$118+34)<='Inputs & Assumptions'!$C$13,INDEX('Inputs & Assumptions'!$D$70:$D$98,'Inputs & Assumptions'!$D$118+34+1),0) -> 0 | AM22: =IF(('Inputs & Assumptions'!$D$118+35)<='Inputs & Assumptions'!$C$13,INDEX('Inputs & Assumptions'!$D$70:$D$98,'Inputs & Assumptions'!$D$118+35+1),0) -> 0 | AN22: =IF(('Inputs & Assumptions'!$D$118+36)<='Inputs & Assumptions'!$C$13,INDEX('Inputs & Assumptions'!$D$70:$D$98,'Inputs & Assumptions'!$D$118+36+1),0) -> 0
B23: ='Inputs & Assumptions'!$B$119 -> 18 | E23: =IF(('Inputs & Assumptions'!$D$119+1)<='Inputs & Assumptions'!$C$13,INDEX('Inputs & Assumptions'!$D$70:$D$98,'Inputs & Assumptions'!$D$119+1+1),0) -> 564540 | F23: =IF(('Inputs & Assumptions'!$D$119+2)<='Inputs & Assumptions'!$C$13,INDEX('Inputs & Assumptions'!$D$70:$D$98,'Inputs & Assumptions'!$D$119+2+1),0) -> 547603.8 | G23: =IF(('Inputs & Assumptions'!$D$119+3)<='Inputs & Assumptions'!$C$13,INDEX('Inputs & Assumptions'!$D$70:$D$98,'Inputs & Assumptions'!$D$119+3+1),0) -> 531175.69 | H23: =IF(('Inputs & Assumptions'!$D$119+4)<='Inputs & Assumptions'!$C$13,INDEX('Inputs & Assumptions'!$D$70:$D$98,'Inputs & Assumptions'!$D$119+4+1),0) -> 515240.42 | I23: =IF(('Inputs & Assumptions'!$D$119+5)<='Inputs & Assumptions'!$C$13,INDEX('Inputs & Assumptions'!$D$70:$D$98,'Inputs & Assumptions'!$D$119+5+1),0) -> 499783.2 | J23: =IF(('Inputs & Assumptions'!$D$119+6)<='Inputs & Assumptions'!$C$13,INDEX('Inputs & Assumptions'!$D$70:$D$98,'Inputs & Assumptions'!$D$119+6+1),0) -> 484789.71 | K23: =IF(('Inputs & Assumptions'!$D$119+7)<='Inputs & Assumptions'!$C$13,INDEX('Inputs & Assumptions'!$D$70:$D$98,'Inputs & Assumptions'!$D$119+7+1),0) -> 470246.02 | L23: =IF(('Inputs & Assumptions'!$D$119+8)<='Inputs & Assumptions'!$C$13,INDEX('Inputs & Assumptions'!$D$70:$D$98,'Inputs & Assumptions'!$D$119+8+1),0) -> 456138.64 | M23: =IF(('Inputs & Assumptions'!$D$119+9)<='Inputs & Assumptions'!$C$13,INDEX('Inputs & Assumptions'!$D$70:$D$98,'Inputs & Assumptions'!$D$119+9+1),0) -> 442454.48 | N23: =IF(('Inputs & Assumptions'!$D$119+10)<='Inputs & Assumptions'!$C$13,INDEX('Inputs & Assumptions'!$D$70:$D$98,'Inputs & Assumptions'!$D$119+10+1),0) -> 429180.84 | O23: =IF(('Inputs & Assumptions'!$D$119+11)<='Inputs & Assumptions'!$C$13,INDEX('Inputs & Assumptions'!$D$70:$D$98,'Inputs & Assumptions'!$D$119+11+1),0) -> 416305.42 | P23: =IF(('Inputs & Assumptions'!$D$119+12)<='Inputs & Assumptions'!$C$13,INDEX('Inputs & Assumptions'!$D$70:$D$98,'Inputs & Assumptions'!$D$119+12+1),0) -> 403816.25 | Q23: =IF(('Inputs & Assumptions'!$D$119+13)<='Inputs & Assumptions'!$C$13,INDEX('Inputs & Assumptions'!$D$70:$D$98,'Inputs & Assumptions'!$D$119+13+1),0) -> 391701.77 | R23: =IF(('Inputs & Assumptions'!$D$119+14)<='Inputs & Assumptions'!$C$13,INDEX('Inputs & Assumptions'!$D$70:$D$98,'Inputs & Assumptions'!$D$119+14+1),0) -> 379950.71 | S23: =IF(('Inputs & Assumptions'!$D$119+15)<='Inputs & Assumptions'!$C$13,INDEX('Inputs & Assumptions'!$D$70:$D$98,'Inputs & Assumptions'!$D$119+15+1),0) -> 368552.19 | T23: =IF(('Inputs & Assumptions'!$D$119+16)<='Inputs & Assumptions'!$C$13,INDEX('Inputs & Assumptions'!$D$70:$D$98,'Inputs & Assumptions'!$D$119+16+1),0) -> 357495.63 | U23: =IF(('Inputs & Assumptions'!$D$119+17)<='Inputs & Assumptions'!$C$13,INDEX('Inputs & Assumptions'!$D$70:$D$98,'Inputs & Assumptions'!$D$119+17+1),0) -> 346770.76 | V23: =IF(('Inputs & Assumptions'!$D$119+18)<='Inputs & Assumptions'!$C$13,INDEX('Inputs & Assumptions'!$D$70:$D$98,'Inputs & Assumptions'!$D$119+18+1),0) -> 336367.63 | W23: =IF(('Inputs & Assumptions'!$D$119+19)<='Inputs & Assumptions'!$C$13,INDEX('Inputs & Assumptions'!$D$70:$D$98,'Inputs & Assumptions'!$D$119+19+1),0) -> 326276.61 | X23: =IF(('Inputs & Assumptions'!$D$119+20)<='Inputs & Assumptions'!$C$13,INDEX('Inputs & Assumptions'!$D$70:$D$98,'Inputs & Assumptions'!$D$119+20+1),0) -> 316488.31 | Y23: =IF(('Inputs & Assumptions'!$D$119+21)<='Inputs & Assumptions'!$C$13,INDEX('Inputs & Assumptions'!$D$70:$D$98,'Inputs & Assumptions'!$D$119+21+1),0) -> 306993.66 | Z23: =IF(('Inputs & Assumptions'!$D$119+22)<='Inputs & Assumptions'!$C$13,INDEX('Inputs & Assumptions'!$D$70:$D$98,'Inputs & Assumptions'!$D$119+22+1),0) -> 9926128.3 | AA23: =IF(('Inputs & Assumptions'!$D$119+23)<='Inputs & Assumptions'!$C$13,INDEX('Inputs & Assumptions'!$D$70:$D$98,'Inputs & Assumptions'!$D$119+23+1),0) -> 0 | AB23: =IF(('Inputs & Assumptions'!$D$119+24)<='Inputs & Assumptions'!$C$13,INDEX('Inputs & Assumptions'!$D$70:$D$98,'Inputs & Assumptions'!$D$119+24+1),0) -> 0 | AC23: =IF(('Inputs & Assumptions'!$D$119+25)<='Inputs & Assumptions'!$C$13,INDEX('Inputs & Assumptions'!$D$70:$D$98,'Inputs & Assumptions'!$D$119+25+1),0) -> 0 | AD23: =IF(('Inputs & Assumptions'!$D$119+26)<='Inputs & Assumptions'!$C$13,INDEX('Inputs & Assumptions'!$D$70:$D$98,'Inputs & Assumptions'!$D$119+26+1),0) -> 0 | AE23: =IF(('Inputs & Assumptions'!$D$119+27)<='Inputs & Assumptions'!$C$13,INDEX('Inputs & Assumptions'!$D$70:$D$98,'Inputs & Assumptions'!$D$119+27+1),0) -> 0 | AF23: =IF(('Inputs & Assumptions'!$D$119+28)<='Inputs & Assumptions'!$C$13,INDEX('Inputs & Assumptions'!$D$70:$D$98,'Inputs & Assumptions'!$D$119+28+1),0) -> 0 | AG23: =IF(('Inputs & Assumptions'!$D$119+29)<='Inputs & Assumptions'!$C$13,INDEX('Inputs & Assumptions'!$D$70:$D$98,'Inputs & Assumptions'!$D$119+29+1),0) -> 0 | AH23: =IF(('Inputs & Assumptions'!$D$119+30)<='Inputs & Assumptions'!$C$13,INDEX('Inputs & Assumptions'!$D$70:$D$98,'Inputs & Assumptions'!$D$119+30+1),0) -> 0 | AI23: =IF(('Inputs & Assumptions'!$D$119+31)<='Inputs & Assumptions'!$C$13,INDEX('Inputs & Assumptions'!$D$70:$D$98,'Inputs & Assumptions'!$D$119+31+1),0) -> 0 | AJ23: =IF(('Inputs & Assumptions'!$D$119+32)<='Inputs & Assumptions'!$C$13,INDEX('Inputs & Assumptions'!$D$70:$D$98,'Inputs & Assumptions'!$D$119+32+1),0) -> 0 | AK23: =IF(('Inputs & Assumptions'!$D$119+33)<='Inputs & Assumptions'!$C$13,INDEX('Inputs & Assumptions'!$D$70:$D$98,'Inputs & Assumptions'!$D$119+33+1),0) -> 0 | AL23: =IF(('Inputs & Assumptions'!$D$119+34)<='Inputs & Assumptions'!$C$13,INDEX('Inputs & Assumptions'!$D$70:$D$98,'Inputs & Assumptions'!$D$119+34+1),0) -> 0 | AM23: =IF(('Inputs & Assumptions'!$D$119+35)<='Inputs & Assumptions'!$C$13,INDEX('Inputs & Assumptions'!$D$70:$D$98,'Inputs & Assumptions'!$D$119+35+1),0) -> 0 | AN23: =IF(('Inputs & Assumptions'!$D$119+36)<='Inputs & Assumptions'!$C$13,INDEX('Inputs & Assumptions'!$D$70:$D$98,'Inputs & Assumptions'!$D$119+36+1),0) -> 0
B24: ='Inputs & Assumptions'!$B$120 -> 19 | E24: =IF(('Inputs & Assumptions'!$D$120+1)<='Inputs & Assumptions'!$C$13,INDEX('Inputs & Assumptions'!$D$70:$D$98,'Inputs & Assumptions'!$D$120+1+1),0) -> 564540 | F24: =IF(('Inputs & Assumptions'!$D$120+2)<='Inputs & Assumptions'!$C$13,INDEX('Inputs & Assumptions'!$D$70:$D$98,'Inputs & Assumptions'!$D$120+2+1),0) -> 547603.8 | G24: =IF(('Inputs & Assumptions'!$D$120+3)<='Inputs & Assumptions'!$C$13,INDEX('Inputs & Assumptions'!$D$70:$D$98,'Inputs & Assumptions'!$D$120+3+1),0) -> 531175.69 | H24: =IF(('Inputs & Assumptions'!$D$120+4)<='Inputs & Assumptions'!$C$13,INDEX('Inputs & Assumptions'!$D$70:$D$98,'Inputs & Assumptions'!$D$120+4+1),0) -> 515240.42 | I24: =IF(('Inputs & Assumptions'!$D$120+5)<='Inputs & Assumptions'!$C$13,INDEX('Inputs & Assumptions'!$D$70:$D$98,'Inputs & Assumptions'!$D$120+5+1),0) -> 499783.2 | J24: =IF(('Inputs & Assumptions'!$D$120+6)<='Inputs & Assumptions'!$C$13,INDEX('Inputs & Assumptions'!$D$70:$D$98,'Inputs & Assumptions'!$D$120+6+1),0) -> 484789.71 | K24: =IF(('Inputs & Assumptions'!$D$120+7)<='Inputs & Assumptions'!$C$13,INDEX('Inputs & Assumptions'!$D$70:$D$98,'Inputs & Assumptions'!$D$120+7+1),0) -> 470246.02 | L24: =IF(('Inputs & Assumptions'!$D$120+8)<='Inputs & Assumptions'!$C$13,INDEX('Inputs & Assumptions'!$D$70:$D$98,'Inputs & Assumptions'!$D$120+8+1),0) -> 456138.64 | M24: =IF(('Inputs & Assumptions'!$D$120+9)<='Inputs & Assumptions'!$C$13,INDEX('Inputs & Assumptions'!$D$70:$D$98,'Inputs & Assumptions'!$D$120+9+1),0) -> 442454.48 | N24: =IF(('Inputs & Assumptions'!$D$120+10)<='Inputs & Assumptions'!$C$13,INDEX('Inputs & Assumptions'!$D$70:$D$98,'Inputs & Assumptions'!$D$120+10+1),0) -> 429180.84 | O24: =IF(('Inputs & Assumptions'!$D$120+11)<='Inputs & Assumptions'!$C$13,INDEX('Inputs & Assumptions'!$D$70:$D$98,'Inputs & Assumptions'!$D$120+11+1),0) -> 416305.42 | P24: =IF(('Inputs & Assumptions'!$D$120+12)<='Inputs & Assumptions'!$C$13,INDEX('Inputs & Assumptions'!$D$70:$D$98,'Inputs & Assumptions'!$D$120+12+1),0) -> 403816.25 | Q24: =IF(('Inputs & Assumptions'!$D$120+13)<='Inputs & Assumptions'!$C$13,INDEX('Inputs & Assumptions'!$D$70:$D$98,'Inputs & Assumptions'!$D$120+13+1),0) -> 391701.77 | R24: =IF(('Inputs & Assumptions'!$D$120+14)<='Inputs & Assumptions'!$C$13,INDEX('Inputs & Assumptions'!$D$70:$D$98,'Inputs & Assumptions'!$D$120+14+1),0) -> 379950.71 | S24: =IF(('Inputs & Assumptions'!$D$120+15)<='Inputs & Assumptions'!$C$13,INDEX('Inputs & Assumptions'!$D$70:$D$98,'Inputs & Assumptions'!$D$120+15+1),0) -> 368552.19 | T24: =IF(('Inputs & Assumptions'!$D$120+16)<='Inputs & Assumptions'!$C$13,INDEX('Inputs & Assumptions'!$D$70:$D$98,'Inputs & Assumptions'!$D$120+16+1),0) -> 357495.63 | U24: =IF(('Inputs & Assumptions'!$D$120+17)<='Inputs & Assumptions'!$C$13,INDEX('Inputs & Assumptions'!$D$70:$D$98,'Inputs & Assumptions'!$D$120+17+1),0) -> 346770.76 | V24: =IF(('Inputs & Assumptions'!$D$120+18)<='Inputs & Assumptions'!$C$13,INDEX('Inputs & Assumptions'!$D$70:$D$98,'Inputs & Assumptions'!$D$120+18+1),0) -> 336367.63 | W24: =IF(('Inputs & Assumptions'!$D$120+19)<='Inputs & Assumptions'!$C$13,INDEX('Inputs & Assumptions'!$D$70:$D$98,'Inputs & Assumptions'!$D$120+19+1),0) -> 326276.61 | X24: =IF(('Inputs & Assumptions'!$D$120+20)<='Inputs & Assumptions'!$C$13,INDEX('Inputs & Assumptions'!$D$70:$D$98,'Inputs & Assumptions'!$D$120+20+1),0) -> 316488.31 | Y24: =IF(('Inputs & Assumptions'!$D$120+21)<='Inputs & Assumptions'!$C$13,INDEX('Inputs & Assumptions'!$D$70:$D$98,'Inputs & Assumptions'!$D$120+21+1),0) -> 306993.66 | Z24: =IF(('Inputs & Assumptions'!$D$120+22)<='Inputs & Assumptions'!$C$13,INDEX('Inputs & Assumptions'!$D$70:$D$98,'Inputs & Assumptions'!$D$120+22+1),0) -> 9926128.3 | AA24: =IF(('Inputs & Assumptions'!$D$120+23)<='Inputs & Assumptions'!$C$13,INDEX('Inputs & Assumptions'!$D$70:$D$98,'Inputs & Assumptions'!$D$120+23+1),0) -> 0 | AB24: =IF(('Inputs & Assumptions'!$D$120+24)<='Inputs & Assumptions'!$C$13,INDEX('Inputs & Assumptions'!$D$70:$D$98,'Inputs & Assumptions'!$D$120+24+1),0) -> 0 | AC24: =IF(('Inputs & Assumptions'!$D$120+25)<='Inputs & Assumptions'!$C$13,INDEX('Inputs & Assumptions'!$D$70:$D$98,'Inputs & Assumptions'!$D$120+25+1),0) -> 0 | AD24: =IF(('Inputs & Assumptions'!$D$120+26)<='Inputs & Assumptions'!$C$13,INDEX('Inputs & Assumptions'!$D$70:$D$98,'Inputs & Assumptions'!$D$120+26+1),0) -> 0 | AE24: =IF(('Inputs & Assumptions'!$D$120+27)<='Inputs & Assumptions'!$C$13,INDEX('Inputs & Assumptions'!$D$70:$D$98,'Inputs & Assumptions'!$D$120+27+1),0) -> 0 | AF24: =IF(('Inputs & Assumptions'!$D$120+28)<='Inputs & Assumptions'!$C$13,INDEX('Inputs & Assumptions'!$D$70:$D$98,'Inputs & Assumptions'!$D$120+28+1),0) -> 0 | AG24: =IF(('Inputs & Assumptions'!$D$120+29)<='Inputs & Assumptions'!$C$13,INDEX('Inputs & Assumptions'!$D$70:$D$98,'Inputs & Assumptions'!$D$120+29+1),0) -> 0 | AH24: =IF(('Inputs & Assumptions'!$D$120+30)<='Inputs & Assumptions'!$C$13,INDEX('Inputs & Assumptions'!$D$70:$D$98,'Inputs & Assumptions'!$D$120+30+1),0) -> 0 | AI24: =IF(('Inputs & Assumptions'!$D$120+31)<='Inputs & Assumptions'!$C$13,INDEX('Inputs & Assumptions'!$D$70:$D$98,'Inputs & Assumptions'!$D$120+31+1),0) -> 0 | AJ24: =IF(('Inputs & Assumptions'!$D$120+32)<='Inputs & Assumptions'!$C$13,INDEX('Inputs & Assumptions'!$D$70:$D$98,'Inputs & Assumptions'!$D$120+32+1),0) -> 0 | AK24: =IF(('Inputs & Assumptions'!$D$120+33)<='Inputs & Assumptions'!$C$13,INDEX('Inputs & Assumptions'!$D$70:$D$98,'Inputs & Assumptions'!$D$120+33+1),0) -> 0 | AL24: =IF(('Inputs & Assumptions'!$D$120+34)<='Inputs & Assumptions'!$C$13,INDEX('Inputs & Assumptions'!$D$70:$D$98,'Inputs & Assumptions'!$D$120+34+1),0) -> 0 | AM24: =IF(('Inputs & Assumptions'!$D$120+35)<='Inputs & Assumptions'!$C$13,INDEX('Inputs & Assumptions'!$D$70:$D$98,'Inputs & Assumptions'!$D$120+35+1),0) -> 0 | AN24: =IF(('Inputs & Assumptions'!$D$120+36)<='Inputs & Assumptions'!$C$13,INDEX('Inputs & Assumptions'!$D$70:$D$98,'Inputs & Assumptions'!$D$120+36+1),0) -> 0
B25: ='Inputs & Assumptions'!$B$121 -> 20 | E25: =IF(('Inputs & Assumptions'!$D$121+1)<='Inputs & Assumptions'!$C$13,INDEX('Inputs & Assumptions'!$D$70:$D$98,'Inputs & Assumptions'!$D$121+1+1),0) -> 547603.8 | F25: =IF(('Inputs & Assumptions'!$D$121+2)<='Inputs & Assumptions'!$C$13,INDEX('Inputs & Assumptions'!$D$70:$D$98,'Inputs & Assumptions'!$D$121+2+1),0) -> 531175.69 | G25: =IF(('Inputs & Assumptions'!$D$121+3)<='Inputs & Assumptions'!$C$13,INDEX('Inputs & Assumptions'!$D$70:$D$98,'Inputs & Assumptions'!$D$121+3+1),0) -> 515240.42 | H25: =IF(('Inputs & Assumptions'!$D$121+4)<='Inputs & Assumptions'!$C$13,INDEX('Inputs & Assumptions'!$D$70:$D$98,'Inputs & Assumptions'!$D$121+4+1),0) -> 499783.2 | I25: =IF(('Inputs & Assumptions'!$D$121+5)<='Inputs & Assumptions'!$C$13,INDEX('Inputs & Assumptions'!$D$70:$D$98,'Inputs & Assumptions'!$D$121+5+1),0) -> 484789.71 | J25: =IF(('Inputs & Assumptions'!$D$121+6)<='Inputs & Assumptions'!$C$13,INDEX('Inputs & Assumptions'!$D$70:$D$98,'Inputs & Assumptions'!$D$121+6+1),0) -> 470246.02 | K25: =IF(('Inputs & Assumptions'!$D$121+7)<='Inputs & Assumptions'!$C$13,INDEX('Inputs & Assumptions'!$D$70:$D$98,'Inputs & Assumptions'!$D$121+7+1),0) -> 456138.64 | L25: =IF(('Inputs & Assumptions'!$D$121+8)<='Inputs & Assumptions'!$C$13,INDEX('Inputs & Assumptions'!$D$70:$D$98,'Inputs & Assumptions'!$D$121+8+1),0) -> 442454.48 | M25: =IF(('Inputs & Assumptions'!$D$121+9)<='Inputs & Assumptions'!$C$13,INDEX('Inputs & Assumptions'!$D$70:$D$98,'Inputs & Assumptions'!$D$121+9+1),0) -> 429180.84 | N25: =IF(('Inputs & Assumptions'!$D$121+10)<='Inputs & Assumptions'!$C$13,INDEX('Inputs & Assumptions'!$D$70:$D$98,'Inputs & Assumptions'!$D$121+10+1),0) -> 416305.42 | O25: =IF(('Inputs & Assumptions'!$D$121+11)<='Inputs & Assumptions'!$C$13,INDEX('Inputs & Assumptions'!$D$70:$D$98,'Inputs & Assumptions'!$D$121+11+1),0) -> 403816.25 | P25: =IF(('Inputs & Assumptions'!$D$121+12)<='Inputs & Assumptions'!$C$13,INDEX('Inputs & Assumptions'!$D$70:$D$98,'Inputs & Assumptions'!$D$121+12+1),0) -> 391701.77 | Q25: =IF(('Inputs & Assumptions'!$D$121+13)<='Inputs & Assumptions'!$C$13,INDEX('Inputs & Assumptions'!$D$70:$D$98,'Inputs & Assumptions'!$D$121+13+1),0) -> 379950.71 | R25: =IF(('Inputs & Assumptions'!$D$121+14)<='Inputs & Assumptions'!$C$13,INDEX('Inputs & Assumptions'!$D$70:$D$98,'Inputs & Assumptions'!$D$121+14+1),0) -> 368552.19 | S25: =IF(('Inputs & Assumptions'!$D$121+15)<='Inputs & Assumptions'!$C$13,INDEX('Inputs & Assumptions'!$D$70:$D$98,'Inputs & Assumptions'!$D$121+15+1),0) -> 357495.63 | T25: =IF(('Inputs & Assumptions'!$D$121+16)<='Inputs & Assumptions'!$C$13,INDEX('Inputs & Assumptions'!$D$70:$D$98,'Inputs & Assumptions'!$D$121+16+1),0) -> 346770.76 | U25: =IF(('Inputs & Assumptions'!$D$121+17)<='Inputs & Assumptions'!$C$13,INDEX('Inputs & Assumptions'!$D$70:$D$98,'Inputs & Assumptions'!$D$121+17+1),0) -> 336367.63 | V25: =IF(('Inputs & Assumptions'!$D$121+18)<='Inputs & Assumptions'!$C$13,INDEX('Inputs & Assumptions'!$D$70:$D$98,'Inputs & Assumptions'!$D$121+18+1),0) -> 326276.61 | W25: =IF(('Inputs & Assumptions'!$D$121+19)<='Inputs & Assumptions'!$C$13,INDEX('Inputs & Assumptions'!$D$70:$D$98,'Inputs & Assumptions'!$D$121+19+1),0) -> 316488.31 | X25: =IF(('Inputs & Assumptions'!$D$121+20)<='Inputs & Assumptions'!$C$13,INDEX('Inputs & Assumptions'!$D$70:$D$98,'Inputs & Assumptions'!$D$121+20+1),0) -> 306993.66 | Y25: =IF(('Inputs & Assumptions'!$D$121+21)<='Inputs & Assumptions'!$C$13,INDEX('Inputs & Assumptions'!$D$70:$D$98,'Inputs & Assumptions'!$D$121+21+1),0) -> 9926128.3 | Z25: =IF(('Inputs & Assumptions'!$D$121+22)<='Inputs & Assumptions'!$C$13,INDEX('Inputs & Assumptions'!$D$70:$D$98,'Inputs & Assumptions'!$D$121+22+1),0) -> 0 | AA25: =IF(('Inputs & Assumptions'!$D$121+23)<='Inputs & Assumptions'!$C$13,INDEX('Inputs & Assumptions'!$D$70:$D$98,'Inputs & Assumptions'!$D$121+23+1),0) -> 0 | AB25: =IF(('Inputs & Assumptions'!$D$121+24)<='Inputs & Assumptions'!$C$13,INDEX('Inputs & Assumptions'!$D$70:$D$98,'Inputs & Assumptions'!$D$121+24+1),0) -> 0 | AC25: =IF(('Inputs & Assumptions'!$D$121+25)<='Inputs & Assumptions'!$C$13,INDEX('Inputs & Assumptions'!$D$70:$D$98,'Inputs & Assumptions'!$D$121+25+1),0) -> 0 | AD25: =IF(('Inputs & Assumptions'!$D$121+26)<='Inputs & Assumptions'!$C$13,INDEX('Inputs & Assumptions'!$D$70:$D$98,'Inputs & Assumptions'!$D$121+26+1),0) -> 0 | AE25: =IF(('Inputs & Assumptions'!$D$121+27)<='Inputs & Assumptions'!$C$13,INDEX('Inputs & Assumptions'!$D$70:$D$98,'Inputs & Assumptions'!$D$121+27+1),0) -> 0 | AF25: =IF(('Inputs & Assumptions'!$D$121+28)<='Inputs & Assumptions'!$C$13,INDEX('Inputs & Assumptions'!$D$70:$D$98,'Inputs & Assumptions'!$D$121+28+1),0) -> 0 | AG25: =IF(('Inputs & Assumptions'!$D$121+29)<='Inputs & Assumptions'!$C$13,INDEX('Inputs & Assumptions'!$D$70:$D$98,'Inputs & Assumptions'!$D$121+29+1),0) -> 0 | AH25: =IF(('Inputs & Assumptions'!$D$121+30)<='Inputs & Assumptions'!$C$13,INDEX('Inputs & Assumptions'!$D$70:$D$98,'Inputs & Assumptions'!$D$121+30+1),0) -> 0 | AI25: =IF(('Inputs & Assumptions'!$D$121+31)<='Inputs & Assumptions'!$C$13,INDEX('Inputs & Assumptions'!$D$70:$D$98,'Inputs & Assumptions'!$D$121+31+1),0) -> 0 | AJ25: =IF(('Inputs & Assumptions'!$D$121+32)<='Inputs & Assumptions'!$C$13,INDEX('Inputs & Assumptions'!$D$70:$D$98,'Inputs & Assumptions'!$D$121+32+1),0) -> 0 | AK25: =IF(('Inputs & Assumptions'!$D$121+33)<='Inputs & Assumptions'!$C$13,INDEX('Inputs & Assumptions'!$D$70:$D$98,'Inputs & Assumptions'!$D$121+33+1),0) -> 0 | AL25: =IF(('Inputs & Assumptions'!$D$121+34)<='Inputs & Assumptions'!$C$13,INDEX('Inputs & Assumptions'!$D$70:$D$98,'Inputs & Assumptions'!$D$121+34+1),0) -> 0 | AM25: =IF(('Inputs & Assumptions'!$D$121+35)<='Inputs & Assumptions'!$C$13,INDEX('Inputs & Assumptions'!$D$70:$D$98,'Inputs & Assumptions'!$D$121+35+1),0) -> 0 | AN25: =IF(('Inputs & Assumptions'!$D$121+36)<='Inputs & Assumptions'!$C$13,INDEX('Inputs & Assumptions'!$D$70:$D$98,'Inputs & Assumptions'!$D$121+36+1),0) -> 0
B26: ='Inputs & Assumptions'!$B$122 -> 21 | E26: =IF(('Inputs & Assumptions'!$D$122+1)<='Inputs & Assumptions'!$C$13,INDEX('Inputs & Assumptions'!$D$70:$D$98,'Inputs & Assumptions'!$D$122+1+1),0) -> 547603.8 | F26: =IF(('Inputs & Assumptions'!$D$122+2)<='Inputs & Assumptions'!$C$13,INDEX('Inputs & Assumptions'!$D$70:$D$98,'Inputs & Assumptions'!$D$122+2+1),0) -> 531175.69 | G26: =IF(('Inputs & Assumptions'!$D$122+3)<='Inputs & Assumptions'!$C$13,INDEX('Inputs & Assumptions'!$D$70:$D$98,'Inputs & Assumptions'!$D$122+3+1),0) -> 515240.42 | H26: =IF(('Inputs & Assumptions'!$D$122+4)<='Inputs & Assumptions'!$C$13,INDEX('Inputs & Assumptions'!$D$70:$D$98,'Inputs & Assumptions'!$D$122+4+1),0) -> 499783.2 | I26: =IF(('Inputs & Assumptions'!$D$122+5)<='Inputs & Assumptions'!$C$13,INDEX('Inputs & Assumptions'!$D$70:$D$98,'Inputs & Assumptions'!$D$122+5+1),0) -> 484789.71 | J26: =IF(('Inputs & Assumptions'!$D$122+6)<='Inputs & Assumptions'!$C$13,INDEX('Inputs & Assumptions'!$D$70:$D$98,'Inputs & Assumptions'!$D$122+6+1),0) -> 470246.02 | K26: =IF(('Inputs & Assumptions'!$D$122+7)<='Inputs & Assumptions'!$C$13,INDEX('Inputs & Assumptions'!$D$70:$D$98,'Inputs & Assumptions'!$D$122+7+1),0) -> 456138.64 | L26: =IF(('Inputs & Assumptions'!$D$122+8)<='Inputs & Assumptions'!$C$13,INDEX('Inputs & Assumptions'!$D$70:$D$98,'Inputs & Assumptions'!$D$122+8+1),0) -> 442454.48 | M26: =IF(('Inputs & Assumptions'!$D$122+9)<='Inputs & Assumptions'!$C$13,INDEX('Inputs & Assumptions'!$D$70:$D$98,'Inputs & Assumptions'!$D$122+9+1),0) -> 429180.84 | N26: =IF(('Inputs & Assumptions'!$D$122+10)<='Inputs & Assumptions'!$C$13,INDEX('Inputs & Assumptions'!$D$70:$D$98,'Inputs & Assumptions'!$D$122+10+1),0) -> 416305.42 | O26: =IF(('Inputs & Assumptions'!$D$122+11)<='Inputs & Assumptions'!$C$13,INDEX('Inputs & Assumptions'!$D$70:$D$98,'Inputs & Assumptions'!$D$122+11+1),0) -> 403816.25 | P26: =IF(('Inputs & Assumptions'!$D$122+12)<='Inputs & Assumptions'!$C$13,INDEX('Inputs & Assumptions'!$D$70:$D$98,'Inputs & Assumptions'!$D$122+12+1),0) -> 391701.77 | Q26: =IF(('Inputs & Assumptions'!$D$122+13)<='Inputs & Assumptions'!$C$13,INDEX('Inputs & Assumptions'!$D$70:$D$98,'Inputs & Assumptions'!$D$122+13+1),0) -> 379950.71 | R26: =IF(('Inputs & Assumptions'!$D$122+14)<='Inputs & Assumptions'!$C$13,INDEX('Inputs & Assumptions'!$D$70:$D$98,'Inputs & Assumptions'!$D$122+14+1),0) -> 368552.19 | S26: =IF(('Inputs & Assumptions'!$D$122+15)<='Inputs & Assumptions'!$C$13,INDEX('Inputs & Assumptions'!$D$70:$D$98,'Inputs & Assumptions'!$D$122+15+1),0) -> 357495.63 | T26: =IF(('Inputs & Assumptions'!$D$122+16)<='Inputs & Assumptions'!$C$13,INDEX('Inputs & Assumptions'!$D$70:$D$98,'Inputs & Assumptions'!$D$122+16+1),0) -> 346770.76 | U26: =IF(('Inputs & Assumptions'!$D$122+17)<='Inputs & Assumptions'!$C$13,INDEX('Inputs & Assumptions'!$D$70:$D$98,'Inputs & Assumptions'!$D$122+17+1),0) -> 336367.63 | V26: =IF(('Inputs & Assumptions'!$D$122+18)<='Inputs & Assumptions'!$C$13,INDEX('Inputs & Assumptions'!$D$70:$D$98,'Inputs & Assumptions'!$D$122+18+1),0) -> 326276.61 | W26: =IF(('Inputs & Assumptions'!$D$122+19)<='Inputs & Assumptions'!$C$13,INDEX('Inputs & Assumptions'!$D$70:$D$98,'Inputs & Assumptions'!$D$122+19+1),0) -> 316488.31 | X26: =IF(('Inputs & Assumptions'!$D$122+20)<='Inputs & Assumptions'!$C$13,INDEX('Inputs & Assumptions'!$D$70:$D$98,'Inputs & Assumptions'!$D$122+20+1),0) -> 306993.66 | Y26: =IF(('Inputs & Assumptions'!$D$122+21)<='Inputs & Assumptions'!$C$13,INDEX('Inputs & Assumptions'!$D$70:$D$98,'Inputs & Assumptions'!$D$122+21+1),0) -> 9926128.3 | Z26: =IF(('Inputs & Assumptions'!$D$122+22)<='Inputs & Assumptions'!$C$13,INDEX('Inputs & Assumptions'!$D$70:$D$98,'Inputs & Assumptions'!$D$122+22+1),0) -> 0 | AA26: =IF(('Inputs & Assumptions'!$D$122+23)<='Inputs & Assumptions'!$C$13,INDEX('Inputs & Assumptions'!$D$70:$D$98,'Inputs & Assumptions'!$D$122+23+1),0) -> 0 | AB26: =IF(('Inputs & Assumptions'!$D$122+24)<='Inputs & Assumptions'!$C$13,INDEX('Inputs & Assumptions'!$D$70:$D$98,'Inputs & Assumptions'!$D$122+24+1),0) -> 0 | AC26: =IF(('Inputs & Assumptions'!$D$122+25)<='Inputs & Assumptions'!$C$13,INDEX('Inputs & Assumptions'!$D$70:$D$98,'Inputs & Assumptions'!$D$122+25+1),0) -> 0 | AD26: =IF(('Inputs & Assumptions'!$D$122+26)<='Inputs & Assumptions'!$C$13,INDEX('Inputs & Assumptions'!$D$70:$D$98,'Inputs & Assumptions'!$D$122+26+1),0) -> 0 | AE26: =IF(('Inputs & Assumptions'!$D$122+27)<='Inputs & Assumptions'!$C$13,INDEX('Inputs & Assumptions'!$D$70:$D$98,'Inputs & Assumptions'!$D$122+27+1),0) -> 0 | AF26: =IF(('Inputs & Assumptions'!$D$122+28)<='Inputs & Assumptions'!$C$13,INDEX('Inputs & Assumptions'!$D$70:$D$98,'Inputs & Assumptions'!$D$122+28+1),0) -> 0 | AG26: =IF(('Inputs & Assumptions'!$D$122+29)<='Inputs & Assumptions'!$C$13,INDEX('Inputs & Assumptions'!$D$70:$D$98,'Inputs & Assumptions'!$D$122+29+1),0) -> 0 | AH26: =IF(('Inputs & Assumptions'!$D$122+30)<='Inputs & Assumptions'!$C$13,INDEX('Inputs & Assumptions'!$D$70:$D$98,'Inputs & Assumptions'!$D$122+30+1),0) -> 0 | AI26: =IF(('Inputs & Assumptions'!$D$122+31)<='Inputs & Assumptions'!$C$13,INDEX('Inputs & Assumptions'!$D$70:$D$98,'Inputs & Assumptions'!$D$122+31+1),0) -> 0 | AJ26: =IF(('Inputs & Assumptions'!$D$122+32)<='Inputs & Assumptions'!$C$13,INDEX('Inputs & Assumptions'!$D$70:$D$98,'Inputs & Assumptions'!$D$122+32+1),0) -> 0 | AK26: =IF(('Inputs & Assumptions'!$D$122+33)<='Inputs & Assumptions'!$C$13,INDEX('Inputs & Assumptions'!$D$70:$D$98,'Inputs & Assumptions'!$D$122+33+1),0) -> 0 | AL26: =IF(('Inputs & Assumptions'!$D$122+34)<='Inputs & Assumptions'!$C$13,INDEX('Inputs & Assumptions'!$D$70:$D$98,'Inputs & Assumptions'!$D$122+34+1),0) -> 0 | AM26: =IF(('Inputs & Assumptions'!$D$122+35)<='Inputs & Assumptions'!$C$13,INDEX('Inputs & Assumptions'!$D$70:$D$98,'Inputs & Assumptions'!$D$122+35+1),0) -> 0 | AN26: =IF(('Inputs & Assumptions'!$D$122+36)<='Inputs & Assumptions'!$C$13,INDEX('Inputs & Assumptions'!$D$70:$D$98,'Inputs & Assumptions'!$D$122+36+1),0) -> 0
B27: ='Inputs & Assumptions'!$B$123 -> 22 | E27: =IF(('Inputs & Assumptions'!$D$123+1)<='Inputs & Assumptions'!$C$13,INDEX('Inputs & Assumptions'!$D$70:$D$98,'Inputs & Assumptions'!$D$123+1+1),0) -> 547603.8 | F27: =IF(('Inputs & Assumptions'!$D$123+2)<='Inputs & Assumptions'!$C$13,INDEX('Inputs & Assumptions'!$D$70:$D$98,'Inputs & Assumptions'!$D$123+2+1),0) -> 531175.69 | G27: =IF(('Inputs & Assumptions'!$D$123+3)<='Inputs & Assumptions'!$C$13,INDEX('Inputs & Assumptions'!$D$70:$D$98,'Inputs & Assumptions'!$D$123+3+1),0) -> 515240.42 | H27: =IF(('Inputs & Assumptions'!$D$123+4)<='Inputs & Assumptions'!$C$13,INDEX('Inputs & Assumptions'!$D$70:$D$98,'Inputs & Assumptions'!$D$123+4+1),0) -> 499783.2 | I27: =IF(('Inputs & Assumptions'!$D$123+5)<='Inputs & Assumptions'!$C$13,INDEX('Inputs & Assumptions'!$D$70:$D$98,'Inputs & Assumptions'!$D$123+5+1),0) -> 484789.71 | J27: =IF(('Inputs & Assumptions'!$D$123+6)<='Inputs & Assumptions'!$C$13,INDEX('Inputs & Assumptions'!$D$70:$D$98,'Inputs & Assumptions'!$D$123+6+1),0) -> 470246.02 | K27: =IF(('Inputs & Assumptions'!$D$123+7)<='Inputs & Assumptions'!$C$13,INDEX('Inputs & Assumptions'!$D$70:$D$98,'Inputs & Assumptions'!$D$123+7+1),0) -> 456138.64 | L27: =IF(('Inputs & Assumptions'!$D$123+8)<='Inputs & Assumptions'!$C$13,INDEX('Inputs & Assumptions'!$D$70:$D$98,'Inputs & Assumptions'!$D$123+8+1),0) -> 442454.48 | M27: =IF(('Inputs & Assumptions'!$D$123+9)<='Inputs & Assumptions'!$C$13,INDEX('Inputs & Assumptions'!$D$70:$D$98,'Inputs & Assumptions'!$D$123+9+1),0) -> 429180.84 | N27: =IF(('Inputs & Assumptions'!$D$123+10)<='Inputs & Assumptions'!$C$13,INDEX('Inputs & Assumptions'!$D$70:$D$98,'Inputs & Assumptions'!$D$123+10+1),0) -> 416305.42 | O27: =IF(('Inputs & Assumptions'!$D$123+11)<='Inputs & Assumptions'!$C$13,INDEX('Inputs & Assumptions'!$D$70:$D$98,'Inputs & Assumptions'!$D$123+11+1),0) -> 403816.25 | P27: =IF(('Inputs & Assumptions'!$D$123+12)<='Inputs & Assumptions'!$C$13,INDEX('Inputs & Assumptions'!$D$70:$D$98,'Inputs & Assumptions'!$D$123+12+1),0) -> 391701.77 | Q27: =IF(('Inputs & Assumptions'!$D$123+13)<='Inputs & Assumptions'!$C$13,INDEX('Inputs & Assumptions'!$D$70:$D$98,'Inputs & Assumptions'!$D$123+13+1),0) -> 379950.71 | R27: =IF(('Inputs & Assumptions'!$D$123+14)<='Inputs & Assumptions'!$C$13,INDEX('Inputs & Assumptions'!$D$70:$D$98,'Inputs & Assumptions'!$D$123+14+1),0) -> 368552.19 | S27: =IF(('Inputs & Assumptions'!$D$123+15)<='Inputs & Assumptions'!$C$13,INDEX('Inputs & Assumptions'!$D$70:$D$98,'Inputs & Assumptions'!$D$123+15+1),0) -> 357495.63 | T27: =IF(('Inputs & Assumptions'!$D$123+16)<='Inputs & Assumptions'!$C$13,INDEX('Inputs & Assumptions'!$D$70:$D$98,'Inputs & Assumptions'!$D$123+16+1),0) -> 346770.76 | U27: =IF(('Inputs & Assumptions'!$D$123+17)<='Inputs & Assumptions'!$C$13,INDEX('Inputs & Assumptions'!$D$70:$D$98,'Inputs & Assumptions'!$D$123+17+1),0) -> 336367.63 | V27: =IF(('Inputs & Assumptions'!$D$123+18)<='Inputs & Assumptions'!$C$13,INDEX('Inputs & Assumptions'!$D$70:$D$98,'Inputs & Assumptions'!$D$123+18+1),0) -> 326276.61 | W27: =IF(('Inputs & Assumptions'!$D$123+19)<='Inputs & Assumptions'!$C$13,INDEX('Inputs & Assumptions'!$D$70:$D$98,'Inputs & Assumptions'!$D$123+19+1),0) -> 316488.31 | X27: =IF(('Inputs & Assumptions'!$D$123+20)<='Inputs & Assumptions'!$C$13,INDEX('Inputs & Assumptions'!$D$70:$D$98,'Inputs & Assumptions'!$D$123+20+1),0) -> 306993.66 | Y27: =IF(('Inputs & Assumptions'!$D$123+21)<='Inputs & Assumptions'!$C$13,INDEX('Inputs & Assumptions'!$D$70:$D$98,'Inputs & Assumptions'!$D$123+21+1),0) -> 9926128.3 | Z27: =IF(('Inputs & Assumptions'!$D$123+22)<='Inputs & Assumptions'!$C$13,INDEX('Inputs & Assumptions'!$D$70:$D$98,'Inputs & Assumptions'!$D$123+22+1),0) -> 0 | AA27: =IF(('Inputs & Assumptions'!$D$123+23)<='Inputs & Assumptions'!$C$13,INDEX('Inputs & Assumptions'!$D$70:$D$98,'Inputs & Assumptions'!$D$123+23+1),0) -> 0 | AB27: =IF(('Inputs & Assumptions'!$D$123+24)<='Inputs & Assumptions'!$C$13,INDEX('Inputs & Assumptions'!$D$70:$D$98,'Inputs & Assumptions'!$D$123+24+1),0) -> 0 | AC27: =IF(('Inputs & Assumptions'!$D$123+25)<='Inputs & Assumptions'!$C$13,INDEX('Inputs & Assumptions'!$D$70:$D$98,'Inputs & Assumptions'!$D$123+25+1),0) -> 0 | AD27: =IF(('Inputs & Assumptions'!$D$123+26)<='Inputs & Assumptions'!$C$13,INDEX('Inputs & Assumptions'!$D$70:$D$98,'Inputs & Assumptions'!$D$123+26+1),0) -> 0 | AE27: =IF(('Inputs & Assumptions'!$D$123+27)<='Inputs & Assumptions'!$C$13,INDEX('Inputs & Assumptions'!$D$70:$D$98,'Inputs & Assumptions'!$D$123+27+1),0) -> 0 | AF27: =IF(('Inputs & Assumptions'!$D$123+28)<='Inputs & Assumptions'!$C$13,INDEX('Inputs & Assumptions'!$D$70:$D$98,'Inputs & Assumptions'!$D$123+28+1),0) -> 0 | AG27: =IF(('Inputs & Assumptions'!$D$123+29)<='Inputs & Assumptions'!$C$13,INDEX('Inputs & Assumptions'!$D$70:$D$98,'Inputs & Assumptions'!$D$123+29+1),0) -> 0 | AH27: =IF(('Inputs & Assumptions'!$D$123+30)<='Inputs & Assumptions'!$C$13,INDEX('Inputs & Assumptions'!$D$70:$D$98,'Inputs & Assumptions'!$D$123+30+1),0) -> 0 | AI27: =IF(('Inputs & Assumptions'!$D$123+31)<='Inputs & Assumptions'!$C$13,INDEX('Inputs & Assumptions'!$D$70:$D$98,'Inputs & Assumptions'!$D$123+31+1),0) -> 0 | AJ27: =IF(('Inputs & Assumptions'!$D$123+32)<='Inputs & Assumptions'!$C$13,INDEX('Inputs & Assumptions'!$D$70:$D$98,'Inputs & Assumptions'!$D$123+32+1),0) -> 0 | AK27: =IF(('Inputs & Assumptions'!$D$123+33)<='Inputs & Assumptions'!$C$13,INDEX('Inputs & Assumptions'!$D$70:$D$98,'Inputs & Assumptions'!$D$123+33+1),0) -> 0 | AL27: =IF(('Inputs & Assumptions'!$D$123+34)<='Inputs & Assumptions'!$C$13,INDEX('Inputs & Assumptions'!$D$70:$D$98,'Inputs & Assumptions'!$D$123+34+1),0) -> 0 | AM27: =IF(('Inputs & Assumptions'!$D$123+35)<='Inputs & Assumptions'!$C$13,INDEX('Inputs & Assumptions'!$D$70:$D$98,'Inputs & Assumptions'!$D$123+35+1),0) -> 0 | AN27: =IF(('Inputs & Assumptions'!$D$123+36)<='Inputs & Assumptions'!$C$13,INDEX('Inputs & Assumptions'!$D$70:$D$98,'Inputs & Assumptions'!$D$123+36+1),0) -> 0
B28: ='Inputs & Assumptions'!$B$124 -> 23 | E28: =IF(('Inputs & Assumptions'!$D$124+1)<='Inputs & Assumptions'!$C$13,INDEX('Inputs & Assumptions'!$D$70:$D$98,'Inputs & Assumptions'!$D$124+1+1),0) -> 531175.69 | F28: =IF(('Inputs & Assumptions'!$D$124+2)<='Inputs & Assumptions'!$C$13,INDEX('Inputs & Assumptions'!$D$70:$D$98,'Inputs & Assumptions'!$D$124+2+1),0) -> 515240.42 | G28: =IF(('Inputs & Assumptions'!$D$124+3)<='Inputs & Assumptions'!$C$13,INDEX('Inputs & Assumptions'!$D$70:$D$98,'Inputs & Assumptions'!$D$124+3+1),0) -> 499783.2 | H28: =IF(('Inputs & Assumptions'!$D$124+4)<='Inputs & Assumptions'!$C$13,INDEX('Inputs & Assumptions'!$D$70:$D$98,'Inputs & Assumptions'!$D$124+4+1),0) -> 484789.71 | I28: =IF(('Inputs & Assumptions'!$D$124+5)<='Inputs & Assumptions'!$C$13,INDEX('Inputs & Assumptions'!$D$70:$D$98,'Inputs & Assumptions'!$D$124+5+1),0) -> 470246.02 | J28: =IF(('Inputs & Assumptions'!$D$124+6)<='Inputs & Assumptions'!$C$13,INDEX('Inputs & Assumptions'!$D$70:$D$98,'Inputs & Assumptions'!$D$124+6+1),0) -> 456138.64 | K28: =IF(('Inputs & Assumptions'!$D$124+7)<='Inputs & Assumptions'!$C$13,INDEX('Inputs & Assumptions'!$D$70:$D$98,'Inputs & Assumptions'!$D$124+7+1),0) -> 442454.48 | L28: =IF(('Inputs & Assumptions'!$D$124+8)<='Inputs & Assumptions'!$C$13,INDEX('Inputs & Assumptions'!$D$70:$D$98,'Inputs & Assumptions'!$D$124+8+1),0) -> 429180.84 | M28: =IF(('Inputs & Assumptions'!$D$124+9)<='Inputs & Assumptions'!$C$13,INDEX('Inputs & Assumptions'!$D$70:$D$98,'Inputs & Assumptions'!$D$124+9+1),0) -> 416305.42 | N28: =IF(('Inputs & Assumptions'!$D$124+10)<='Inputs & Assumptions'!$C$13,INDEX('Inputs & Assumptions'!$D$70:$D$98,'Inputs & Assumptions'!$D$124+10+1),0) -> 403816.25 | O28: =IF(('Inputs & Assumptions'!$D$124+11)<='Inputs & Assumptions'!$C$13,INDEX('Inputs & Assumptions'!$D$70:$D$98,'Inputs & Assumptions'!$D$124+11+1),0) -> 391701.77 | P28: =IF(('Inputs & Assumptions'!$D$124+12)<='Inputs & Assumptions'!$C$13,INDEX('Inputs & Assumptions'!$D$70:$D$98,'Inputs & Assumptions'!$D$124+12+1),0) -> 379950.71 | Q28: =IF(('Inputs & Assumptions'!$D$124+13)<='Inputs & Assumptions'!$C$13,INDEX('Inputs & Assumptions'!$D$70:$D$98,'Inputs & Assumptions'!$D$124+13+1),0) -> 368552.19 | R28: =IF(('Inputs & Assumptions'!$D$124+14)<='Inputs & Assumptions'!$C$13,INDEX('Inputs & Assumptions'!$D$70:$D$98,'Inputs & Assumptions'!$D$124+14+1),0) -> 357495.63 | S28: =IF(('Inputs & Assumptions'!$D$124+15)<='Inputs & Assumptions'!$C$13,INDEX('Inputs & Assumptions'!$D$70:$D$98,'Inputs & Assumptions'!$D$124+15+1),0) -> 346770.76 | T28: =IF(('Inputs & Assumptions'!$D$124+16)<='Inputs & Assumptions'!$C$13,INDEX('Inputs & Assumptions'!$D$70:$D$98,'Inputs & Assumptions'!$D$124+16+1),0) -> 336367.63 | U28: =IF(('Inputs & Assumptions'!$D$124+17)<='Inputs & Assumptions'!$C$13,INDEX('Inputs & Assumptions'!$D$70:$D$98,'Inputs & Assumptions'!$D$124+17+1),0) -> 326276.61 | V28: =IF(('Inputs & Assumptions'!$D$124+18)<='Inputs & Assumptions'!$C$13,INDEX('Inputs & Assumptions'!$D$70:$D$98,'Inputs & Assumptions'!$D$124+18+1),0) -> 316488.31 | W28: =IF(('Inputs & Assumptions'!$D$124+19)<='Inputs & Assumptions'!$C$13,INDEX('Inputs & Assumptions'!$D$70:$D$98,'Inputs & Assumptions'!$D$124+19+1),0) -> 306993.66 | X28: =IF(('Inputs & Assumptions'!$D$124+20)<='Inputs & Assumptions'!$C$13,INDEX('Inputs & Assumptions'!$D$70:$D$98,'Inputs & Assumptions'!$D$124+20+1),0) -> 9926128.3 | Y28: =IF(('Inputs & Assumptions'!$D$124+21)<='Inputs & Assumptions'!$C$13,INDEX('Inputs & Assumptions'!$D$70:$D$98,'Inputs & Assumptions'!$D$124+21+1),0) -> 0 | Z28: =IF(('Inputs & Assumptions'!$D$124+22)<='Inputs & Assumptions'!$C$13,INDEX('Inputs & Assumptions'!$D$70:$D$98,'Inputs & Assumptions'!$D$124+22+1),0) -> 0 | AA28: =IF(('Inputs & Assumptions'!$D$124+23)<='Inputs & Assumptions'!$C$13,INDEX('Inputs & Assumptions'!$D$70:$D$98,'Inputs & Assumptions'!$D$124+23+1),0) -> 0 | AB28: =IF(('Inputs & Assumptions'!$D$124+24)<='Inputs & Assumptions'!$C$13,INDEX('Inputs & Assumptions'!$D$70:$D$98,'Inputs & Assumptions'!$D$124+24+1),0) -> 0 | AC28: =IF(('Inputs & Assumptions'!$D$124+25)<='Inputs & Assumptions'!$C$13,INDEX('Inputs & Assumptions'!$D$70:$D$98,'Inputs & Assumptions'!$D$124+25+1),0) -> 0 | AD28: =IF(('Inputs & Assumptions'!$D$124+26)<='Inputs & Assumptions'!$C$13,INDEX('Inputs & Assumptions'!$D$70:$D$98,'Inputs & Assumptions'!$D$124+26+1),0) -> 0 | AE28: =IF(('Inputs & Assumptions'!$D$124+27)<='Inputs & Assumptions'!$C$13,INDEX('Inputs & Assumptions'!$D$70:$D$98,'Inputs & Assumptions'!$D$124+27+1),0) -> 0 | AF28: =IF(('Inputs & Assumptions'!$D$124+28)<='Inputs & Assumptions'!$C$13,INDEX('Inputs & Assumptions'!$D$70:$D$98,'Inputs & Assumptions'!$D$124+28+1),0) -> 0 | AG28: =IF(('Inputs & Assumptions'!$D$124+29)<='Inputs & Assumptions'!$C$13,INDEX('Inputs & Assumptions'!$D$70:$D$98,'Inputs & Assumptions'!$D$124+29+1),0) -> 0 | AH28: =IF(('Inputs & Assumptions'!$D$124+30)<='Inputs & Assumptions'!$C$13,INDEX('Inputs & Assumptions'!$D$70:$D$98,'Inputs & Assumptions'!$D$124+30+1),0) -> 0 | AI28: =IF(('Inputs & Assumptions'!$D$124+31)<='Inputs & Assumptions'!$C$13,INDEX('Inputs & Assumptions'!$D$70:$D$98,'Inputs & Assumptions'!$D$124+31+1),0) -> 0 | AJ28: =IF(('Inputs & Assumptions'!$D$124+32)<='Inputs & Assumptions'!$C$13,INDEX('Inputs & Assumptions'!$D$70:$D$98,'Inputs & Assumptions'!$D$124+32+1),0) -> 0 | AK28: =IF(('Inputs & Assumptions'!$D$124+33)<='Inputs & Assumptions'!$C$13,INDEX('Inputs & Assumptions'!$D$70:$D$98,'Inputs & Assumptions'!$D$124+33+1),0) -> 0 | AL28: =IF(('Inputs & Assumptions'!$D$124+34)<='Inputs & Assumptions'!$C$13,INDEX('Inputs & Assumptions'!$D$70:$D$98,'Inputs & Assumptions'!$D$124+34+1),0) -> 0 | AM28: =IF(('Inputs & Assumptions'!$D$124+35)<='Inputs & Assumptions'!$C$13,INDEX('Inputs & Assumptions'!$D$70:$D$98,'Inputs & Assumptions'!$D$124+35+1),0) -> 0 | AN28: =IF(('Inputs & Assumptions'!$D$124+36)<='Inputs & Assumptions'!$C$13,INDEX('Inputs & Assumptions'!$D$70:$D$98,'Inputs & Assumptions'!$D$124+36+1),0) -> 0
B29: ='Inputs & Assumptions'!$B$125 -> 24 | E29: =IF(('Inputs & Assumptions'!$D$125+1)<='Inputs & Assumptions'!$C$13,INDEX('Inputs & Assumptions'!$D$70:$D$98,'Inputs & Assumptions'!$D$125+1+1),0) -> 531175.69 | F29: =IF(('Inputs & Assumptions'!$D$125+2)<='Inputs & Assumptions'!$C$13,INDEX('Inputs & Assumptions'!$D$70:$D$98,'Inputs & Assumptions'!$D$125+2+1),0) -> 515240.42 | G29: =IF(('Inputs & Assumptions'!$D$125+3)<='Inputs & Assumptions'!$C$13,INDEX('Inputs & Assumptions'!$D$70:$D$98,'Inputs & Assumptions'!$D$125+3+1),0) -> 499783.2 | H29: =IF(('Inputs & Assumptions'!$D$125+4)<='Inputs & Assumptions'!$C$13,INDEX('Inputs & Assumptions'!$D$70:$D$98,'Inputs & Assumptions'!$D$125+4+1),0) -> 484789.71 | I29: =IF(('Inputs & Assumptions'!$D$125+5)<='Inputs & Assumptions'!$C$13,INDEX('Inputs & Assumptions'!$D$70:$D$98,'Inputs & Assumptions'!$D$125+5+1),0) -> 470246.02 | J29: =IF(('Inputs & Assumptions'!$D$125+6)<='Inputs & Assumptions'!$C$13,INDEX('Inputs & Assumptions'!$D$70:$D$98,'Inputs & Assumptions'!$D$125+6+1),0) -> 456138.64 | K29: =IF(('Inputs & Assumptions'!$D$125+7)<='Inputs & Assumptions'!$C$13,INDEX('Inputs & Assumptions'!$D$70:$D$98,'Inputs & Assumptions'!$D$125+7+1),0) -> 442454.48 | L29: =IF(('Inputs & Assumptions'!$D$125+8)<='Inputs & Assumptions'!$C$13,INDEX('Inputs & Assumptions'!$D$70:$D$98,'Inputs & Assumptions'!$D$125+8+1),0) -> 429180.84 | M29: =IF(('Inputs & Assumptions'!$D$125+9)<='Inputs & Assumptions'!$C$13,INDEX('Inputs & Assumptions'!$D$70:$D$98,'Inputs & Assumptions'!$D$125+9+1),0) -> 416305.42 | N29: =IF(('Inputs & Assumptions'!$D$125+10)<='Inputs & Assumptions'!$C$13,INDEX('Inputs & Assumptions'!$D$70:$D$98,'Inputs & Assumptions'!$D$125+10+1),0) -> 403816.25 | O29: =IF(('Inputs & Assumptions'!$D$125+11)<='Inputs & Assumptions'!$C$13,INDEX('Inputs & Assumptions'!$D$70:$D$98,'Inputs & Assumptions'!$D$125+11+1),0) -> 391701.77 | P29: =IF(('Inputs & Assumptions'!$D$125+12)<='Inputs & Assumptions'!$C$13,INDEX('Inputs & Assumptions'!$D$70:$D$98,'Inputs & Assumptions'!$D$125+12+1),0) -> 379950.71 | Q29: =IF(('Inputs & Assumptions'!$D$125+13)<='Inputs & Assumptions'!$C$13,INDEX('Inputs & Assumptions'!$D$70:$D$98,'Inputs & Assumptions'!$D$125+13+1),0) -> 368552.19 | R29: =IF(('Inputs & Assumptions'!$D$125+14)<='Inputs & Assumptions'!$C$13,INDEX('Inputs & Assumptions'!$D$70:$D$98,'Inputs & Assumptions'!$D$125+14+1),0) -> 357495.63 | S29: =IF(('Inputs & Assumptions'!$D$125+15)<='Inputs & Assumptions'!$C$13,INDEX('Inputs & Assumptions'!$D$70:$D$98,'Inputs & Assumptions'!$D$125+15+1),0) -> 346770.76 | T29: =IF(('Inputs & Assumptions'!$D$125+16)<='Inputs & Assumptions'!$C$13,INDEX('Inputs & Assumptions'!$D$70:$D$98,'Inputs & Assumptions'!$D$125+16+1),0) -> 336367.63 | U29: =IF(('Inputs & Assumptions'!$D$125+17)<='Inputs & Assumptions'!$C$13,INDEX('Inputs & Assumptions'!$D$70:$D$98,'Inputs & Assumptions'!$D$125+17+1),0) -> 326276.61 | V29: =IF(('Inputs & Assumptions'!$D$125+18)<='Inputs & Assumptions'!$C$13,INDEX('Inputs & Assumptions'!$D$70:$D$98,'Inputs & Assumptions'!$D$125+18+1),0) -> 316488.31 | W29: =IF(('Inputs & Assumptions'!$D$125+19)<='Inputs & Assumptions'!$C$13,INDEX('Inputs & Assumptions'!$D$70:$D$98,'Inputs & Assumptions'!$D$125+19+1),0) -> 306993.66 | X29: =IF(('Inputs & Assumptions'!$D$125+20)<='Inputs & Assumptions'!$C$13,INDEX('Inputs & Assumptions'!$D$70:$D$98,'Inputs & Assumptions'!$D$125+20+1),0) -> 9926128.3 | Y29: =IF(('Inputs & Assumptions'!$D$125+21)<='Inputs & Assumptions'!$C$13,INDEX('Inputs & Assumptions'!$D$70:$D$98,'Inputs & Assumptions'!$D$125+21+1),0) -> 0 | Z29: =IF(('Inputs & Assumptions'!$D$125+22)<='Inputs & Assumptions'!$C$13,INDEX('Inputs & Assumptions'!$D$70:$D$98,'Inputs & Assumptions'!$D$125+22+1),0) -> 0 | AA29: =IF(('Inputs & Assumptions'!$D$125+23)<='Inputs & Assumptions'!$C$13,INDEX('Inputs & Assumptions'!$D$70:$D$98,'Inputs & Assumptions'!$D$125+23+1),0) -> 0 | AB29: =IF(('Inputs & Assumptions'!$D$125+24)<='Inputs & Assumptions'!$C$13,INDEX('Inputs & Assumptions'!$D$70:$D$98,'Inputs & Assumptions'!$D$125+24+1),0) -> 0 | AC29: =IF(('Inputs & Assumptions'!$D$125+25)<='Inputs & Assumptions'!$C$13,INDEX('Inputs & Assumptions'!$D$70:$D$98,'Inputs & Assumptions'!$D$125+25+1),0) -> 0 | AD29: =IF(('Inputs & Assumptions'!$D$125+26)<='Inputs & Assumptions'!$C$13,INDEX('Inputs & Assumptions'!$D$70:$D$98,'Inputs & Assumptions'!$D$125+26+1),0) -> 0 | AE29: =IF(('Inputs & Assumptions'!$D$125+27)<='Inputs & Assumptions'!$C$13,INDEX('Inputs & Assumptions'!$D$70:$D$98,'Inputs & Assumptions'!$D$125+27+1),0) -> 0 | AF29: =IF(('Inputs & Assumptions'!$D$125+28)<='Inputs & Assumptions'!$C$13,INDEX('Inputs & Assumptions'!$D$70:$D$98,'Inputs & Assumptions'!$D$125+28+1),0) -> 0 | AG29: =IF(('Inputs & Assumptions'!$D$125+29)<='Inputs & Assumptions'!$C$13,INDEX('Inputs & Assumptions'!$D$70:$D$98,'Inputs & Assumptions'!$D$125+29+1),0) -> 0 | AH29: =IF(('Inputs & Assumptions'!$D$125+30)<='Inputs & Assumptions'!$C$13,INDEX('Inputs & Assumptions'!$D$70:$D$98,'Inputs & Assumptions'!$D$125+30+1),0) -> 0 | AI29: =IF(('Inputs & Assumptions'!$D$125+31)<='Inputs & Assumptions'!$C$13,INDEX('Inputs & Assumptions'!$D$70:$D$98,'Inputs & Assumptions'!$D$125+31+1),0) -> 0 | AJ29: =IF(('Inputs & Assumptions'!$D$125+32)<='Inputs & Assumptions'!$C$13,INDEX('Inputs & Assumptions'!$D$70:$D$98,'Inputs & Assumptions'!$D$125+32+1),0) -> 0 | AK29: =IF(('Inputs & Assumptions'!$D$125+33)<='Inputs & Assumptions'!$C$13,INDEX('Inputs & Assumptions'!$D$70:$D$98,'Inputs & Assumptions'!$D$125+33+1),0) -> 0 | AL29: =IF(('Inputs & Assumptions'!$D$125+34)<='Inputs & Assumptions'!$C$13,INDEX('Inputs & Assumptions'!$D$70:$D$98,'Inputs & Assumptions'!$D$125+34+1),0) -> 0 | AM29: =IF(('Inputs & Assumptions'!$D$125+35)<='Inputs & Assumptions'!$C$13,INDEX('Inputs & Assumptions'!$D$70:$D$98,'Inputs & Assumptions'!$D$125+35+1),0) -> 0 | AN29: =IF(('Inputs & Assumptions'!$D$125+36)<='Inputs & Assumptions'!$C$13,INDEX('Inputs & Assumptions'!$D$70:$D$98,'Inputs & Assumptions'!$D$125+36+1),0) -> 0
B30: ='Inputs & Assumptions'!$B$126 -> 25 | E30: =IF(('Inputs & Assumptions'!$D$126+1)<='Inputs & Assumptions'!$C$13,INDEX('Inputs & Assumptions'!$D$70:$D$98,'Inputs & Assumptions'!$D$126+1+1),0) -> 531175.69 | F30: =IF(('Inputs & Assumptions'!$D$126+2)<='Inputs & Assumptions'!$C$13,INDEX('Inputs & Assumptions'!$D$70:$D$98,'Inputs & Assumptions'!$D$126+2+1),0) -> 515240.42 | G30: =IF(('Inputs & Assumptions'!$D$126+3)<='Inputs & Assumptions'!$C$13,INDEX('Inputs & Assumptions'!$D$70:$D$98,'Inputs & Assumptions'!$D$126+3+1),0) -> 499783.2 | H30: =IF(('Inputs & Assumptions'!$D$126+4)<='Inputs & Assumptions'!$C$13,INDEX('Inputs & Assumptions'!$D$70:$D$98,'Inputs & Assumptions'!$D$126+4+1),0) -> 484789.71 | I30: =IF(('Inputs & Assumptions'!$D$126+5)<='Inputs & Assumptions'!$C$13,INDEX('Inputs & Assumptions'!$D$70:$D$98,'Inputs & Assumptions'!$D$126+5+1),0) -> 470246.02 | J30: =IF(('Inputs & Assumptions'!$D$126+6)<='Inputs & Assumptions'!$C$13,INDEX('Inputs & Assumptions'!$D$70:$D$98,'Inputs & Assumptions'!$D$126+6+1),0) -> 456138.64 | K30: =IF(('Inputs & Assumptions'!$D$126+7)<='Inputs & Assumptions'!$C$13,INDEX('Inputs & Assumptions'!$D$70:$D$98,'Inputs & Assumptions'!$D$126+7+1),0) -> 442454.48 | L30: =IF(('Inputs & Assumptions'!$D$126+8)<='Inputs & Assumptions'!$C$13,INDEX('Inputs & Assumptions'!$D$70:$D$98,'Inputs & Assumptions'!$D$126+8+1),0) -> 429180.84 | M30: =IF(('Inputs & Assumptions'!$D$126+9)<='Inputs & Assumptions'!$C$13,INDEX('Inputs & Assumptions'!$D$70:$D$98,'Inputs & Assumptions'!$D$126+9+1),0) -> 416305.42 | N30: =IF(('Inputs & Assumptions'!$D$126+10)<='Inputs & Assumptions'!$C$13,INDEX('Inputs & Assumptions'!$D$70:$D$98,'Inputs & Assumptions'!$D$126+10+1),0) -> 403816.25 | O30: =IF(('Inputs & Assumptions'!$D$126+11)<='Inputs & Assumptions'!$C$13,INDEX('Inputs & Assumptions'!$D$70:$D$98,'Inputs & Assumptions'!$D$126+11+1),0) -> 391701.77 | P30: =IF(('Inputs & Assumptions'!$D$126+12)<='Inputs & Assumptions'!$C$13,INDEX('Inputs & Assumptions'!$D$70:$D$98,'Inputs & Assumptions'!$D$126+12+1),0) -> 379950.71 | Q30: =IF(('Inputs & Assumptions'!$D$126+13)<='Inputs & Assumptions'!$C$13,INDEX('Inputs & Assumptions'!$D$70:$D$98,'Inputs & Assumptions'!$D$126+13+1),0) -> 368552.19 | R30: =IF(('Inputs & Assumptions'!$D$126+14)<='Inputs & Assumptions'!$C$13,INDEX('Inputs & Assumptions'!$D$70:$D$98,'Inputs & Assumptions'!$D$126+14+1),0) -> 357495.63 | S30: =IF(('Inputs & Assumptions'!$D$126+15)<='Inputs & Assumptions'!$C$13,INDEX('Inputs & Assumptions'!$D$70:$D$98,'Inputs & Assumptions'!$D$126+15+1),0) -> 346770.76 | T30: =IF(('Inputs & Assumptions'!$D$126+16)<='Inputs & Assumptions'!$C$13,INDEX('Inputs & Assumptions'!$D$70:$D$98,'Inputs & Assumptions'!$D$126+16+1),0) -> 336367.63 | U30: =IF(('Inputs & Assumptions'!$D$126+17)<='Inputs & Assumptions'!$C$13,INDEX('Inputs & Assumptions'!$D$70:$D$98,'Inputs & Assumptions'!$D$126+17+1),0) -> 326276.61 | V30: =IF(('Inputs & Assumptions'!$D$126+18)<='Inputs & Assumptions'!$C$13,INDEX('Inputs & Assumptions'!$D$70:$D$98,'Inputs & Assumptions'!$D$126+18+1),0) -> 316488.31 | W30: =IF(('Inputs & Assumptions'!$D$126+19)<='Inputs & Assumptions'!$C$13,INDEX('Inputs & Assumptions'!$D$70:$D$98,'Inputs & Assumptions'!$D$126+19+1),0) -> 306993.66 | X30: =IF(('Inputs & Assumptions'!$D$126+20)<='Inputs & Assumptions'!$C$13,INDEX('Inputs & Assumptions'!$D$70:$D$98,'Inputs & Assumptions'!$D$126+20+1),0) -> 9926128.3 | Y30: =IF(('Inputs & Assumptions'!$D$126+21)<='Inputs & Assumptions'!$C$13,INDEX('Inputs & Assumptions'!$D$70:$D$98,'Inputs & Assumptions'!$D$126+21+1),0) -> 0 | Z30: =IF(('Inputs & Assumptions'!$D$126+22)<='Inputs & Assumptions'!$C$13,INDEX('Inputs & Assumptions'!$D$70:$D$98,'Inputs & Assumptions'!$D$126+22+1),0) -> 0 | AA30: =IF(('Inputs & Assumptions'!$D$126+23)<='Inputs & Assumptions'!$C$13,INDEX('Inputs & Assumptions'!$D$70:$D$98,'Inputs & Assumptions'!$D$126+23+1),0) -> 0 | AB30: =IF(('Inputs & Assumptions'!$D$126+24)<='Inputs & Assumptions'!$C$13,INDEX('Inputs & Assumptions'!$D$70:$D$98,'Inputs & Assumptions'!$D$126+24+1),0) -> 0 | AC30: =IF(('Inputs & Assumptions'!$D$126+25)<='Inputs & Assumptions'!$C$13,INDEX('Inputs & Assumptions'!$D$70:$D$98,'Inputs & Assumptions'!$D$126+25+1),0) -> 0 | AD30: =IF(('Inputs & Assumptions'!$D$126+26)<='Inputs & Assumptions'!$C$13,INDEX('Inputs & Assumptions'!$D$70:$D$98,'Inputs & Assumptions'!$D$126+26+1),0) -> 0 | AE30: =IF(('Inputs & Assumptions'!$D$126+27)<='Inputs & Assumptions'!$C$13,INDEX('Inputs & Assumptions'!$D$70:$D$98,'Inputs & Assumptions'!$D$126+27+1),0) -> 0 | AF30: =IF(('Inputs & Assumptions'!$D$126+28)<='Inputs & Assumptions'!$C$13,INDEX('Inputs & Assumptions'!$D$70:$D$98,'Inputs & Assumptions'!$D$126+28+1),0) -> 0 | AG30: =IF(('Inputs & Assumptions'!$D$126+29)<='Inputs & Assumptions'!$C$13,INDEX('Inputs & Assumptions'!$D$70:$D$98,'Inputs & Assumptions'!$D$126+29+1),0) -> 0 | AH30: =IF(('Inputs & Assumptions'!$D$126+30)<='Inputs & Assumptions'!$C$13,INDEX('Inputs & Assumptions'!$D$70:$D$98,'Inputs & Assumptions'!$D$126+30+1),0) -> 0 | AI30: =IF(('Inputs & Assumptions'!$D$126+31)<='Inputs & Assumptions'!$C$13,INDEX('Inputs & Assumptions'!$D$70:$D$98,'Inputs & Assumptions'!$D$126+31+1),0) -> 0 | AJ30: =IF(('Inputs & Assumptions'!$D$126+32)<='Inputs & Assumptions'!$C$13,INDEX('Inputs & Assumptions'!$D$70:$D$98,'Inputs & Assumptions'!$D$126+32+1),0) -> 0 | AK30: =IF(('Inputs & Assumptions'!$D$126+33)<='Inputs & Assumptions'!$C$13,INDEX('Inputs & Assumptions'!$D$70:$D$98,'Inputs & Assumptions'!$D$126+33+1),0) -> 0 | AL30: =IF(('Inputs & Assumptions'!$D$126+34)<='Inputs & Assumptions'!$C$13,INDEX('Inputs & Assumptions'!$D$70:$D$98,'Inputs & Assumptions'!$D$126+34+1),0) -> 0 | AM30: =IF(('Inputs & Assumptions'!$D$126+35)<='Inputs & Assumptions'!$C$13,INDEX('Inputs & Assumptions'!$D$70:$D$98,'Inputs & Assumptions'!$D$126+35+1),0) -> 0 | AN30: =IF(('Inputs & Assumptions'!$D$126+36)<='Inputs & Assumptions'!$C$13,INDEX('Inputs & Assumptions'!$D$70:$D$98,'Inputs & Assumptions'!$D$126+36+1),0) -> 0
B31: ='Inputs & Assumptions'!$B$127 -> 26 | E31: =IF(('Inputs & Assumptions'!$D$127+1)<='Inputs & Assumptions'!$C$13,INDEX('Inputs & Assumptions'!$D$70:$D$98,'Inputs & Assumptions'!$D$127+1+1),0) -> 515240.42 | F31: =IF(('Inputs & Assumptions'!$D$127+2)<='Inputs & Assumptions'!$C$13,INDEX('Inputs & Assumptions'!$D$70:$D$98,'Inputs & Assumptions'!$D$127+2+1),0) -> 499783.2 | G31: =IF(('Inputs & Assumptions'!$D$127+3)<='Inputs & Assumptions'!$C$13,INDEX('Inputs & Assumptions'!$D$70:$D$98,'Inputs & Assumptions'!$D$127+3+1),0) -> 484789.71 | H31: =IF(('Inputs & Assumptions'!$D$127+4)<='Inputs & Assumptions'!$C$13,INDEX('Inputs & Assumptions'!$D$70:$D$98,'Inputs & Assumptions'!$D$127+4+1),0) -> 470246.02 | I31: =IF(('Inputs & Assumptions'!$D$127+5)<='Inputs & Assumptions'!$C$13,INDEX('Inputs & Assumptions'!$D$70:$D$98,'Inputs & Assumptions'!$D$127+5+1),0) -> 456138.64 | J31: =IF(('Inputs & Assumptions'!$D$127+6)<='Inputs & Assumptions'!$C$13,INDEX('Inputs & Assumptions'!$D$70:$D$98,'Inputs & Assumptions'!$D$127+6+1),0) -> 442454.48 | K31: =IF(('Inputs & Assumptions'!$D$127+7)<='Inputs & Assumptions'!$C$13,INDEX('Inputs & Assumptions'!$D$70:$D$98,'Inputs & Assumptions'!$D$127+7+1),0) -> 429180.84 | L31: =IF(('Inputs & Assumptions'!$D$127+8)<='Inputs & Assumptions'!$C$13,INDEX('Inputs & Assumptions'!$D$70:$D$98,'Inputs & Assumptions'!$D$127+8+1),0) -> 416305.42 | M31: =IF(('Inputs & Assumptions'!$D$127+9)<='Inputs & Assumptions'!$C$13,INDEX('Inputs & Assumptions'!$D$70:$D$98,'Inputs & Assumptions'!$D$127+9+1),0) -> 403816.25 | N31: =IF(('Inputs & Assumptions'!$D$127+10)<='Inputs & Assumptions'!$C$13,INDEX('Inputs & Assumptions'!$D$70:$D$98,'Inputs & Assumptions'!$D$127+10+1),0) -> 391701.77 | O31: =IF(('Inputs & Assumptions'!$D$127+11)<='Inputs & Assumptions'!$C$13,INDEX('Inputs & Assumptions'!$D$70:$D$98,'Inputs & Assumptions'!$D$127+11+1),0) -> 379950.71 | P31: =IF(('Inputs & Assumptions'!$D$127+12)<='Inputs & Assumptions'!$C$13,INDEX('Inputs & Assumptions'!$D$70:$D$98,'Inputs & Assumptions'!$D$127+12+1),0) -> 368552.19 | Q31: =IF(('Inputs & Assumptions'!$D$127+13)<='Inputs & Assumptions'!$C$13,INDEX('Inputs & Assumptions'!$D$70:$D$98,'Inputs & Assumptions'!$D$127+13+1),0) -> 357495.63 | R31: =IF(('Inputs & Assumptions'!$D$127+14)<='Inputs & Assumptions'!$C$13,INDEX('Inputs & Assumptions'!$D$70:$D$98,'Inputs & Assumptions'!$D$127+14+1),0) -> 346770.76 | S31: =IF(('Inputs & Assumptions'!$D$127+15)<='Inputs & Assumptions'!$C$13,INDEX('Inputs & Assumptions'!$D$70:$D$98,'Inputs & Assumptions'!$D$127+15+1),0) -> 336367.63 | T31: =IF(('Inputs & Assumptions'!$D$127+16)<='Inputs & Assumptions'!$C$13,INDEX('Inputs & Assumptions'!$D$70:$D$98,'Inputs & Assumptions'!$D$127+16+1),0) -> 326276.61 | U31: =IF(('Inputs & Assumptions'!$D$127+17)<='Inputs & Assumptions'!$C$13,INDEX('Inputs & Assumptions'!$D$70:$D$98,'Inputs & Assumptions'!$D$127+17+1),0) -> 316488.31 | V31: =IF(('Inputs & Assumptions'!$D$127+18)<='Inputs & Assumptions'!$C$13,INDEX('Inputs & Assumptions'!$D$70:$D$98,'Inputs & Assumptions'!$D$127+18+1),0) -> 306993.66 | W31: =IF(('Inputs & Assumptions'!$D$127+19)<='Inputs & Assumptions'!$C$13,INDEX('Inputs & Assumptions'!$D$70:$D$98,'Inputs & Assumptions'!$D$127+19+1),0) -> 9926128.3 | X31: =IF(('Inputs & Assumptions'!$D$127+20)<='Inputs & Assumptions'!$C$13,INDEX('Inputs & Assumptions'!$D$70:$D$98,'Inputs & Assumptions'!$D$127+20+1),0) -> 0 | Y31: =IF(('Inputs & Assumptions'!$D$127+21)<='Inputs & Assumptions'!$C$13,INDEX('Inputs & Assumptions'!$D$70:$D$98,'Inputs & Assumptions'!$D$127+21+1),0) -> 0 | Z31: =IF(('Inputs & Assumptions'!$D$127+22)<='Inputs & Assumptions'!$C$13,INDEX('Inputs & Assumptions'!$D$70:$D$98,'Inputs & Assumptions'!$D$127+22+1),0) -> 0 | AA31: =IF(('Inputs & Assumptions'!$D$127+23)<='Inputs & Assumptions'!$C$13,INDEX('Inputs & Assumptions'!$D$70:$D$98,'Inputs & Assumptions'!$D$127+23+1),0) -> 0 | AB31: =IF(('Inputs & Assumptions'!$D$127+24)<='Inputs & Assumptions'!$C$13,INDEX('Inputs & Assumptions'!$D$70:$D$98,'Inputs & Assumptions'!$D$127+24+1),0) -> 0 | AC31: =IF(('Inputs & Assumptions'!$D$127+25)<='Inputs & Assumptions'!$C$13,INDEX('Inputs & Assumptions'!$D$70:$D$98,'Inputs & Assumptions'!$D$127+25+1),0) -> 0 | AD31: =IF(('Inputs & Assumptions'!$D$127+26)<='Inputs & Assumptions'!$C$13,INDEX('Inputs & Assumptions'!$D$70:$D$98,'Inputs & Assumptions'!$D$127+26+1),0) -> 0 | AE31: =IF(('Inputs & Assumptions'!$D$127+27)<='Inputs & Assumptions'!$C$13,INDEX('Inputs & Assumptions'!$D$70:$D$98,'Inputs & Assumptions'!$D$127+27+1),0) -> 0 | AF31: =IF(('Inputs & Assumptions'!$D$127+28)<='Inputs & Assumptions'!$C$13,INDEX('Inputs & Assumptions'!$D$70:$D$98,'Inputs & Assumptions'!$D$127+28+1),0) -> 0 | AG31: =IF(('Inputs & Assumptions'!$D$127+29)<='Inputs & Assumptions'!$C$13,INDEX('Inputs & Assumptions'!$D$70:$D$98,'Inputs & Assumptions'!$D$127+29+1),0) -> 0 | AH31: =IF(('Inputs & Assumptions'!$D$127+30)<='Inputs & Assumptions'!$C$13,INDEX('Inputs & Assumptions'!$D$70:$D$98,'Inputs & Assumptions'!$D$127+30+1),0) -> 0 | AI31: =IF(('Inputs & Assumptions'!$D$127+31)<='Inputs & Assumptions'!$C$13,INDEX('Inputs & Assumptions'!$D$70:$D$98,'Inputs & Assumptions'!$D$127+31+1),0) -> 0 | AJ31: =IF(('Inputs & Assumptions'!$D$127+32)<='Inputs & Assumptions'!$C$13,INDEX('Inputs & Assumptions'!$D$70:$D$98,'Inputs & Assumptions'!$D$127+32+1),0) -> 0 | AK31: =IF(('Inputs & Assumptions'!$D$127+33)<='Inputs & Assumptions'!$C$13,INDEX('Inputs & Assumptions'!$D$70:$D$98,'Inputs & Assumptions'!$D$127+33+1),0) -> 0 | AL31: =IF(('Inputs & Assumptions'!$D$127+34)<='Inputs & Assumptions'!$C$13,INDEX('Inputs & Assumptions'!$D$70:$D$98,'Inputs & Assumptions'!$D$127+34+1),0) -> 0 | AM31: =IF(('Inputs & Assumptions'!$D$127+35)<='Inputs & Assumptions'!$C$13,INDEX('Inputs & Assumptions'!$D$70:$D$98,'Inputs & Assumptions'!$D$127+35+1),0) -> 0 | AN31: =IF(('Inputs & Assumptions'!$D$127+36)<='Inputs & Assumptions'!$C$13,INDEX('Inputs & Assumptions'!$D$70:$D$98,'Inputs & Assumptions'!$D$127+36+1),0) -> 0
B32: ='Inputs & Assumptions'!$B$128 -> 27 | E32: =IF(('Inputs & Assumptions'!$D$128+1)<='Inputs & Assumptions'!$C$13,INDEX('Inputs & Assumptions'!$D$70:$D$98,'Inputs & Assumptions'!$D$128+1+1),0) -> 515240.42 | F32: =IF(('Inputs & Assumptions'!$D$128+2)<='Inputs & Assumptions'!$C$13,INDEX('Inputs & Assumptions'!$D$70:$D$98,'Inputs & Assumptions'!$D$128+2+1),0) -> 499783.2 | G32: =IF(('Inputs & Assumptions'!$D$128+3)<='Inputs & Assumptions'!$C$13,INDEX('Inputs & Assumptions'!$D$70:$D$98,'Inputs & Assumptions'!$D$128+3+1),0) -> 484789.71 | H32: =IF(('Inputs & Assumptions'!$D$128+4)<='Inputs & Assumptions'!$C$13,INDEX('Inputs & Assumptions'!$D$70:$D$98,'Inputs & Assumptions'!$D$128+4+1),0) -> 470246.02 | I32: =IF(('Inputs & Assumptions'!$D$128+5)<='Inputs & Assumptions'!$C$13,INDEX('Inputs & Assumptions'!$D$70:$D$98,'Inputs & Assumptions'!$D$128+5+1),0) -> 456138.64 | J32: =IF(('Inputs & Assumptions'!$D$128+6)<='Inputs & Assumptions'!$C$13,INDEX('Inputs & Assumptions'!$D$70:$D$98,'Inputs & Assumptions'!$D$128+6+1),0) -> 442454.48 | K32: =IF(('Inputs & Assumptions'!$D$128+7)<='Inputs & Assumptions'!$C$13,INDEX('Inputs & Assumptions'!$D$70:$D$98,'Inputs & Assumptions'!$D$128+7+1),0) -> 429180.84 | L32: =IF(('Inputs & Assumptions'!$D$128+8)<='Inputs & Assumptions'!$C$13,INDEX('Inputs & Assumptions'!$D$70:$D$98,'Inputs & Assumptions'!$D$128+8+1),0) -> 416305.42 | M32: =IF(('Inputs & Assumptions'!$D$128+9)<='Inputs & Assumptions'!$C$13,INDEX('Inputs & Assumptions'!$D$70:$D$98,'Inputs & Assumptions'!$D$128+9+1),0) -> 403816.25 | N32: =IF(('Inputs & Assumptions'!$D$128+10)<='Inputs & Assumptions'!$C$13,INDEX('Inputs & Assumptions'!$D$70:$D$98,'Inputs & Assumptions'!$D$128+10+1),0) -> 391701.77 | O32: =IF(('Inputs & Assumptions'!$D$128+11)<='Inputs & Assumptions'!$C$13,INDEX('Inputs & Assumptions'!$D$70:$D$98,'Inputs & Assumptions'!$D$128+11+1),0) -> 379950.71 | P32: =IF(('Inputs & Assumptions'!$D$128+12)<='Inputs & Assumptions'!$C$13,INDEX('Inputs & Assumptions'!$D$70:$D$98,'Inputs & Assumptions'!$D$128+12+1),0) -> 368552.19 | Q32: =IF(('Inputs & Assumptions'!$D$128+13)<='Inputs & Assumptions'!$C$13,INDEX('Inputs & Assumptions'!$D$70:$D$98,'Inputs & Assumptions'!$D$128+13+1),0) -> 357495.63 | R32: =IF(('Inputs & Assumptions'!$D$128+14)<='Inputs & Assumptions'!$C$13,INDEX('Inputs & Assumptions'!$D$70:$D$98,'Inputs & Assumptions'!$D$128+14+1),0) -> 346770.76 | S32: =IF(('Inputs & Assumptions'!$D$128+15)<='Inputs & Assumptions'!$C$13,INDEX('Inputs & Assumptions'!$D$70:$D$98,'Inputs & Assumptions'!$D$128+15+1),0) -> 336367.63 | T32: =IF(('Inputs & Assumptions'!$D$128+16)<='Inputs & Assumptions'!$C$13,INDEX('Inputs & Assumptions'!$D$70:$D$98,'Inputs & Assumptions'!$D$128+16+1),0) -> 326276.61 | U32: =IF(('Inputs & Assumptions'!$D$128+17)<='Inputs & Assumptions'!$C$13,INDEX('Inputs & Assumptions'!$D$70:$D$98,'Inputs & Assumptions'!$D$128+17+1),0) -> 316488.31 | V32: =IF(('Inputs & Assumptions'!$D$128+18)<='Inputs & Assumptions'!$C$13,INDEX('Inputs & Assumptions'!$D$70:$D$98,'Inputs & Assumptions'!$D$128+18+1),0) -> 306993.66 | W32: =IF(('Inputs & Assumptions'!$D$128+19)<='Inputs & Assumptions'!$C$13,INDEX('Inputs & Assumptions'!$D$70:$D$98,'Inputs & Assumptions'!$D$128+19+1),0) -> 9926128.3 | X32: =IF(('Inputs & Assumptions'!$D$128+20)<='Inputs & Assumptions'!$C$13,INDEX('Inputs & Assumptions'!$D$70:$D$98,'Inputs & Assumptions'!$D$128+20+1),0) -> 0 | Y32: =IF(('Inputs & Assumptions'!$D$128+21)<='Inputs & Assumptions'!$C$13,INDEX('Inputs & Assumptions'!$D$70:$D$98,'Inputs & Assumptions'!$D$128+21+1),0) -> 0 | Z32: =IF(('Inputs & Assumptions'!$D$128+22)<='Inputs & Assumptions'!$C$13,INDEX('Inputs & Assumptions'!$D$70:$D$98,'Inputs & Assumptions'!$D$128+22+1),0) -> 0 | AA32: =IF(('Inputs & Assumptions'!$D$128+23)<='Inputs & Assumptions'!$C$13,INDEX('Inputs & Assumptions'!$D$70:$D$98,'Inputs & Assumptions'!$D$128+23+1),0) -> 0 | AB32: =IF(('Inputs & Assumptions'!$D$128+24)<='Inputs & Assumptions'!$C$13,INDEX('Inputs & Assumptions'!$D$70:$D$98,'Inputs & Assumptions'!$D$128+24+1),0) -> 0 | AC32: =IF(('Inputs & Assumptions'!$D$128+25)<='Inputs & Assumptions'!$C$13,INDEX('Inputs & Assumptions'!$D$70:$D$98,'Inputs & Assumptions'!$D$128+25+1),0) -> 0 | AD32: =IF(('Inputs & Assumptions'!$D$128+26)<='Inputs & Assumptions'!$C$13,INDEX('Inputs & Assumptions'!$D$70:$D$98,'Inputs & Assumptions'!$D$128+26+1),0) -> 0 | AE32: =IF(('Inputs & Assumptions'!$D$128+27)<='Inputs & Assumptions'!$C$13,INDEX('Inputs & Assumptions'!$D$70:$D$98,'Inputs & Assumptions'!$D$128+27+1),0) -> 0 | AF32: =IF(('Inputs & Assumptions'!$D$128+28)<='Inputs & Assumptions'!$C$13,INDEX('Inputs & Assumptions'!$D$70:$D$98,'Inputs & Assumptions'!$D$128+28+1),0) -> 0 | AG32: =IF(('Inputs & Assumptions'!$D$128+29)<='Inputs & Assumptions'!$C$13,INDEX('Inputs & Assumptions'!$D$70:$D$98,'Inputs & Assumptions'!$D$128+29+1),0) -> 0 | AH32: =IF(('Inputs & Assumptions'!$D$128+30)<='Inputs & Assumptions'!$C$13,INDEX('Inputs & Assumptions'!$D$70:$D$98,'Inputs & Assumptions'!$D$128+30+1),0) -> 0 | AI32: =IF(('Inputs & Assumptions'!$D$128+31)<='Inputs & Assumptions'!$C$13,INDEX('Inputs & Assumptions'!$D$70:$D$98,'Inputs & Assumptions'!$D$128+31+1),0) -> 0 | AJ32: =IF(('Inputs & Assumptions'!$D$128+32)<='Inputs & Assumptions'!$C$13,INDEX('Inputs & Assumptions'!$D$70:$D$98,'Inputs & Assumptions'!$D$128+32+1),0) -> 0 | AK32: =IF(('Inputs & Assumptions'!$D$128+33)<='Inputs & Assumptions'!$C$13,INDEX('Inputs & Assumptions'!$D$70:$D$98,'Inputs & Assumptions'!$D$128+33+1),0) -> 0 | AL32: =IF(('Inputs & Assumptions'!$D$128+34)<='Inputs & Assumptions'!$C$13,INDEX('Inputs & Assumptions'!$D$70:$D$98,'Inputs & Assumptions'!$D$128+34+1),0) -> 0 | AM32: =IF(('Inputs & Assumptions'!$D$128+35)<='Inputs & Assumptions'!$C$13,INDEX('Inputs & Assumptions'!$D$70:$D$98,'Inputs & Assumptions'!$D$128+35+1),0) -> 0 | AN32: =IF(('Inputs & Assumptions'!$D$128+36)<='Inputs & Assumptions'!$C$13,INDEX('Inputs & Assumptions'!$D$70:$D$98,'Inputs & Assumptions'!$D$128+36+1),0) -> 0
B33: ='Inputs & Assumptions'!$B$129 -> 28 | E33: =IF(('Inputs & Assumptions'!$D$129+1)<='Inputs & Assumptions'!$C$13,INDEX('Inputs & Assumptions'!$D$70:$D$98,'Inputs & Assumptions'!$D$129+1+1),0) -> 515240.42 | F33: =IF(('Inputs & Assumptions'!$D$129+2)<='Inputs & Assumptions'!$C$13,INDEX('Inputs & Assumptions'!$D$70:$D$98,'Inputs & Assumptions'!$D$129+2+1),0) -> 499783.2 | G33: =IF(('Inputs & Assumptions'!$D$129+3)<='Inputs & Assumptions'!$C$13,INDEX('Inputs & Assumptions'!$D$70:$D$98,'Inputs & Assumptions'!$D$129+3+1),0) -> 484789.71 | H33: =IF(('Inputs & Assumptions'!$D$129+4)<='Inputs & Assumptions'!$C$13,INDEX('Inputs & Assumptions'!$D$70:$D$98,'Inputs & Assumptions'!$D$129+4+1),0) -> 470246.02 | I33: =IF(('Inputs & Assumptions'!$D$129+5)<='Inputs & Assumptions'!$C$13,INDEX('Inputs & Assumptions'!$D$70:$D$98,'Inputs & Assumptions'!$D$129+5+1),0) -> 456138.64 | J33: =IF(('Inputs & Assumptions'!$D$129+6)<='Inputs & Assumptions'!$C$13,INDEX('Inputs & Assumptions'!$D$70:$D$98,'Inputs & Assumptions'!$D$129+6+1),0) -> 442454.48 | K33: =IF(('Inputs & Assumptions'!$D$129+7)<='Inputs & Assumptions'!$C$13,INDEX('Inputs & Assumptions'!$D$70:$D$98,'Inputs & Assumptions'!$D$129+7+1),0) -> 429180.84 | L33: =IF(('Inputs & Assumptions'!$D$129+8)<='Inputs & Assumptions'!$C$13,INDEX('Inputs & Assumptions'!$D$70:$D$98,'Inputs & Assumptions'!$D$129+8+1),0) -> 416305.42 | M33: =IF(('Inputs & Assumptions'!$D$129+9)<='Inputs & Assumptions'!$C$13,INDEX('Inputs & Assumptions'!$D$70:$D$98,'Inputs & Assumptions'!$D$129+9+1),0) -> 403816.25 | N33: =IF(('Inputs & Assumptions'!$D$129+10)<='Inputs & Assumptions'!$C$13,INDEX('Inputs & Assumptions'!$D$70:$D$98,'Inputs & Assumptions'!$D$129+10+1),0) -> 391701.77 | O33: =IF(('Inputs & Assumptions'!$D$129+11)<='Inputs & Assumptions'!$C$13,INDEX('Inputs & Assumptions'!$D$70:$D$98,'Inputs & Assumptions'!$D$129+11+1),0) -> 379950.71 | P33: =IF(('Inputs & Assumptions'!$D$129+12)<='Inputs & Assumptions'!$C$13,INDEX('Inputs & Assumptions'!$D$70:$D$98,'Inputs & Assumptions'!$D$129+12+1),0) -> 368552.19 | Q33: =IF(('Inputs & Assumptions'!$D$129+13)<='Inputs & Assumptions'!$C$13,INDEX('Inputs & Assumptions'!$D$70:$D$98,'Inputs & Assumptions'!$D$129+13+1),0) -> 357495.63 | R33: =IF(('Inputs & Assumptions'!$D$129+14)<='Inputs & Assumptions'!$C$13,INDEX('Inputs & Assumptions'!$D$70:$D$98,'Inputs & Assumptions'!$D$129+14+1),0) -> 346770.76 | S33: =IF(('Inputs & Assumptions'!$D$129+15)<='Inputs & Assumptions'!$C$13,INDEX('Inputs & Assumptions'!$D$70:$D$98,'Inputs & Assumptions'!$D$129+15+1),0) -> 336367.63 | T33: =IF(('Inputs & Assumptions'!$D$129+16)<='Inputs & Assumptions'!$C$13,INDEX('Inputs & Assumptions'!$D$70:$D$98,'Inputs & Assumptions'!$D$129+16+1),0) -> 326276.61 | U33: =IF(('Inputs & Assumptions'!$D$129+17)<='Inputs & Assumptions'!$C$13,INDEX('Inputs & Assumptions'!$D$70:$D$98,'Inputs & Assumptions'!$D$129+17+1),0) -> 316488.31 | V33: =IF(('Inputs & Assumptions'!$D$129+18)<='Inputs & Assumptions'!$C$13,INDEX('Inputs & Assumptions'!$D$70:$D$98,'Inputs & Assumptions'!$D$129+18+1),0) -> 306993.66 | W33: =IF(('Inputs & Assumptions'!$D$129+19)<='Inputs & Assumptions'!$C$13,INDEX('Inputs & Assumptions'!$D$70:$D$98,'Inputs & Assumptions'!$D$129+19+1),0) -> 9926128.3 | X33: =IF(('Inputs & Assumptions'!$D$129+20)<='Inputs & Assumptions'!$C$13,INDEX('Inputs & Assumptions'!$D$70:$D$98,'Inputs & Assumptions'!$D$129+20+1),0) -> 0 | Y33: =IF(('Inputs & Assumptions'!$D$129+21)<='Inputs & Assumptions'!$C$13,INDEX('Inputs & Assumptions'!$D$70:$D$98,'Inputs & Assumptions'!$D$129+21+1),0) -> 0 | Z33: =IF(('Inputs & Assumptions'!$D$129+22)<='Inputs & Assumptions'!$C$13,INDEX('Inputs & Assumptions'!$D$70:$D$98,'Inputs & Assumptions'!$D$129+22+1),0) -> 0 | AA33: =IF(('Inputs & Assumptions'!$D$129+23)<='Inputs & Assumptions'!$C$13,INDEX('Inputs & Assumptions'!$D$70:$D$98,'Inputs & Assumptions'!$D$129+23+1),0) -> 0 | AB33: =IF(('Inputs & Assumptions'!$D$129+24)<='Inputs & Assumptions'!$C$13,INDEX('Inputs & Assumptions'!$D$70:$D$98,'Inputs & Assumptions'!$D$129+24+1),0) -> 0 | AC33: =IF(('Inputs & Assumptions'!$D$129+25)<='Inputs & Assumptions'!$C$13,INDEX('Inputs & Assumptions'!$D$70:$D$98,'Inputs & Assumptions'!$D$129+25+1),0) -> 0 | AD33: =IF(('Inputs & Assumptions'!$D$129+26)<='Inputs & Assumptions'!$C$13,INDEX('Inputs & Assumptions'!$D$70:$D$98,'Inputs & Assumptions'!$D$129+26+1),0) -> 0 | AE33: =IF(('Inputs & Assumptions'!$D$129+27)<='Inputs & Assumptions'!$C$13,INDEX('Inputs & Assumptions'!$D$70:$D$98,'Inputs & Assumptions'!$D$129+27+1),0) -> 0 | AF33: =IF(('Inputs & Assumptions'!$D$129+28)<='Inputs & Assumptions'!$C$13,INDEX('Inputs & Assumptions'!$D$70:$D$98,'Inputs & Assumptions'!$D$129+28+1),0) -> 0 | AG33: =IF(('Inputs & Assumptions'!$D$129+29)<='Inputs & Assumptions'!$C$13,INDEX('Inputs & Assumptions'!$D$70:$D$98,'Inputs & Assumptions'!$D$129+29+1),0) -> 0 | AH33: =IF(('Inputs & Assumptions'!$D$129+30)<='Inputs & Assumptions'!$C$13,INDEX('Inputs & Assumptions'!$D$70:$D$98,'Inputs & Assumptions'!$D$129+30+1),0) -> 0 | AI33: =IF(('Inputs & Assumptions'!$D$129+31)<='Inputs & Assumptions'!$C$13,INDEX('Inputs & Assumptions'!$D$70:$D$98,'Inputs & Assumptions'!$D$129+31+1),0) -> 0 | AJ33: =IF(('Inputs & Assumptions'!$D$129+32)<='Inputs & Assumptions'!$C$13,INDEX('Inputs & Assumptions'!$D$70:$D$98,'Inputs & Assumptions'!$D$129+32+1),0) -> 0 | AK33: =IF(('Inputs & Assumptions'!$D$129+33)<='Inputs & Assumptions'!$C$13,INDEX('Inputs & Assumptions'!$D$70:$D$98,'Inputs & Assumptions'!$D$129+33+1),0) -> 0 | AL33: =IF(('Inputs & Assumptions'!$D$129+34)<='Inputs & Assumptions'!$C$13,INDEX('Inputs & Assumptions'!$D$70:$D$98,'Inputs & Assumptions'!$D$129+34+1),0) -> 0 | AM33: =IF(('Inputs & Assumptions'!$D$129+35)<='Inputs & Assumptions'!$C$13,INDEX('Inputs & Assumptions'!$D$70:$D$98,'Inputs & Assumptions'!$D$129+35+1),0) -> 0 | AN33: =IF(('Inputs & Assumptions'!$D$129+36)<='Inputs & Assumptions'!$C$13,INDEX('Inputs & Assumptions'!$D$70:$D$98,'Inputs & Assumptions'!$D$129+36+1),0) -> 0
B34: ='Inputs & Assumptions'!$B$130 -> 29 | E34: =IF(('Inputs & Assumptions'!$D$130+1)<='Inputs & Assumptions'!$C$13,INDEX('Inputs & Assumptions'!$D$70:$D$98,'Inputs & Assumptions'!$D$130+1+1),0) -> 499783.2 | F34: =IF(('Inputs & Assumptions'!$D$130+2)<='Inputs & Assumptions'!$C$13,INDEX('Inputs & Assumptions'!$D$70:$D$98,'Inputs & Assumptions'!$D$130+2+1),0) -> 484789.71 | G34: =IF(('Inputs & Assumptions'!$D$130+3)<='Inputs & Assumptions'!$C$13,INDEX('Inputs & Assumptions'!$D$70:$D$98,'Inputs & Assumptions'!$D$130+3+1),0) -> 470246.02 | H34: =IF(('Inputs & Assumptions'!$D$130+4)<='Inputs & Assumptions'!$C$13,INDEX('Inputs & Assumptions'!$D$70:$D$98,'Inputs & Assumptions'!$D$130+4+1),0) -> 456138.64 | I34: =IF(('Inputs & Assumptions'!$D$130+5)<='Inputs & Assumptions'!$C$13,INDEX('Inputs & Assumptions'!$D$70:$D$98,'Inputs & Assumptions'!$D$130+5+1),0) -> 442454.48 | J34: =IF(('Inputs & Assumptions'!$D$130+6)<='Inputs & Assumptions'!$C$13,INDEX('Inputs & Assumptions'!$D$70:$D$98,'Inputs & Assumptions'!$D$130+6+1),0) -> 429180.84 | K34: =IF(('Inputs & Assumptions'!$D$130+7)<='Inputs & Assumptions'!$C$13,INDEX('Inputs & Assumptions'!$D$70:$D$98,'Inputs & Assumptions'!$D$130+7+1),0) -> 416305.42 | L34: =IF(('Inputs & Assumptions'!$D$130+8)<='Inputs & Assumptions'!$C$13,INDEX('Inputs & Assumptions'!$D$70:$D$98,'Inputs & Assumptions'!$D$130+8+1),0) -> 403816.25 | M34: =IF(('Inputs & Assumptions'!$D$130+9)<='Inputs & Assumptions'!$C$13,INDEX('Inputs & Assumptions'!$D$70:$D$98,'Inputs & Assumptions'!$D$130+9+1),0) -> 391701.77 | N34: =IF(('Inputs & Assumptions'!$D$130+10)<='Inputs & Assumptions'!$C$13,INDEX('Inputs & Assumptions'!$D$70:$D$98,'Inputs & Assumptions'!$D$130+10+1),0) -> 379950.71 | O34: =IF(('Inputs & Assumptions'!$D$130+11)<='Inputs & Assumptions'!$C$13,INDEX('Inputs & Assumptions'!$D$70:$D$98,'Inputs & Assumptions'!$D$130+11+1),0) -> 368552.19 | P34: =IF(('Inputs & Assumptions'!$D$130+12)<='Inputs & Assumptions'!$C$13,INDEX('Inputs & Assumptions'!$D$70:$D$98,'Inputs & Assumptions'!$D$130+12+1),0) -> 357495.63 | Q34: =IF(('Inputs & Assumptions'!$D$130+13)<='Inputs & Assumptions'!$C$13,INDEX('Inputs & Assumptions'!$D$70:$D$98,'Inputs & Assumptions'!$D$130+13+1),0) -> 346770.76 | R34: =IF(('Inputs & Assumptions'!$D$130+14)<='Inputs & Assumptions'!$C$13,INDEX('Inputs & Assumptions'!$D$70:$D$98,'Inputs & Assumptions'!$D$130+14+1),0) -> 336367.63 | S34: =IF(('Inputs & Assumptions'!$D$130+15)<='Inputs & Assumptions'!$C$13,INDEX('Inputs & Assumptions'!$D$70:$D$98,'Inputs & Assumptions'!$D$130+15+1),0) -> 326276.61 | T34: =IF(('Inputs & Assumptions'!$D$130+16)<='Inputs & Assumptions'!$C$13,INDEX('Inputs & Assumptions'!$D$70:$D$98,'Inputs & Assumptions'!$D$130+16+1),0) -> 316488.31 | U34: =IF(('Inputs & Assumptions'!$D$130+17)<='Inputs & Assumptions'!$C$13,INDEX('Inputs & Assumptions'!$D$70:$D$98,'Inputs & Assumptions'!$D$130+17+1),0) -> 306993.66 | V34: =IF(('Inputs & Assumptions'!$D$130+18)<='Inputs & Assumptions'!$C$13,INDEX('Inputs & Assumptions'!$D$70:$D$98,'Inputs & Assumptions'!$D$130+18+1),0) -> 9926128.3 | W34: =IF(('Inputs & Assumptions'!$D$130+19)<='Inputs & Assumptions'!$C$13,INDEX('Inputs & Assumptions'!$D$70:$D$98,'Inputs & Assumptions'!$D$130+19+1),0) -> 0 | X34: =IF(('Inputs & Assumptions'!$D$130+20)<='Inputs & Assumptions'!$C$13,INDEX('Inputs & Assumptions'!$D$70:$D$98,'Inputs & Assumptions'!$D$130+20+1),0) -> 0 | Y34: =IF(('Inputs & Assumptions'!$D$130+21)<='Inputs & Assumptions'!$C$13,INDEX('Inputs & Assumptions'!$D$70:$D$98,'Inputs & Assumptions'!$D$130+21+1),0) -> 0 | Z34: =IF(('Inputs & Assumptions'!$D$130+22)<='Inputs & Assumptions'!$C$13,INDEX('Inputs & Assumptions'!$D$70:$D$98,'Inputs & Assumptions'!$D$130+22+1),0) -> 0 | AA34: =IF(('Inputs & Assumptions'!$D$130+23)<='Inputs & Assumptions'!$C$13,INDEX('Inputs & Assumptions'!$D$70:$D$98,'Inputs & Assumptions'!$D$130+23+1),0) -> 0 | AB34: =IF(('Inputs & Assumptions'!$D$130+24)<='Inputs & Assumptions'!$C$13,INDEX('Inputs & Assumptions'!$D$70:$D$98,'Inputs & Assumptions'!$D$130+24+1),0) -> 0 | AC34: =IF(('Inputs & Assumptions'!$D$130+25)<='Inputs & Assumptions'!$C$13,INDEX('Inputs & Assumptions'!$D$70:$D$98,'Inputs & Assumptions'!$D$130+25+1),0) -> 0 | AD34: =IF(('Inputs & Assumptions'!$D$130+26)<='Inputs & Assumptions'!$C$13,INDEX('Inputs & Assumptions'!$D$70:$D$98,'Inputs & Assumptions'!$D$130+26+1),0) -> 0 | AE34: =IF(('Inputs & Assumptions'!$D$130+27)<='Inputs & Assumptions'!$C$13,INDEX('Inputs & Assumptions'!$D$70:$D$98,'Inputs & Assumptions'!$D$130+27+1),0) -> 0 | AF34: =IF(('Inputs & Assumptions'!$D$130+28)<='Inputs & Assumptions'!$C$13,INDEX('Inputs & Assumptions'!$D$70:$D$98,'Inputs & Assumptions'!$D$130+28+1),0) -> 0 | AG34: =IF(('Inputs & Assumptions'!$D$130+29)<='Inputs & Assumptions'!$C$13,INDEX('Inputs & Assumptions'!$D$70:$D$98,'Inputs & Assumptions'!$D$130+29+1),0) -> 0 | AH34: =IF(('Inputs & Assumptions'!$D$130+30)<='Inputs & Assumptions'!$C$13,INDEX('Inputs & Assumptions'!$D$70:$D$98,'Inputs & Assumptions'!$D$130+30+1),0) -> 0 | AI34: =IF(('Inputs & Assumptions'!$D$130+31)<='Inputs & Assumptions'!$C$13,INDEX('Inputs & Assumptions'!$D$70:$D$98,'Inputs & Assumptions'!$D$130+31+1),0) -> 0 | AJ34: =IF(('Inputs & Assumptions'!$D$130+32)<='Inputs & Assumptions'!$C$13,INDEX('Inputs & Assumptions'!$D$70:$D$98,'Inputs & Assumptions'!$D$130+32+1),0) -> 0 | AK34: =IF(('Inputs & Assumptions'!$D$130+33)<='Inputs & Assumptions'!$C$13,INDEX('Inputs & Assumptions'!$D$70:$D$98,'Inputs & Assumptions'!$D$130+33+1),0) -> 0 | AL34: =IF(('Inputs & Assumptions'!$D$130+34)<='Inputs & Assumptions'!$C$13,INDEX('Inputs & Assumptions'!$D$70:$D$98,'Inputs & Assumptions'!$D$130+34+1),0) -> 0 | AM34: =IF(('Inputs & Assumptions'!$D$130+35)<='Inputs & Assumptions'!$C$13,INDEX('Inputs & Assumptions'!$D$70:$D$98,'Inputs & Assumptions'!$D$130+35+1),0) -> 0 | AN34: =IF(('Inputs & Assumptions'!$D$130+36)<='Inputs & Assumptions'!$C$13,INDEX('Inputs & Assumptions'!$D$70:$D$98,'Inputs & Assumptions'!$D$130+36+1),0) -> 0
B35: ='Inputs & Assumptions'!$B$131 -> 30 | E35: =IF(('Inputs & Assumptions'!$D$131+1)<='Inputs & Assumptions'!$C$13,INDEX('Inputs & Assumptions'!$D$70:$D$98,'Inputs & Assumptions'!$D$131+1+1),0) -> 499783.2 | F35: =IF(('Inputs & Assumptions'!$D$131+2)<='Inputs & Assumptions'!$C$13,INDEX('Inputs & Assumptions'!$D$70:$D$98,'Inputs & Assumptions'!$D$131+2+1),0) -> 484789.71 | G35: =IF(('Inputs & Assumptions'!$D$131+3)<='Inputs & Assumptions'!$C$13,INDEX('Inputs & Assumptions'!$D$70:$D$98,'Inputs & Assumptions'!$D$131+3+1),0) -> 470246.02 | H35: =IF(('Inputs & Assumptions'!$D$131+4)<='Inputs & Assumptions'!$C$13,INDEX('Inputs & Assumptions'!$D$70:$D$98,'Inputs & Assumptions'!$D$131+4+1),0) -> 456138.64 | I35: =IF(('Inputs & Assumptions'!$D$131+5)<='Inputs & Assumptions'!$C$13,INDEX('Inputs & Assumptions'!$D$70:$D$98,'Inputs & Assumptions'!$D$131+5+1),0) -> 442454.48 | J35: =IF(('Inputs & Assumptions'!$D$131+6)<='Inputs & Assumptions'!$C$13,INDEX('Inputs & Assumptions'!$D$70:$D$98,'Inputs & Assumptions'!$D$131+6+1),0) -> 429180.84 | K35: =IF(('Inputs & Assumptions'!$D$131+7)<='Inputs & Assumptions'!$C$13,INDEX('Inputs & Assumptions'!$D$70:$D$98,'Inputs & Assumptions'!$D$131+7+1),0) -> 416305.42 | L35: =IF(('Inputs & Assumptions'!$D$131+8)<='Inputs & Assumptions'!$C$13,INDEX('Inputs & Assumptions'!$D$70:$D$98,'Inputs & Assumptions'!$D$131+8+1),0) -> 403816.25 | M35: =IF(('Inputs & Assumptions'!$D$131+9)<='Inputs & Assumptions'!$C$13,INDEX('Inputs & Assumptions'!$D$70:$D$98,'Inputs & Assumptions'!$D$131+9+1),0) -> 391701.77 | N35: =IF(('Inputs & Assumptions'!$D$131+10)<='Inputs & Assumptions'!$C$13,INDEX('Inputs & Assumptions'!$D$70:$D$98,'Inputs & Assumptions'!$D$131+10+1),0) -> 379950.71 | O35: =IF(('Inputs & Assumptions'!$D$131+11)<='Inputs & Assumptions'!$C$13,INDEX('Inputs & Assumptions'!$D$70:$D$98,'Inputs & Assumptions'!$D$131+11+1),0) -> 368552.19 | P35: =IF(('Inputs & Assumptions'!$D$131+12)<='Inputs & Assumptions'!$C$13,INDEX('Inputs & Assumptions'!$D$70:$D$98,'Inputs & Assumptions'!$D$131+12+1),0) -> 357495.63 | Q35: =IF(('Inputs & Assumptions'!$D$131+13)<='Inputs & Assumptions'!$C$13,INDEX('Inputs & Assumptions'!$D$70:$D$98,'Inputs & Assumptions'!$D$131+13+1),0) -> 346770.76 | R35: =IF(('Inputs & Assumptions'!$D$131+14)<='Inputs & Assumptions'!$C$13,INDEX('Inputs & Assumptions'!$D$70:$D$98,'Inputs & Assumptions'!$D$131+14+1),0) -> 336367.63 | S35: =IF(('Inputs & Assumptions'!$D$131+15)<='Inputs & Assumptions'!$C$13,INDEX('Inputs & Assumptions'!$D$70:$D$98,'Inputs & Assumptions'!$D$131+15+1),0) -> 326276.61 | T35: =IF(('Inputs & Assumptions'!$D$131+16)<='Inputs & Assumptions'!$C$13,INDEX('Inputs & Assumptions'!$D$70:$D$98,'Inputs & Assumptions'!$D$131+16+1),0) -> 316488.31 | U35: =IF(('Inputs & Assumptions'!$D$131+17)<='Inputs & Assumptions'!$C$13,INDEX('Inputs & Assumptions'!$D$70:$D$98,'Inputs & Assumptions'!$D$131+17+1),0) -> 306993.66 | V35: =IF(('Inputs & Assumptions'!$D$131+18)<='Inputs & Assumptions'!$C$13,INDEX('Inputs & Assumptions'!$D$70:$D$98,'Inputs & Assumptions'!$D$131+18+1),0) -> 9926128.3 | W35: =IF(('Inputs & Assumptions'!$D$131+19)<='Inputs & Assumptions'!$C$13,INDEX('Inputs & Assumptions'!$D$70:$D$98,'Inputs & Assumptions'!$D$131+19+1),0) -> 0 | X35: =IF(('Inputs & Assumptions'!$D$131+20)<='Inputs & Assumptions'!$C$13,INDEX('Inputs & Assumptions'!$D$70:$D$98,'Inputs & Assumptions'!$D$131+20+1),0) -> 0 | Y35: =IF(('Inputs & Assumptions'!$D$131+21)<='Inputs & Assumptions'!$C$13,INDEX('Inputs & Assumptions'!$D$70:$D$98,'Inputs & Assumptions'!$D$131+21+1),0) -> 0 | Z35: =IF(('Inputs & Assumptions'!$D$131+22)<='Inputs & Assumptions'!$C$13,INDEX('Inputs & Assumptions'!$D$70:$D$98,'Inputs & Assumptions'!$D$131+22+1),0) -> 0 | AA35: =IF(('Inputs & Assumptions'!$D$131+23)<='Inputs & Assumptions'!$C$13,INDEX('Inputs & Assumptions'!$D$70:$D$98,'Inputs & Assumptions'!$D$131+23+1),0) -> 0 | AB35: =IF(('Inputs & Assumptions'!$D$131+24)<='Inputs & Assumptions'!$C$13,INDEX('Inputs & Assumptions'!$D$70:$D$98,'Inputs & Assumptions'!$D$131+24+1),0) -> 0 | AC35: =IF(('Inputs & Assumptions'!$D$131+25)<='Inputs & Assumptions'!$C$13,INDEX('Inputs & Assumptions'!$D$70:$D$98,'Inputs & Assumptions'!$D$131+25+1),0) -> 0 | AD35: =IF(('Inputs & Assumptions'!$D$131+26)<='Inputs & Assumptions'!$C$13,INDEX('Inputs & Assumptions'!$D$70:$D$98,'Inputs & Assumptions'!$D$131+26+1),0) -> 0 | AE35: =IF(('Inputs & Assumptions'!$D$131+27)<='Inputs & Assumptions'!$C$13,INDEX('Inputs & Assumptions'!$D$70:$D$98,'Inputs & Assumptions'!$D$131+27+1),0) -> 0 | AF35: =IF(('Inputs & Assumptions'!$D$131+28)<='Inputs & Assumptions'!$C$13,INDEX('Inputs & Assumptions'!$D$70:$D$98,'Inputs & Assumptions'!$D$131+28+1),0) -> 0 | AG35: =IF(('Inputs & Assumptions'!$D$131+29)<='Inputs & Assumptions'!$C$13,INDEX('Inputs & Assumptions'!$D$70:$D$98,'Inputs & Assumptions'!$D$131+29+1),0) -> 0 | AH35: =IF(('Inputs & Assumptions'!$D$131+30)<='Inputs & Assumptions'!$C$13,INDEX('Inputs & Assumptions'!$D$70:$D$98,'Inputs & Assumptions'!$D$131+30+1),0) -> 0 | AI35: =IF(('Inputs & Assumptions'!$D$131+31)<='Inputs & Assumptions'!$C$13,INDEX('Inputs & Assumptions'!$D$70:$D$98,'Inputs & Assumptions'!$D$131+31+1),0) -> 0 | AJ35: =IF(('Inputs & Assumptions'!$D$131+32)<='Inputs & Assumptions'!$C$13,INDEX('Inputs & Assumptions'!$D$70:$D$98,'Inputs & Assumptions'!$D$131+32+1),0) -> 0 | AK35: =IF(('Inputs & Assumptions'!$D$131+33)<='Inputs & Assumptions'!$C$13,INDEX('Inputs & Assumptions'!$D$70:$D$98,'Inputs & Assumptions'!$D$131+33+1),0) -> 0 | AL35: =IF(('Inputs & Assumptions'!$D$131+34)<='Inputs & Assumptions'!$C$13,INDEX('Inputs & Assumptions'!$D$70:$D$98,'Inputs & Assumptions'!$D$131+34+1),0) -> 0 | AM35: =IF(('Inputs & Assumptions'!$D$131+35)<='Inputs & Assumptions'!$C$13,INDEX('Inputs & Assumptions'!$D$70:$D$98,'Inputs & Assumptions'!$D$131+35+1),0) -> 0 | AN35: =IF(('Inputs & Assumptions'!$D$131+36)<='Inputs & Assumptions'!$C$13,INDEX('Inputs & Assumptions'!$D$70:$D$98,'Inputs & Assumptions'!$D$131+36+1),0) -> 0
